Workbook

Sheet Index
A1: ID | B1: Card | C1: Type | D1: Stage / Rarity (trainer) | E1: Remaining Evo | F1: Deck Feature Tier | G1: Opener Archetype | H1: Pressure | I1: Wants | J1: Possible CPU Deck Block? | K1: Included in opp Deck? | L1: Gated Until (promo only) | N1: Feature Tier Key
A2: base1-1 | B2: Alakazam | C2: P | D2: 2 | F2: 2.5 | H2: AP, SL | I2: Tanks on the bench to move damage to with its pokemon power. It's a competent fighter with its ability to confuse but leans toward prefering the bench. If it's in the active spot itself or if a valuable ally is, it likes to move damage counters off the active one onto a tank on the bench. It prefers decks with several high-HP tank pokemon like Kangaskhan, Chansey, and Snorlax | K2: TRUE | N2: Not shown | O2: Not worth noting
A3: base1-10 | B3: Mewtwo | C3: P | D3: b | E3: n | F3: 0.5 | G3: f | I3: Its damage from Psychic scales with opponent energy, so it likes to come in after there's already a powered-up opponent. The bot should be able to do the math in terms of how much damage Psychic would do to the opponent's active pokemon every time a new pokemon has to be promoted to active. I can't think of any situation Barrier would be used. It requires an energy funnel in order to survive long enough for the next energy funnel, all while the enegy funnel prevents you from powering anything up. | K3: TRUE | N3: 1 | O3: Strategic Opener / Tank / Other utility
A4: base1-100 | B4: E Energy | C4: Energy | K4: TRUE | N4: 2 | O4: Secondary Feature
A5: base1-101 | B5: P Energy | C5: Energy | K5: TRUE | N5: 3 | O5: Primary Feature
A6: base1-102 | B6: W Energy | C6: Energy | K6: TRUE | N6: 4 | O6: Elite Feature
A7: base1-11 | B7: Nidoking | C7: G | D7: 2 | F7: 3 | H7: SL | I7: Both its moves cost the same and both are worth using, but it usually wants to start with Toxic due to the extra poision damage before switching to Thrash, as the extra poision damage on top of Toxic's natural damage equal the 50/50 damage potential of Thrash. Once the opponent is poisoned, Toxic cannot add additional poison damage, so Thrash becomes more valuable. | K7: TRUE
A8: base1-12 | B8: Ninetales | C8: R | D8: 1 | E8: n | F8: 2 | H8: HD | I8: To come in after it's ready to use Fire Blast, and to never be required to choose between Lure and nothing. Fire Blast wants an energy funnel but does high damage, so it requires some maintenance and stops bench growth every turn it attacks, but can one-shot many opponents. Lure does have uses, such as removing a dangerous pokemon and replacing it with one that is not ready to attack and is not able to retreat. | K8: TRUE
A9: base1-13 | B9: Poliwrath | C9: W | D9: 2 | F9: 3 | H9: ED | I9: An Attack Choice, as both attacks are valid. Whirlpool is preferred due to the very high value of discarding opponent energy cards, but Water Gun can be Over-Attached into doing higher damage. Water Gun should be used when it results in a kill that Whrilpool wouldn't, and the bot should be willing to add that fifth energy to do so | K9: TRUE | N9: Tier ranking is only for last of evolution line and select useful others. Partially based in subjectivity and play experience
A10: base1-14 | B10: Raichu | C10: E | D10: 1 | E10: n | F10: 2 | H10: WP, HD | I10: To use Agility when Thunder wouldn't kill, or when Thunder risks a self-kill that isn't worthwhile. Does need some degree of Kamakaze Timing. Agility buys turns through damage *and status* denial on a coin flip, while Thunder risks 30 self-dmg on a coin flip. | K10: TRUE | N10: Remaining Evo only applies to Basic and Stage 1. All stage 2 are assumed to not have evolutions remaining
A11: base1-15 | B11: Venusaur | C11: G | D11: 2 | F11: 3 | H11: BG, HD | I11: Does not necessarily prefer the bench despite its pokemon power, but doesn't mind it there either. Uses Energy Trans to shift energy from bench pokemon to whatever is active for an instant power up, as long as the active pokemon isn't just going to die and lose it all right away. While the newly powered up active pokemon (which could be Venusaur itself) fights, its owner can slowly re-power the bench cards they stripped energy from | K11: TRUE | N11: Labels here are used for the lookup table on the deck tabs, but we can possibly get utility from it as well with the AI
A12: base1-16 | B12: Zapdos | C12: E | D12: b | E12: n | F12: 1.5 | G12: h | H12: HD | I12: To deal high damage and die rather quickly. Prefers to go down fighting over retreat, though not by self-kill. Thunder is the preferred attack until Zapdos looks like it will die on the opponent's next turn, or it risks a self-kill on this turn. In those cases, Thunderbolt should be used. | K12: TRUE | N12: Trainer rarity is used to gauge usefulness in decks
A13: base1-17 | B13: Beedrill | C13: G | D13: 2 | F13: 3 | H13: SL | I13: To use Poison Sting first, and then Twineedle when the opponent is already poisoned. Poison Sting is preferred again when a guaranteed 40 damage or less is needed, rather than gambled on Twineedle's coin flip | K13: TRUE | N13: Half steps are used. Consider those candidates for the next tier with proper support
A14: base1-18 | B14: Dragonair | C14: C | D14: 1 | E14: y | F14: 1 | H14: ED | I14: Is not afraid to fight even though it's not fully evolved, as long as Hyper Beam can be used and the opponent is unable to powerup for a kill because of it. Slam use is rare due to the value of discarding an opponent energy. | K14: TRUE | N14: Opener archetypes per card are tracked. I don't know if we'll need these but it's cheap to do while going through the set anyway. Unlabeled ones should be deferred as openers when possible, but usually committed to once they're in. Based on battle utility, not whether they can evolve, etc
A15: base1-19 | B15: Dugtrio | C15: F | D15: 1 | E15: n | F15: 2 | H15: HD | I15: Slash is preferred unless Earthquake would kill and Slash wouldn't. The damage to its user's own bench should be weighed against Earthquake | K15: TRUE | N15: Numbers added to the end of names is for differentiation purposes between cards with the same name. Ex: B2 means base2/Jungle
A16: base1-2 | B16: Blastoise | C16: W | D16: 2 | F16: 4 | H16: HD | I16: 5-ish extra W energy in deck, Over-Attach 2 extra energy for Hydro Pump's max potential, which is worth it. Loves to fight. When it evolves, its user should immediately use Rain Dance to dump as many energy cards on their pokemon as those pokemon require, prioritizing the ones currently fighting and Blastoise itself | K16: TRUE | N16: Nonholo duplicates are tagged with NH after their name. It helps the lookup table
A17: base1-20 | B17: Electabuzz | C17: E | D17: b | E17: n | F17: 1 | G17: a | H17: SL | I17: Loves to open. Chooses between its moves based on the quickest path to a kill (assuming Thunderpunch's guaranteed 30 damage rather than an average), but prefers Thundershock first when it doesn't lose it a turn by doing so. | K17: TRUE | N17: Trainer Function Key, Pressure, and Wants were added at the advice of #15 and haven't been fully applied retroactively yet
A18: base1-21 | B18: Electrode | C18: E | D18: 1 | E18: n | F18: 2 | J18: y | K18: TRUE | N18: Opener archetypes are only applied to basic pokemon here
A19: base1-22 | B19: Pidgeotto | C19: C | D19: 1 | E19: y | H19: PC | I19: Almost always uses Whirlwind to throw opponents around the play area and doens't even power up Mirror Move unless doing so to prepare for evolution. Mirror Move should only be used when it would result in a kill that Whirlwind wouldn't, and the bot should be willing to spend the energy at the time to do so rather than in advance | K19: TRUE
A20: base1-23 | B20: Arcanine | C20: R | D20: 1 | E20: n | F20: 2 | H20: HD | I20: Both attacks do high damage and both have drawbacks. Flamethrower requires an energy funnel but should be the default due to Take Down's self-damage. However, Take Down should stay powered up and ready to go for when it's needed, meaning the bot should not want to use even Flamethrower until Arcanine has four energies attached, as it requires that constant funnel that would make Take Down unavailable if used at three energies | K20: TRUE
A21: base1-24 | B21: Charmeleon | C21: R | D21: 1 | E21: y | I21: Does decent damage but does not want to fight. Prefers to sit on the bench and pre-Over-Attach energies for an evolution to Charizard, even when Charizard isn't in the hand. Flamethrower does good damage but requires an energy funnel on the card that you want to evolve into the biggest energy funnel of all, so it's best avoided unless necessary. A Charmeleon that ends up fighting and having to use Flamethrower should almost be written off for evolution and used only as a fodder attacker. | K21: TRUE | N21: Opener Archetype Key:
A22: base1-25 | B22: Dewgong | C22: W | D22: 1 | E22: n | F22: 2 | H22: SL | I22: Classic Attack Choice between Aurora Beam and Ice Beam. Punches above its weight and doesn't retreat | K22: TRUE
A23: base1-26 | B23: Dratini | C23: C | D23: b | E23: y | K23: TRUE | N23: A | O23: Attack Opener. Openers that use stalling attacks, low damage attacks w/ high HP, or build up to damage quickly without evo. Should be weighted high for starter selection or stalling jobs, lower for retreat. Can sometimes also build up to stronger moves while stalling. Ex: Onix, Jynx
A24: base1-27 | B24: Farfetch'd | C24: C | D24: b | E24: n | G24: a | I24: Likes to open, and its only useful role ever is to open, and even that is not very useful. Should use Leek Slap and then be left to die while other things are powered up, unless desperate enough to need to power up Pot Smash. Our autobuilder should probably weight this one rather low | K24: TRUE | N24: T | O24: Tanks. Usually used as openers but attacks are usually defensive stalling or card drawing. Usually weighted higher than other openers. Ex: Chansey
A25: base1-28 | B25: Growlithe | C25: R | D25: b | E25: y | I25: Low-weight opener. Arcanine's high energy cost makes it prefer the bench | K25: TRUE | N25: F | O25: Fallback opener. Good cheap attack option during game, not a main weapon but capable of bridging gaps. Good opener if other options aren't available. Ex: Mewtwo (1-10)
A26: base1-29 | B26: Haunter | C26: P | D26: 1 | E26: y | H26: SL | I26: Hypnosis + Dream Eater is a Setup Turn combo but Dream Eater only has a 1/4 chance of being successful before even before you factor in the opponent's chance to wake up by evolving. Therefore it doesn't want to fight, and should be used only as a staller when it does. It's still useful to keep at 2 energies rather than Dream Eater being a reactive energy-add at the time it's needed, due to Gengar's attack needing 3 energies. If kept at 2 while Haunter, it can evolve and attack the same turn a Gengar is drawn (as long as its player has the extra energy in hand) | K26: TRUE | N26: E | O26: Evo openerer. Lower weight when it comes to opening due to evolution possibility but does have stalling moves or can do damage, and should be prioritized when stalling is needed and no other options available. Higher priority if evolution exists in hand and is realistic to survive long enough to evolve. Ex: Squirtle
A27: base1-3 | B27: Chansey | C27: C | D27: b | E27: n | F27: 1 | G27: t | H27: WP | I27: To work as a tank or staller, hiding behind Scrunch and rarely ever retreating or using Double-Edge | K27: TRUE | N27: N | O27: Avoid using as an opener when possible. Should be weighted lower than the baseline and possibly even switched out when other options become available. Ex: Magikarp
A28: base1-30 | B28: Ivysaur | C28: G | D28: 1 | E28: y | H28: SL | I28: A middle stage that doesn't mind fighting due to Poisonpowder's guaranteed poisoning. If it evolved from Bulbasaur in the active spot, then it's already in good position to deal damage due to Bulbasaur's attack costing 2 energies, and both of Ivysaur's costing 3, meaning Bulbasaur can be evolved fluidly without being pre-loaded while fighting | K28: TRUE | N28: H | O28: HP staller. A high HP card that would normally be used as an attacker is substituted as a tank due to lack of other options. Committed to once in, not retreated or powered up unless smart to do so. A complete sacrifice. Ex: Zapdos
A29: base1-31 | B29: Jynx | C29: P | D29: b | E29: n | F29: 0.5 | G29: a | I29: Meditate is preferred and can be extremely effective against much stronger (but damaged) pokemon. Loves to start and use Doubleslap while powering up Meditate, or might choose to tank without only Doubleslap while something more valuable is powered up on the bench instead. Meditate's potential damage should always be considered by the bot when choosing something to promote | K29: TRUE
A30: base1-32 | B30: Kadabra | C30: P | D30: 1 | E30: y | H30: HD | I30: Super Psy does high damage for what it is, and even outdoes its own evolution's damage. The evolution is still preferred in most situations though due to its pokemon power and chance to confuse. Recover should never be used. It drains an energy from a pokemon that wants to stay at 3 energies at all times. Getting in a 50 dmg hit and dying is almost always preferable to recovery or retreat | K30: TRUE
A31: base1-33 | B31: Kakuna | C31: G | D31: 1 | E31: y | H31: SL | I31: Is a good fighting mid-stage that likes to meddle with Poisonpowder. Damage and chance to poison is almost always preferable to a 50/50 chance at damage prevention with Stiffen | K31: TRUE
A32: base1-34 | B32: Machoke | C32: F | D32: 1 | E32: y | I32: A tough card to use because one attack's damage shrinks very quickly with damage taken, and the other deals self-damage. Can deal high damage to an opponent quickly but can become useless after that. Prefers to evolve on the bench unless a quick cheap hit is needed, at which time it does have a use | K32: TRUE | N32: Trainer Function Key (uses the Deck Feature Tier column):
A33: base1-35 | B33: Magikarp | C33: W | D33: b | E33: y | G33: n | I33: If this guy is fighting, you're in a bad spot | K33: TRUE | N33: D | O33: Draw. Cards are picked up from the top of the deck
A34: base1-36 | B34: Magmar | C34: R | D34: b | E34: n | G34: f | H34: HD | I34: Flamethrower does good damage but requires an energy funnel, and this is not a pokemon you want consuming all your energies. Use Fire Punch as default but be ready for Flamethrower when needed. Low HP means it dies rather quickly. | K34: TRUE | N34: S | O34: Search. Search for a card in the deck
A35: base1-37 | B35: Nidorino | C35: G | D35: 1 | E35: y | I35: Horn Drill preferred, Double Kick only when it can't be afforded | K35: TRUE | N35: P | O35: Disruption. Interferes with the opponent or the status of the board
A36: base1-38 | B36: Poliwhirl | C36: W | D36: 1 | E36: y | I36: Amnesia can block an opponent's damage before Doubleslap has the energy to be used or if Poliwhirl needs to survive to the next turn to evolve. Otherwise Doubleslap is always preferred | K36: TRUE | N36: H | O36: Heal. Removes damage from Pokemon
A37: base1-39 | B37: Porygon | C37: C | D37: b | E37: n | G37: a | I37: To use Conversion 2 to stay resistant to its opponent while it stalls as long as it can before death. Conversion 1 should only be used when Conversion 2 can't be afforded, and when it is, the bot should shift the opponent's weakness the type of their own current strongest (non-colorless) bench pokemon | K37: TRUE | N37: M | O37: Movement. Moves someone from somewhere to somewhere
A38: base1-4 | B38: Charizard | C38: R | D38: 2 | F38: 4 | H38: HD | I38: A deck where four DCE replace four R energies, and to be pre-Over-Attached with as many energies as possibe before being sent into battle. Even Charmeleon should be preloaded on the bench before evolution in anticipation of this card's high Energy Funel costs. | K38: TRUE | N38: R | O38: Recovery. Removes status conditions
A39: base1-40 | B39: Raticate | C39: C | D39: 1 | E39: n | I39: Bite is primary, and Super Fang usually isn't worth it. Power up beyond Bite only if there are no better options for that energy | K39: TRUE | N39: E | O39: Exclude from baseline. Doesn't fall in with the other functions but should be excluded from baseline readings
A40: base1-41 | B40: Seel | C40: W | D40: b | E40: y | K40: TRUE
A41: base1-42 | B41: Wartortle | C41: W | D41: 1 | E41: y | I41: Only withdraws when it can't use Bite. Doesn't mind fighting while it waits to evolve | K41: TRUE
A42: base1-43 | B42: Abra | C42: P | D42: b | E42: y | G42: e | H42: SL | K42: TRUE
A43: base1-44 | B43: Bulbasaur | C43: G | D43: b | E43: y | I43: To open if starting with an Ivysaur in hand | K43: TRUE | N43: Pressure
A44: base1-45 | B44: Caterpie | C44: G | D44: b | E44: y | G44: e | H44: SL | K44: TRUE | N44: ED | O44: Energy Denial - Strips the investement you already made
A45: base1-46 | B45: Charmander | C45: R | D45: b | E45: y | I45: Ember is an energy funnel on a card whose evolutions also demand energy funnels, so a Charmander forced to use it should almost be written off for evolution if there are other options | K45: TRUE | N45: BD | O45: Bench Damage - Your cards aren't safe
A46: base1-47 | B46: Diglett | C46: F | D46: b | E46: y | G46: e | I46: To open when a better option isn't available due to Mud Slap's high damage for that stage | K46: TRUE | N46: PC | O46: Position Control - You fight with the wrong pokemon
A47: base1-48 | B47: Doduo | C47: C | D47: b | E47: y | G47: a | K47: TRUE | N47: SL | O47: Status Lock - It takes your turns away
A48: base1-49 | B48: Drowzee | C48: P | D48: b | E48: y | G48: a | H48: SL | I48: Pound only used when Confuse Ray can't be | K48: TRUE | N48: HT | O48: Hand/Trainer Denial - Your outs stop arriving
A49: base1-5 | B49: Clefairy | C49: C | D49: b | E49: y | F49: 0.5 | H49: SL | I49: Prefers to evolve on the bench. Sing is only a 25% chance to cost the opponent an attack and Metronome takes up a turn before the Copied Effect can be used, during which time Clefairy would likely die (if copying any move worthwhile). | K49: TRUE | N49: WP | O49: Wall/Prevention - Your damage stops landing
A50: base1-50 | B50: Gastly | C50: P | D50: b | E50: y | I50: Sleeping gas only has a 25% chance to cost the opponent a turn, so this pokemon probably shouldn't be used at all. Destiny Bond does become useful if it's in the active spot and about to die, though it requires an energy funnel and any opponent (including the bot) should weigh the option of just not attacking for that turn, as Gastly would need another Energy Funneled in to try it again. | K50: TRUE | N50: AP | O50: Attrition/Recovery - It refuses to run out
A51: base1-51 | B51: Koffing | C51: G | D51: b | E51: y | G51: a | H51: SL | I51: Loves to open and wreaks havok when it does. Foul Gas guarantees one of two different status conditions | K51: TRUE | N51: HD | O51: High Damage - Hits you harder than you can absorb
A52: base1-52 | B52: Machop | C52: F | D52: b | E52: y | G52: e | I52: To open as a solid attacker. Low Kick deals high damage for low energy and Machop has high HP relative to other evolving basics | K52: TRUE | N52: BG | O52: Bench Growth - Your opponent is able to build up their reserves more quickly. Definition expanded to include drawing cards and skipping turns via quick evolution or extra energy attachments
A53: base1-53 | B53: Magnemite | C53: E | D53: b | E53: y | G53: e | H53: SL, HD, BD | I53: Thunder Wave is primary and tries to paralyze, while Selfdestruct should be a Kamakaze Timer that also weighs the damage to both players' benches | K53: TRUE
A54: base1-54 | B54: Metapod | C54: G | D54: 1 | E54: y | H54: SL | I54: Stun Spore is always preferred, and there are extremely few situations Stiffen is used due to the 50/50 damage block chance. For the same energy cost and same 50/50 chance, Stun Spore can cost a turn through paralysis while dealing 20 guaranteed damage | K54: TRUE | N54: Order matters for pokemon with multiple pressures listed. The first has priority
A55: base1-55 | B55: Nidoran ♂ | C55: G | D55: 1 | E55: y | G55: a | I55: To open but its effectiveness depends on Coin Luck | K55: TRUE
A56: base1-56 | B56: Onix | C56: F | D56: b | E56: n | G56: t | I56: Loves to open as a tank. Never powers up to Harden because it doesn't need it. Rock Throw is a good, cheap, steady 10 dmg to do each turn | K56: TRUE
A57: base1-57 | B57: Pidgey | C57: C | D57: b | E57: y | H57: PC | I57: Likes the bench, but plays position control when it's forced to attack | K57: TRUE | N57: Promo cards become available in *all* packs after the one it's gated until
A58: base1-58 | B58: Pikachu | C58: E | D58: b | E58: y | I58: Thunder Jolt is the preferred attack but risks self-damage toward a low-HP pokemon. Prefers to evolve on the bench. There are about a thousand Pikachu variants and our autobuilder should prefer most of the others over this one. | K58: TRUE | N58: Promo Card gate order contains judgement calls for balance and is not always released in order for us
A59: base1-59 | B59: Poliwag | C59: W | D59: b | E59: y | G59: e | I59: Wants to Over-Attach two energies for Water Gun while fighting, which puts in a good position for evolution | K59: TRUE | N59: Promo suffexes are for differentiation in the spreadsheet, not necessarily in-game
A60: base1-6 | B60: Gyarados | C60: W | D60: 1 | E60: n | F60: 2.5 | H60: SL | I60: Magikarp kept safe enough to evolve | K60: TRUE
A61: base1-60 | B61: Ponyta | C61: R | D61: b | E61: y | G61: e | I61: An okay starter if Rapidash is in hand | K61: TRUE | N61: Promo Suffix Key
A62: base1-61 | B62: Rattata | C62: C | D62: b | E62: y | K62: TRUE | N62: GP | O62: General Promo release
A63: base1-62 | B63: Sandshrew | C63: F | D63: b | E63: y | G63: a | H63: WP | K63: TRUE | N63: MS | O63: Movie Stamp - Special visual stamp from movie release
A64: base1-63 | B64: Squirtle | C64: W | D64: b | E64: y | G64: e | H64: SL | I64: Likes to open if its deck contains Blastoise, as it's a very good line to evolve while fighting at the start of a match | K64: TRUE | N64: CH | O64: Cosmos Holo - A special holo promo card
A65: base1-64 | B65: Starmie | C65: W | D65: 1 | E65: n | F65: 1.5 | H65: SL | I65: Recover needs an Energy Funnel and should be avoided. See Kadabra entry for more detail | K65: TRUE
A66: base1-65 | B66: Staryu | C66: W | D66: b | E66: y | K66: TRUE
A67: base1-66 | B67: Tangela | C67: G | D67: b | E67: n | G67: f | H67: SL | I67: Poisonpowder first, Bind once poisoned or before it can be afforded. See Nidoking for reasoning | K67: TRUE
A68: base1-67 | B68: Voltorb | C68: E | D68: b | E68: y | K68: TRUE | N68: Ancient Mew, which is unnumbered and not part of any set, has been given a number and added to the Promo set by me. This might be done for some other unnumbered cards as well in the future
A69: base1-68 | B69: Vulpix | C69: R | D69: b | E69: y | G69: e | H69: SL | K69: TRUE | N69: Per WotC rulings: Promo Cool Porygon *can* evolve (when Porygon2 is introduced), but the [adjective] Pikachu variants *cannot* evolve
A70: base1-69 | B70: Weedle | C70: G | D70: b | E70: y | G70: a | H70: SL | K70: TRUE | N70: "Trevor's Pikachu" was originally "_____'s Pikachu" that has variable attack damage based on its owner's birthday. Rather than building in a birthday system, I decided to use mine as a placeholder
A71: base1-7 | B71: Hitmonchan | C71: F | D71: b | E71: n | F71: 0.5 | G71: a | I71: A stalling or opening role. Jab is the main one to power up. Special Punch is expensive and should only be powered up if the bench doesn't have better options. | K71: TRUE | N71: If you don't have stats for Ancient Mew I can provide them.
A72: base1-70 | B72: Clefairy Doll | C72: T | D72: r | F72: e | J72: y | K72: FALSE
A73: base1-71 | B73: Computer Search | C73: T | D73: r | F73: s | I73: To be used to find a needed evolution card, another basic if basics are in short supply or if its evolution is in hand, or whatever else might be most needed at the moment | K73: TRUE
A74: base1-72 | B74: Devolution Spray | C74: T | D74: r | F74: r | J74: y | K74: FALSE
A75: base1-73 | B75: Impostor Professor Oak | C75: T | D75: r | F75: p | I75: To be used when its opponent has a lot of cards in their hand. It's disruptive in many cases, but this gets the largest effect | K75: TRUE
A76: base1-74 | B76: Item Finder | C76: T | D76: r | F76: s | K76: TRUE
A77: base1-75 | B77: Lass | C77: T | D77: r | F77: p | I77: A deck with relatively few trainer cards so the opponent is disproportionately affected | K77: TRUE
A78: base1-76 | B78: Pokemon Breeder | C78: T | D78: r | F78: m | I78: A deck with many stage 2 cards, and preferably multiple stage 2 lines | K78: TRUE
A79: base1-77 | B79: Pokemon Trader | C79: T | D79: r | F79: s | I79: Same use case as Computer Search but a card is sent back to the deck rather than discarded | K79: TRUE
A80: base1-78 | B80: Scoop Up | C80: T | D80: r | F80: m | I80: To rescue a high-HP basic pokemon, usually a tank like Snorlax or Chansey, after it has high damage. As a tank, there are usually few energy cards attached so not much is lost, and as a basic they can just be thrown back to the bench right away with now damage. This works great in combination with Alakazam's Pokemon Power loading up a tank on the bench with damage, scooping up the high damage pokemon, and then putting it right back on the bench to be loaded up again | K80: TRUE
A81: base1-79 | B81: Super Energy Removal | C81: T | D81: r | F81: p | I81: Costs you a turn of tempo in exchange for costing the opponent two turns of tempo. Your own energy drop should be from a pokemon who needs it the least, and the opponent pokemon selected should be one where this would really cost it, usually the active one. DOES NOT want to be used on an opponent pokemon with only one energy because then you don't gain an advantage. | K81: TRUE
A82: base1-8 | B82: Machamp | C82: F | D82: 2 | F82: 3 | I82: A very standard card that our bot will do fine with. Strikes Back is more of a passive punishment for killing it that's hard to strategize for other than the nuisanse it is just by existing | K82: TRUE
A83: base1-80 | B83: Defender | C83: T | D83: u | F83: p | I83: To be used only when the active pokemon expects to take damage on the next turn, and only damage that's survivable with the Defender attached. Defenders also block self-damage, so they can be used strategically there as well (our game does not block self-damage yet with Defender but it should). The best time to use it is when it would save a valuable active pokemon that would otherwise die. Should not be played just because it exists in the bot's hand. | K83: TRUE
A84: base1-81 | B84: Energy Retrieval | C84: T | D84: u | F84: s | I84: To be in decks that require energy funnels, or in multi-type decks where a desired energy can be rescued from discard if running short | K84: TRUE
A85: base1-82 | B85: Full Heal | C85: T | D85: u | F85: r | I85: To be in most decks, and save a pokemon from a missed turn from an opponent's status move. It especially loves decks with pokemon that apply status conditions to themselves, like Vileplume | K85: TRUE
A86: base1-83 | B86: Maintenance | C86: T | D86: u | F86: d | I86: Not a useful card. Autobuilder should avoid | K86: TRUE
A87: base1-84 | B87: PlusPower | C87: T | D87: u | F87: p | I87: To be used strategically but not be held onto like it's in a vault. The best times are when your own pokemon would fall 10 damage short of knocking out the opponent, or when an additional 10 damage would result in 1 fewer turn to kill the opponent, as in a move doing 30 damage attacking a pokemon with 70 HP. The best practice there is to plant to hit for 30 on the first turn and use the PlusPower for 40 on the second turn. If you might not survive until the second turn, the PlusPower could probably be used early | K87: TRUE
A88: base1-85 | B88: Pokemon Center | C88: T | D88: u | F88: h | J88: y | K88: FALSE
A89: base1-86 | B89: Pokemon Flute | C89: T | D89: u | F89: m | J89: y | K89: FALSE
A90: base1-87 | B90: Pokedex | C90: T | D90: u | F90: p | I90: Best if the autobuilder avoids | K90: TRUE
A91: base1-88 | B91: Professor Oak | C91: T | D91: u | F91: d | I91: To be played when either desperate for cards or when little of value would be lost by discarding its owner's hand. Consumables like Potion or PlusPower want to be used immediately before Professor Oak even if they're not needed, because they get discarded otherwise | K91: TRUE
A92: base1-89 | B92: Revive | C92: T | D92: u | F92: m | I92: To be used to revive a tank, and not much else. Best if the autobuilder avoids | J92: y | K92: FALSE
A93: base1-9 | B93: Magneton | C93: E | D93: 1 | E93: n | F93: 2 | H93: SL, HD | I93: The same logic as base1 Magnemite and other Kamakaze Timers. Thunder Wave is used as a status lock until that's needed | K93: TRUE
A94: base1-90 | B94: Super Potion | C94: T | D94: u | F94: h | I94: To heal a moderate amount of damage at the cost of 1 tempo of energy. Should not be used to save a pokemon that it would prevent from powering up enough to attack, as that would just be stalling for no benefit | K94: TRUE
A95: base1-91 | B95: Bill | C95: T | D95: c | F95: d | I95: To be used right away and exist in almost every deck. Weak decks have 1-2, stronger decks have 3-4 | K95: TRUE
A96: base1-92 | B96: Energy Removal | C96: T | D96: c | F96: p | I96: To be used liberally and strategically. Do not remove an energy just to remove an energy, do it to something that it would inconvenience by having to re-attach. The opponent's active pokemon usually makes for the best target, but something powerful on the bench could work as well. Denying the active pokemon forces the opponent to re-power that one instead of preparing the bench, might lead to the opponent taking an extra turn to attack, and might completely stop the opponent if he doesn't have any extra energies. After a pokemone is selected, if it has multiple energy types, DCE should be the first target and its own energy type (as in the hard requirements for its moves rather than the colorless extras) should be the second. | K96: TRUE
A97: base1-93 | B97: Gust of Wind | C97: T | D97: c | F97: m | I97: To drag in a damaged bench pokemon to finish it off, preferably a strong one that could pose a menace. Bringing in a high damage pokemon from the bench with low HP can still lay a large hit on you before you have a turn to finish it off, and this card allows you to preempt that. It can also shift a dangerous pokemon out of the active spot and replace it with something else that doesn't have the energy to attack or retreat yet. | K97: TRUE
A98: base1-94 | B98: Potion | C98: T | D98: c | F98: h | I98: To not be used to heal only 10 damage unless that has the immediate potential to be life saving (and the pokemon is worth saving) | K98: TRUE
A99: base1-95 | B99: Switch | C99: T | D99: c | F99: m | I99: To retreat a high value pokemon without paying the retreat cost, or launch a sudden switch for a quick attack that the opponent wasn't expecting. Does not want to be used on a free-retreat cost pokemon and prefers heavier retreat costs to nullify. Should not be played just because it exists in the bot's hand | K99: TRUE
A100: base1-96 | B100: DC Energy | C100: Energy | K100: TRUE
...

Sheet Deck List
B1: Base1 | D1: Jungle | F1: Fossil | H1: Challenge 1 | J1: Rocket
A2: T2-1 | B2: F, W | C2: Starmie | D2: E, R, W | E2: Eevee | F2: W, P | G2: Hypno NH | H2: G | I2: Weezing | J2: E, R, W | K2: Eevee R
A3: T2-2 | B3: P, R | C3: Alakazam | D3: G, P | E3: Nidoqueen | F3: F, E | G3: Hitmonlee | H3: F | I3: Aerodactyl | J3: E, G | K3: Dark Raichu
A4: T2-3 | B4: G, E | C4: Beedrill | D4: F, G | E4: Rhydon | F4: G, W | G4: Muk | H4: P | I4: Gengar | J4: R, P | K4: Dark Charizard
A5: T2-4 | B5: E, F | C5: Machamp | H5: R | I5: Moltres | J5: P, C | K5: Dark Alakazam
A6: T2-5 | B6: W, P | C6: Poliwrath | H6: E | I6: Zapdos B3
A7: T3-1 | B7: G | C7: Venusaur | D7: C, G | E7: Pidgeot | F7: W | G7: Omastar | H7: W | I7: Articuno | J7: G | K7: Dark Vileplume
A8: T3-2 | B8: W | C8: Blastoise | F8: C, F | G8: Dragonite | H8: C | I8: Wigglytuff | J8: F | K8: Dark Machamp
A9: T3-3 | J9: C, E, R, W | K9: Dark Dragonite
A10: T4 | B10: R | C10: Charizard | D10: G | E10: Vileplume | F10: P | G10: Haunter B3 | J10: W | K10: Dark Blastoise
A13: Challenge ignores regular Tier structure

Sheet Template
A1: Card | B1: Quantity | C1: Type | D1: ID | E1: Stage / Rarity | F1: Remaining Evo | G1: Feature Weight | I1: Card Total | K1: Type | L1: Num | M1: Basic | N1: S1 Max | O1: S1 Mid | P1: S2 | Q1: No Evolve
C2: {=IF(NOT(ISBLANK($A2)), (_xlfn.XLOOKUP($A2,Index!$B$2:$B$995,Index!$C$2:$C$995,"Not Found")),"")} | D2: {=IF(NOT(ISBLANK(A2)), (_xlfn.XLOOKUP($A2,Index!$B$2:B$995,Index!$A$2:$A$995,"Not Found")),"")} | E2: {=IF(NOT(ISBLANK($A2)), (_xlfn.XLOOKUP($A2,Index!$B$2:$B$995,Index!$D$2:$D$995,"Not Found")),"")} | F2: {=IF(NOT(ISBLANK($A2)), (_xlfn.XLOOKUP($A2,Index!$B$2:$B$995,Index!$E$2:$E$995,"Not Found")),"")} | G2: {=IF(NOT(ISBLANK(A2)), ((_xlfn.XLOOKUP(A2,Index!$B$2:$B$995,Index!$F$2:$F$995,"Not Found"))*B2),"")} | I2: =SUM(B2:B38) -> 0 | L2: =IF(NOT(ISBLANK(K2)), SUM(M2:P2), "") | M2: =IF(NOT(ISBLANK($K2)), SUMIFS($B$2:$B$32, $E$2:$E$32, "B", $C$2:$C$32,$K2), "") | N2: =IF(NOT(ISBLANK($K2)),SUMIFS($B$2:$B$32,$E$2:$E$32, "1", $C$2:$C$32,$K2,$F$2:$F$32,"N"), "") | O2: =IF(NOT(ISBLANK($K2)),SUMIFS($B$2:$B$32,$E$2:$E$32, "1", $C$2:$C$32,$K2,$F$2:$F$32,"Y"), "") | P2: =IF(NOT(ISBLANK($K2)),SUMIFS($B$2:$B$32,$E$2:$E$32, "2", $C$2:$C$32,$K2), "") | Q2: =IF(NOT(ISBLANK($K2)),SUMIFS($B$2:$B$32,$E$2:$E$32, "B", $C$2:$C$32,$K2,$F$2:$F$32,"N"), "")
C3: {=IF(NOT(ISBLANK($A3)), (_xlfn.XLOOKUP($A3,Index!$B$2:$B$995,Index!$C$2:$C$995,"Not Found")),"")} | D3: {=IF(NOT(ISBLANK(A3)), (_xlfn.XLOOKUP($A3,Index!$B$2:B$995,Index!$A$2:$A$995,"Not Found")),"")} | E3: {=IF(NOT(ISBLANK($A3)), (_xlfn.XLOOKUP($A3,Index!$B$2:$B$995,Index!$D$2:$D$995,"Not Found")),"")} | F3: {=IF(NOT(ISBLANK($A3)), (_xlfn.XLOOKUP($A3,Index!$B$2:$B$995,Index!$E$2:$E$995,"Not Found")),"")} | G3: {=IF(NOT(ISBLANK(A3)), ((_xlfn.XLOOKUP(A3,Index!$B$2:$B$995,Index!$F$2:$F$995,"Not Found"))*B3),"")} | L3: =IF(NOT(ISBLANK(K3)), SUM(M3:P3), "") | M3: =IF(NOT(ISBLANK($K3)), SUMIFS($B$2:$B$32, $E$2:$E$32, "B", $C$2:$C$32,$K3), "") | N3: =IF(NOT(ISBLANK($K3)),SUMIFS($B$2:$B$32,$E$2:$E$32, "1", $C$2:$C$32,$K3,$F$2:$F$32,"N"), "") | O3: =IF(NOT(ISBLANK($K3)),SUMIFS($B$2:$B$32,$E$2:$E$32, "1", $C$2:$C$32,$K3,$F$2:$F$32,"Y"), "") | P3: =IF(NOT(ISBLANK($K3)),SUMIFS($B$2:$B$32,$E$2:$E$32, "2", $C$2:$C$32,$K3), "") | Q3: =IF(NOT(ISBLANK($K3)),SUMIFS($B$2:$B$32,$E$2:$E$32, "B", $C$2:$C$32,$K3,$F$2:$F$32,"N"), "")
C4: {=IF(NOT(ISBLANK($A4)), (_xlfn.XLOOKUP($A4,Index!$B$2:$B$995,Index!$C$2:$C$995,"Not Found")),"")} | D4: {=IF(NOT(ISBLANK(A4)), (_xlfn.XLOOKUP($A4,Index!$B$2:B$995,Index!$A$2:$A$995,"Not Found")),"")} | E4: {=IF(NOT(ISBLANK($A4)), (_xlfn.XLOOKUP($A4,Index!$B$2:$B$995,Index!$D$2:$D$995,"Not Found")),"")} | F4: {=IF(NOT(ISBLANK($A4)), (_xlfn.XLOOKUP($A4,Index!$B$2:$B$995,Index!$E$2:$E$995,"Not Found")),"")} | G4: {=IF(NOT(ISBLANK(A4)), ((_xlfn.XLOOKUP(A4,Index!$B$2:$B$995,Index!$F$2:$F$995,"Not Found"))*B4),"")} | L4: =IF(NOT(ISBLANK(K4)), SUM(M4:P4), "") | M4: =IF(NOT(ISBLANK($K4)), SUMIFS($B$2:$B$32, $E$2:$E$32, "B", $C$2:$C$32,$K4), "") | N4: =IF(NOT(ISBLANK($K4)),SUMIFS($B$2:$B$32,$E$2:$E$32, "1", $C$2:$C$32,$K4,$F$2:$F$32,"N"), "") | O4: =IF(NOT(ISBLANK($K4)),SUMIFS($B$2:$B$32,$E$2:$E$32, "1", $C$2:$C$32,$K4,$F$2:$F$32,"Y"), "") | P4: =IF(NOT(ISBLANK($K4)),SUMIFS($B$2:$B$32,$E$2:$E$32, "2", $C$2:$C$32,$K4), "") | Q4: =IF(NOT(ISBLANK($K4)),SUMIFS($B$2:$B$32,$E$2:$E$32, "B", $C$2:$C$32,$K4,$F$2:$F$32,"N"), "")
C5: {=IF(NOT(ISBLANK($A5)), (_xlfn.XLOOKUP($A5,Index!$B$2:$B$995,Index!$C$2:$C$995,"Not Found")),"")} | D5: {=IF(NOT(ISBLANK(A5)), (_xlfn.XLOOKUP($A5,Index!$B$2:B$995,Index!$A$2:$A$995,"Not Found")),"")} | E5: {=IF(NOT(ISBLANK($A5)), (_xlfn.XLOOKUP($A5,Index!$B$2:$B$995,Index!$D$2:$D$995,"Not Found")),"")} | F5: {=IF(NOT(ISBLANK($A5)), (_xlfn.XLOOKUP($A5,Index!$B$2:$B$995,Index!$E$2:$E$995,"Not Found")),"")} | G5: {=IF(NOT(ISBLANK(A5)), ((_xlfn.XLOOKUP(A5,Index!$B$2:$B$995,Index!$F$2:$F$995,"Not Found"))*B5),"")} | L5: =IF(NOT(ISBLANK(K5)), SUM(M5:P5), "") | M5: =IF(NOT(ISBLANK($K5)), SUMIFS($B$2:$B$32, $E$2:$E$32, "B", $C$2:$C$32,$K5), "") | N5: =IF(NOT(ISBLANK($K5)),SUMIFS($B$2:$B$32,$E$2:$E$32, "1", $C$2:$C$32,$K5,$F$2:$F$32,"N"), "") | O5: =IF(NOT(ISBLANK($K5)),SUMIFS($B$2:$B$32,$E$2:$E$32, "1", $C$2:$C$32,$K5,$F$2:$F$32,"Y"), "") | P5: =IF(NOT(ISBLANK($K5)),SUMIFS($B$2:$B$32,$E$2:$E$32, "2", $C$2:$C$32,$K5), "") | Q5: =IF(NOT(ISBLANK($K5)),SUMIFS($B$2:$B$32,$E$2:$E$32, "B", $C$2:$C$32,$K5,$F$2:$F$32,"N"), "")
C6: {=IF(NOT(ISBLANK($A6)), (_xlfn.XLOOKUP($A6,Index!$B$2:$B$995,Index!$C$2:$C$995,"Not Found")),"")} | D6: {=IF(NOT(ISBLANK(A6)), (_xlfn.XLOOKUP($A6,Index!$B$2:B$995,Index!$A$2:$A$995,"Not Found")),"")} | E6: {=IF(NOT(ISBLANK($A6)), (_xlfn.XLOOKUP($A6,Index!$B$2:$B$995,Index!$D$2:$D$995,"Not Found")),"")} | F6: {=IF(NOT(ISBLANK($A6)), (_xlfn.XLOOKUP($A6,Index!$B$2:$B$995,Index!$E$2:$E$995,"Not Found")),"")} | G6: {=IF(NOT(ISBLANK(A6)), ((_xlfn.XLOOKUP(A6,Index!$B$2:$B$995,Index!$F$2:$F$995,"Not Found"))*B6),"")} | L6: =IF(NOT(ISBLANK(K6)), SUM(M6:P6), "") | M6: =IF(NOT(ISBLANK($K6)), COUNTIFS($E$2:$E$32, "B", $C$2:$C$32,$K6), "") | N6: =IF(NOT(ISBLANK(K6)),COUNTIFS($E$2:$E$32, "1", $C$2:$C$32,$K6,$F$2:$F$32,"N"), "") | O6: =IF(NOT(ISBLANK($K6)),COUNTIFS($E$2:$E$32, "1", $C$2:$C$32,$K6,$F$2:$F$32,"Y"), "") | P6: =IF(NOT(ISBLANK($K6)),COUNTIFS($E$2:$E$32, "2", $C$2:$C$32,$K6), "") | Q6: =IF(NOT(ISBLANK($K6)),COUNTIFS($E$2:$E$32, "B", $C$2:$C$32,$K6,$F$2:$F$32,"N"), "")
C7: {=IF(NOT(ISBLANK($A7)), (_xlfn.XLOOKUP($A7,Index!$B$2:$B$995,Index!$C$2:$C$995,"Not Found")),"")} | D7: {=IF(NOT(ISBLANK(A7)), (_xlfn.XLOOKUP($A7,Index!$B$2:B$995,Index!$A$2:$A$995,"Not Found")),"")} | E7: {=IF(NOT(ISBLANK($A7)), (_xlfn.XLOOKUP($A7,Index!$B$2:$B$995,Index!$D$2:$D$995,"Not Found")),"")} | F7: {=IF(NOT(ISBLANK($A7)), (_xlfn.XLOOKUP($A7,Index!$B$2:$B$995,Index!$E$2:$E$995,"Not Found")),"")} | G7: {=IF(NOT(ISBLANK(A7)), ((_xlfn.XLOOKUP(A7,Index!$B$2:$B$995,Index!$F$2:$F$995,"Not Found"))*B7),"")} | K7: Total | L7: =SUM(L2:L6) -> 0 | M7: =SUM(M2:M6) -> 0 | N7: =SUM(N2:N6) -> 0 | O7: =SUM(O2:O6) -> 0 | P7: =SUM(P2:P6) -> 0 | Q7: =SUM(Q2:Q6) -> 0
C8: {=IF(NOT(ISBLANK($A8)), (_xlfn.XLOOKUP($A8,Index!$B$2:$B$995,Index!$C$2:$C$995,"Not Found")),"")} | D8: {=IF(NOT(ISBLANK(A8)), (_xlfn.XLOOKUP($A8,Index!$B$2:B$995,Index!$A$2:$A$995,"Not Found")),"")} | E8: {=IF(NOT(ISBLANK($A8)), (_xlfn.XLOOKUP($A8,Index!$B$2:$B$995,Index!$D$2:$D$995,"Not Found")),"")} | F8: {=IF(NOT(ISBLANK($A8)), (_xlfn.XLOOKUP($A8,Index!$B$2:$B$995,Index!$E$2:$E$995,"Not Found")),"")} | G8: {=IF(NOT(ISBLANK(A8)), ((_xlfn.XLOOKUP(A8,Index!$B$2:$B$995,Index!$F$2:$F$995,"Not Found"))*B8),"")}
C9: {=IF(NOT(ISBLANK($A9)), (_xlfn.XLOOKUP($A9,Index!$B$2:$B$995,Index!$C$2:$C$995,"Not Found")),"")} | D9: {=IF(NOT(ISBLANK(A9)), (_xlfn.XLOOKUP($A9,Index!$B$2:B$995,Index!$A$2:$A$995,"Not Found")),"")} | E9: {=IF(NOT(ISBLANK($A9)), (_xlfn.XLOOKUP($A9,Index!$B$2:$B$995,Index!$D$2:$D$995,"Not Found")),"")} | F9: {=IF(NOT(ISBLANK($A9)), (_xlfn.XLOOKUP($A9,Index!$B$2:$B$995,Index!$E$2:$E$995,"Not Found")),"")} | G9: {=IF(NOT(ISBLANK(A9)), ((_xlfn.XLOOKUP(A9,Index!$B$2:$B$995,Index!$F$2:$F$995,"Not Found"))*B9),"")} | M9: Common | N9: Uncommon | O9: Rare
C10: {=IF(NOT(ISBLANK($A10)), (_xlfn.XLOOKUP($A10,Index!$B$2:$B$995,Index!$C$2:$C$995,"Not Found")),"")} | D10: {=IF(NOT(ISBLANK(A10)), (_xlfn.XLOOKUP($A10,Index!$B$2:B$995,Index!$A$2:$A$995,"Not Found")),"")} | E10: {=IF(NOT(ISBLANK($A10)), (_xlfn.XLOOKUP($A10,Index!$B$2:$B$995,Index!$D$2:$D$995,"Not Found")),"")} | F10: {=IF(NOT(ISBLANK($A10)), (_xlfn.XLOOKUP($A10,Index!$B$2:$B$995,Index!$E$2:$E$995,"Not Found")),"")} | G10: {=IF(NOT(ISBLANK(A10)), ((_xlfn.XLOOKUP(A10,Index!$B$2:$B$995,Index!$F$2:$F$995,"Not Found"))*B10),"")} | K10: Trainer | L10: =SUM(M10:P10) -> 0 | M10: =IF(NOT(ISBLANK($K10)), SUMIFS($B$2:$B$32,$E$2:$E$32, "C", $C$2:$C$32,"T"), "") -> 0 | N10: =IF(NOT(ISBLANK($K10)), SUMIFS($B$2:$B$32,$E$2:$E$32, "U", $C$2:$C$32,"T"), "") -> 0 | O10: =IF(NOT(ISBLANK($K$2)), SUMIFS($B$2:$B$32,$E$2:$E$32, "R", $C$2:$C$32,"T"), "")
C11: {=IF(NOT(ISBLANK($A11)), (_xlfn.XLOOKUP($A11,Index!$B$2:$B$995,Index!$C$2:$C$995,"Not Found")),"")} | D11: {=IF(NOT(ISBLANK(A11)), (_xlfn.XLOOKUP($A11,Index!$B$2:B$995,Index!$A$2:$A$995,"Not Found")),"")} | E11: {=IF(NOT(ISBLANK($A11)), (_xlfn.XLOOKUP($A11,Index!$B$2:$B$995,Index!$D$2:$D$995,"Not Found")),"")} | F11: {=IF(NOT(ISBLANK($A11)), (_xlfn.XLOOKUP($A11,Index!$B$2:$B$995,Index!$E$2:$E$995,"Not Found")),"")} | G11: {=IF(NOT(ISBLANK(A11)), ((_xlfn.XLOOKUP(A11,Index!$B$2:$B$995,Index!$F$2:$F$995,"Not Found"))*B11),"")} | K11: Energy | L11: =IF(NOT(ISBLANK($K$2)), SUMIFS($B$2:$B$32, $C$2:$C$32,"Energy"), "")
C12: {=IF(NOT(ISBLANK($A12)), (_xlfn.XLOOKUP($A12,Index!$B$2:$B$995,Index!$C$2:$C$995,"Not Found")),"")} | D12: {=IF(NOT(ISBLANK(A12)), (_xlfn.XLOOKUP($A12,Index!$B$2:B$995,Index!$A$2:$A$995,"Not Found")),"")} | E12: {=IF(NOT(ISBLANK($A12)), (_xlfn.XLOOKUP($A12,Index!$B$2:$B$995,Index!$D$2:$D$995,"Not Found")),"")} | F12: {=IF(NOT(ISBLANK($A12)), (_xlfn.XLOOKUP($A12,Index!$B$2:$B$995,Index!$E$2:$E$995,"Not Found")),"")} | G12: {=IF(NOT(ISBLANK(A12)), ((_xlfn.XLOOKUP(A12,Index!$B$2:$B$995,Index!$F$2:$F$995,"Not Found"))*B12),"")} | K12: Pokemon | L12: =L7 -> 0
C13: {=IF(NOT(ISBLANK($A13)), (_xlfn.XLOOKUP($A13,Index!$B$2:$B$995,Index!$C$2:$C$995,"Not Found")),"")} | D13: {=IF(NOT(ISBLANK(A13)), (_xlfn.XLOOKUP($A13,Index!$B$2:B$995,Index!$A$2:$A$995,"Not Found")),"")} | E13: {=IF(NOT(ISBLANK($A13)), (_xlfn.XLOOKUP($A13,Index!$B$2:$B$995,Index!$D$2:$D$995,"Not Found")),"")} | F13: {=IF(NOT(ISBLANK($A13)), (_xlfn.XLOOKUP($A13,Index!$B$2:$B$995,Index!$E$2:$E$995,"Not Found")),"")} | G13: {=IF(NOT(ISBLANK(A13)), ((_xlfn.XLOOKUP(A13,Index!$B$2:$B$995,Index!$F$2:$F$995,"Not Found"))*B13),"")}
C14: {=IF(NOT(ISBLANK($A14)), (_xlfn.XLOOKUP($A14,Index!$B$2:$B$995,Index!$C$2:$C$995,"Not Found")),"")} | D14: {=IF(NOT(ISBLANK(A14)), (_xlfn.XLOOKUP($A14,Index!$B$2:B$995,Index!$A$2:$A$995,"Not Found")),"")} | E14: {=IF(NOT(ISBLANK($A14)), (_xlfn.XLOOKUP($A14,Index!$B$2:$B$995,Index!$D$2:$D$995,"Not Found")),"")} | F14: {=IF(NOT(ISBLANK($A14)), (_xlfn.XLOOKUP($A14,Index!$B$2:$B$995,Index!$E$2:$E$995,"Not Found")),"")} | G14: {=IF(NOT(ISBLANK(A14)), ((_xlfn.XLOOKUP(A14,Index!$B$2:$B$995,Index!$F$2:$F$995,"Not Found"))*B14),"")}
C15: {=IF(NOT(ISBLANK($A15)), (_xlfn.XLOOKUP($A15,Index!$B$2:$B$995,Index!$C$2:$C$995,"Not Found")),"")} | D15: {=IF(NOT(ISBLANK(A15)), (_xlfn.XLOOKUP($A15,Index!$B$2:B$995,Index!$A$2:$A$995,"Not Found")),"")} | E15: {=IF(NOT(ISBLANK($A15)), (_xlfn.XLOOKUP($A15,Index!$B$2:$B$995,Index!$D$2:$D$995,"Not Found")),"")} | F15: {=IF(NOT(ISBLANK($A15)), (_xlfn.XLOOKUP($A15,Index!$B$2:$B$995,Index!$E$2:$E$995,"Not Found")),"")} | G15: {=IF(NOT(ISBLANK(A15)), ((_xlfn.XLOOKUP(A15,Index!$B$2:$B$995,Index!$F$2:$F$995,"Not Found"))*B15),"")} | K15: Feature Weight:
C16: {=IF(NOT(ISBLANK($A16)), (_xlfn.XLOOKUP($A16,Index!$B$2:$B$995,Index!$C$2:$C$995,"Not Found")),"")} | D16: {=IF(NOT(ISBLANK(A16)), (_xlfn.XLOOKUP($A16,Index!$B$2:B$995,Index!$A$2:$A$995,"Not Found")),"")} | E16: {=IF(NOT(ISBLANK($A16)), (_xlfn.XLOOKUP($A16,Index!$B$2:$B$995,Index!$D$2:$D$995,"Not Found")),"")} | F16: {=IF(NOT(ISBLANK($A16)), (_xlfn.XLOOKUP($A16,Index!$B$2:$B$995,Index!$E$2:$E$995,"Not Found")),"")} | G16: {=IF(NOT(ISBLANK(A16)), ((_xlfn.XLOOKUP(A16,Index!$B$2:$B$995,Index!$F$2:$F$995,"Not Found"))*B16),"")} | K16: =K2 | L16: =IF(NOT(ISBLANK($K2)), SUMIFS($G$2:$G$32, $C$2:$C$32,$K2), "")
C17: {=IF(NOT(ISBLANK($A17)), (_xlfn.XLOOKUP($A17,Index!$B$2:$B$995,Index!$C$2:$C$995,"Not Found")),"")} | D17: {=IF(NOT(ISBLANK(A17)), (_xlfn.XLOOKUP($A17,Index!$B$2:B$995,Index!$A$2:$A$995,"Not Found")),"")} | E17: {=IF(NOT(ISBLANK($A17)), (_xlfn.XLOOKUP($A17,Index!$B$2:$B$995,Index!$D$2:$D$995,"Not Found")),"")} | F17: {=IF(NOT(ISBLANK($A17)), (_xlfn.XLOOKUP($A17,Index!$B$2:$B$995,Index!$E$2:$E$995,"Not Found")),"")} | G17: {=IF(NOT(ISBLANK(A17)), ((_xlfn.XLOOKUP(A17,Index!$B$2:$B$995,Index!$F$2:$F$995,"Not Found"))*B17),"")} | K17: =K3 | L17: =IF(NOT(ISBLANK($K3)), SUMIFS($G$2:$G$32, $C$2:$C$32,$K3), "")
C18: {=IF(NOT(ISBLANK($A18)), (_xlfn.XLOOKUP($A18,Index!$B$2:$B$995,Index!$C$2:$C$995,"Not Found")),"")} | D18: {=IF(NOT(ISBLANK(A18)), (_xlfn.XLOOKUP($A18,Index!$B$2:B$995,Index!$A$2:$A$995,"Not Found")),"")} | E18: {=IF(NOT(ISBLANK($A18)), (_xlfn.XLOOKUP($A18,Index!$B$2:$B$995,Index!$D$2:$D$995,"Not Found")),"")} | F18: {=IF(NOT(ISBLANK($A18)), (_xlfn.XLOOKUP($A18,Index!$B$2:$B$995,Index!$E$2:$E$995,"Not Found")),"")} | G18: {=IF(NOT(ISBLANK(A18)), ((_xlfn.XLOOKUP(A18,Index!$B$2:$B$995,Index!$F$2:$F$995,"Not Found"))*B18),"")} | K18: =K4 | L18: =IF(NOT(ISBLANK($K4)), SUMIFS($G$2:$G$32, $C$2:$C$32,$K4), "")
C19: {=IF(NOT(ISBLANK($A19)), (_xlfn.XLOOKUP($A19,Index!$B$2:$B$995,Index!$C$2:$C$995,"Not Found")),"")} | D19: {=IF(NOT(ISBLANK(A19)), (_xlfn.XLOOKUP($A19,Index!$B$2:B$995,Index!$A$2:$A$995,"Not Found")),"")} | E19: {=IF(NOT(ISBLANK($A19)), (_xlfn.XLOOKUP($A19,Index!$B$2:$B$995,Index!$D$2:$D$995,"Not Found")),"")} | F19: {=IF(NOT(ISBLANK($A19)), (_xlfn.XLOOKUP($A19,Index!$B$2:$B$995,Index!$E$2:$E$995,"Not Found")),"")} | G19: {=IF(NOT(ISBLANK(A19)), ((_xlfn.XLOOKUP(A19,Index!$B$2:$B$995,Index!$F$2:$F$995,"Not Found"))*B19),"")} | K19: =K5 | L19: =IF(NOT(ISBLANK($K5)), SUMIFS($G$2:$G$32, $C$2:$C$32,$K5), "")
C20: {=IF(NOT(ISBLANK($A20)), (_xlfn.XLOOKUP($A20,Index!$B$2:$B$995,Index!$C$2:$C$995,"Not Found")),"")} | D20: {=IF(NOT(ISBLANK(A20)), (_xlfn.XLOOKUP($A20,Index!$B$2:B$995,Index!$A$2:$A$995,"Not Found")),"")} | E20: {=IF(NOT(ISBLANK($A20)), (_xlfn.XLOOKUP($A20,Index!$B$2:$B$995,Index!$D$2:$D$995,"Not Found")),"")} | F20: {=IF(NOT(ISBLANK($A20)), (_xlfn.XLOOKUP($A20,Index!$B$2:$B$995,Index!$E$2:$E$995,"Not Found")),"")} | G20: {=IF(NOT(ISBLANK(A20)), ((_xlfn.XLOOKUP(A20,Index!$B$2:$B$995,Index!$F$2:$F$995,"Not Found"))*B20),"")} | K20: =K6
C21: {=IF(NOT(ISBLANK($A21)), (_xlfn.XLOOKUP($A21,Index!$B$2:$B$995,Index!$C$2:$C$995,"Not Found")),"")} | D21: {=IF(NOT(ISBLANK(A21)), (_xlfn.XLOOKUP($A21,Index!$B$2:B$995,Index!$A$2:$A$995,"Not Found")),"")} | E21: {=IF(NOT(ISBLANK($A21)), (_xlfn.XLOOKUP($A21,Index!$B$2:$B$995,Index!$D$2:$D$995,"Not Found")),"")} | F21: {=IF(NOT(ISBLANK($A21)), (_xlfn.XLOOKUP($A21,Index!$B$2:$B$995,Index!$E$2:$E$995,"Not Found")),"")} | G21: {=IF(NOT(ISBLANK(A21)), ((_xlfn.XLOOKUP(A21,Index!$B$2:$B$995,Index!$F$2:$F$995,"Not Found"))*B21),"")} | K21: Total: | L21: =SUM(L15:L19) -> 0
C22: {=IF(NOT(ISBLANK($A22)), (_xlfn.XLOOKUP($A22,Index!$B$2:$B$995,Index!$C$2:$C$995,"Not Found")),"")} | D22: {=IF(NOT(ISBLANK(A22)), (_xlfn.XLOOKUP($A22,Index!$B$2:B$995,Index!$A$2:$A$995,"Not Found")),"")} | E22: {=IF(NOT(ISBLANK($A22)), (_xlfn.XLOOKUP($A22,Index!$B$2:$B$995,Index!$D$2:$D$995,"Not Found")),"")} | F22: {=IF(NOT(ISBLANK($A22)), (_xlfn.XLOOKUP($A22,Index!$B$2:$B$995,Index!$E$2:$E$995,"Not Found")),"")} | G22: {=IF(NOT(ISBLANK(A22)), ((_xlfn.XLOOKUP(A22,Index!$B$2:$B$995,Index!$F$2:$F$995,"Not Found"))*B22),"")}
C23: {=IF(NOT(ISBLANK($A23)), (_xlfn.XLOOKUP($A23,Index!$B$2:$B$995,Index!$C$2:$C$995,"Not Found")),"")} | D23: {=IF(NOT(ISBLANK(A23)), (_xlfn.XLOOKUP($A23,Index!$B$2:B$995,Index!$A$2:$A$995,"Not Found")),"")} | E23: {=IF(NOT(ISBLANK($A23)), (_xlfn.XLOOKUP($A23,Index!$B$2:$B$995,Index!$D$2:$D$995,"Not Found")),"")} | F23: {=IF(NOT(ISBLANK($A23)), (_xlfn.XLOOKUP($A23,Index!$B$2:$B$995,Index!$E$2:$E$995,"Not Found")),"")} | G23: {=IF(NOT(ISBLANK(A23)), ((_xlfn.XLOOKUP(A23,Index!$B$2:$B$995,Index!$F$2:$F$995,"Not Found"))*B23),"")}
C24: {=IF(NOT(ISBLANK($A24)), (_xlfn.XLOOKUP($A24,Index!$B$2:$B$995,Index!$C$2:$C$995,"Not Found")),"")} | D24: {=IF(NOT(ISBLANK(A24)), (_xlfn.XLOOKUP($A24,Index!$B$2:B$995,Index!$A$2:$A$995,"Not Found")),"")} | E24: {=IF(NOT(ISBLANK($A24)), (_xlfn.XLOOKUP($A24,Index!$B$2:$B$995,Index!$D$2:$D$995,"Not Found")),"")} | F24: {=IF(NOT(ISBLANK($A24)), (_xlfn.XLOOKUP($A24,Index!$B$2:$B$995,Index!$E$2:$E$995,"Not Found")),"")} | G24: {=IF(NOT(ISBLANK(A24)), ((_xlfn.XLOOKUP(A24,Index!$B$2:$B$995,Index!$F$2:$F$995,"Not Found"))*B24),"")} | K24: Cover Card:
C25: {=IF(NOT(ISBLANK($A25)), (_xlfn.XLOOKUP($A25,Index!$B$2:$B$995,Index!$C$2:$C$995,"Not Found")),"")} | D25: {=IF(NOT(ISBLANK(A25)), (_xlfn.XLOOKUP($A25,Index!$B$2:B$995,Index!$A$2:$A$995,"Not Found")),"")} | E25: {=IF(NOT(ISBLANK($A25)), (_xlfn.XLOOKUP($A25,Index!$B$2:$B$995,Index!$D$2:$D$995,"Not Found")),"")} | F25: {=IF(NOT(ISBLANK($A25)), (_xlfn.XLOOKUP($A25,Index!$B$2:$B$995,Index!$E$2:$E$995,"Not Found")),"")} | G25: {=IF(NOT(ISBLANK(A25)), ((_xlfn.XLOOKUP(A25,Index!$B$2:$B$995,Index!$F$2:$F$995,"Not Found"))*B25),"")}
C26: {=IF(NOT(ISBLANK($A26)), (_xlfn.XLOOKUP($A26,Index!$B$2:$B$995,Index!$C$2:$C$995,"Not Found")),"")} | D26: {=IF(NOT(ISBLANK(A26)), (_xlfn.XLOOKUP($A26,Index!$B$2:B$995,Index!$A$2:$A$995,"Not Found")),"")} | E26: {=IF(NOT(ISBLANK($A26)), (_xlfn.XLOOKUP($A26,Index!$B$2:$B$995,Index!$D$2:$D$995,"Not Found")),"")} | F26: {=IF(NOT(ISBLANK($A26)), (_xlfn.XLOOKUP($A26,Index!$B$2:$B$995,Index!$E$2:$E$995,"Not Found")),"")} | G26: {=IF(NOT(ISBLANK(A26)), ((_xlfn.XLOOKUP(A26,Index!$B$2:$B$995,Index!$F$2:$F$995,"Not Found"))*B26),"")}
C27: {=IF(NOT(ISBLANK($A27)), (_xlfn.XLOOKUP($A27,Index!$B$2:$B$995,Index!$C$2:$C$995,"Not Found")),"")} | D27: {=IF(NOT(ISBLANK(A27)), (_xlfn.XLOOKUP($A27,Index!$B$2:B$995,Index!$A$2:$A$995,"Not Found")),"")} | E27: {=IF(NOT(ISBLANK($A27)), (_xlfn.XLOOKUP($A27,Index!$B$2:$B$995,Index!$D$2:$D$995,"Not Found")),"")} | F27: {=IF(NOT(ISBLANK($A27)), (_xlfn.XLOOKUP($A27,Index!$B$2:$B$995,Index!$E$2:$E$995,"Not Found")),"")} | G27: {=IF(NOT(ISBLANK(A27)), ((_xlfn.XLOOKUP(A27,Index!$B$2:$B$995,Index!$F$2:$F$995,"Not Found"))*B27),"")}
C28: {=IF(NOT(ISBLANK($A28)), (_xlfn.XLOOKUP($A28,Index!$B$2:$B$995,Index!$C$2:$C$995,"Not Found")),"")} | D28: {=IF(NOT(ISBLANK(A28)), (_xlfn.XLOOKUP($A28,Index!$B$2:B$995,Index!$A$2:$A$995,"Not Found")),"")} | E28: {=IF(NOT(ISBLANK($A28)), (_xlfn.XLOOKUP($A28,Index!$B$2:$B$995,Index!$D$2:$D$995,"Not Found")),"")} | F28: {=IF(NOT(ISBLANK($A28)), (_xlfn.XLOOKUP($A28,Index!$B$2:$B$995,Index!$E$2:$E$995,"Not Found")),"")} | G28: {=IF(NOT(ISBLANK(A28)), ((_xlfn.XLOOKUP(A28,Index!$B$2:$B$995,Index!$F$2:$F$995,"Not Found"))*B28),"")}
C29: {=IF(NOT(ISBLANK($A29)), (_xlfn.XLOOKUP($A29,Index!$B$2:$B$995,Index!$C$2:$C$995,"Not Found")),"")} | D29: {=IF(NOT(ISBLANK(A29)), (_xlfn.XLOOKUP($A29,Index!$B$2:B$995,Index!$A$2:$A$995,"Not Found")),"")} | E29: {=IF(NOT(ISBLANK($A29)), (_xlfn.XLOOKUP($A29,Index!$B$2:$B$995,Index!$D$2:$D$995,"Not Found")),"")} | F29: {=IF(NOT(ISBLANK($A29)), (_xlfn.XLOOKUP($A29,Index!$B$2:$B$995,Index!$E$2:$E$995,"Not Found")),"")} | G29: {=IF(NOT(ISBLANK(A29)), ((_xlfn.XLOOKUP(A29,Index!$B$2:$B$995,Index!$F$2:$F$995,"Not Found"))*B29),"")}
C30: {=IF(NOT(ISBLANK($A30)), (_xlfn.XLOOKUP($A30,Index!$B$2:$B$995,Index!$C$2:$C$995,"Not Found")),"")} | D30: {=IF(NOT(ISBLANK(A30)), (_xlfn.XLOOKUP($A30,Index!$B$2:B$995,Index!$A$2:$A$995,"Not Found")),"")} | E30: {=IF(NOT(ISBLANK($A30)), (_xlfn.XLOOKUP($A30,Index!$B$2:$B$995,Index!$D$2:$D$995,"Not Found")),"")} | F30: {=IF(NOT(ISBLANK($A30)), (_xlfn.XLOOKUP($A30,Index!$B$2:$B$995,Index!$E$2:$E$995,"Not Found")),"")} | G30: {=IF(NOT(ISBLANK(A30)), ((_xlfn.XLOOKUP(A30,Index!$B$2:$B$995,Index!$F$2:$F$995,"Not Found"))*B30),"")}
C31: {=IF(NOT(ISBLANK($A31)), (_xlfn.XLOOKUP($A31,Index!$B$2:$B$995,Index!$C$2:$C$995,"Not Found")),"")} | D31: {=IF(NOT(ISBLANK(A31)), (_xlfn.XLOOKUP($A31,Index!$B$2:B$995,Index!$A$2:$A$995,"Not Found")),"")} | E31: {=IF(NOT(ISBLANK($A31)), (_xlfn.XLOOKUP($A31,Index!$B$2:$B$995,Index!$D$2:$D$995,"Not Found")),"")} | F31: {=IF(NOT(ISBLANK($A31)), (_xlfn.XLOOKUP($A31,Index!$B$2:$B$995,Index!$E$2:$E$995,"Not Found")),"")} | G31: {=IF(NOT(ISBLANK(A31)), ((_xlfn.XLOOKUP(A31,Index!$B$2:$B$995,Index!$F$2:$F$995,"Not Found"))*B31),"")}
C32: {=IF(NOT(ISBLANK($A32)), (_xlfn.XLOOKUP($A32,Index!$B$2:$B$995,Index!$C$2:$C$995,"Not Found")),"")} | D32: {=IF(NOT(ISBLANK(A32)), (_xlfn.XLOOKUP($A32,Index!$B$2:B$995,Index!$A$2:$A$995,"Not Found")),"")} | E32: {=IF(NOT(ISBLANK($A32)), (_xlfn.XLOOKUP($A32,Index!$B$2:$B$995,Index!$D$2:$D$995,"Not Found")),"")} | F32: {=IF(NOT(ISBLANK($A32)), (_xlfn.XLOOKUP($A32,Index!$B$2:$B$995,Index!$E$2:$E$995,"Not Found")),"")} | G32: {=IF(NOT(ISBLANK(A32)), ((_xlfn.XLOOKUP(A32,Index!$B$2:$B$995,Index!$F$2:$F$995,"Not Found"))*B32),"")}
C33: {=IF(NOT(ISBLANK($A33)), (_xlfn.XLOOKUP($A33,Index!$B$2:$B$995,Index!$C$2:$C$995,"Not Found")),"")} | D33: {=IF(NOT(ISBLANK(A33)), (_xlfn.XLOOKUP($A33,Index!$B$2:B$995,Index!$A$2:$A$995,"Not Found")),"")} | E33: {=IF(NOT(ISBLANK($A33)), (_xlfn.XLOOKUP($A33,Index!$B$2:$B$995,Index!$D$2:$D$995,"Not Found")),"")} | F33: {=IF(NOT(ISBLANK($A33)), (_xlfn.XLOOKUP($A33,Index!$B$2:$B$995,Index!$E$2:$E$995,"Not Found")),"")} | G33: {=IF(NOT(ISBLANK(A33)), ((_xlfn.XLOOKUP(A33,Index!$B$2:$B$995,Index!$F$2:$F$995,"Not Found"))*B33),"")}
C34: {=IF(NOT(ISBLANK($A34)), (_xlfn.XLOOKUP($A34,Index!$B$2:$B$995,Index!$C$2:$C$995,"Not Found")),"")} | D34: {=IF(NOT(ISBLANK(A34)), (_xlfn.XLOOKUP($A34,Index!$B$2:B$995,Index!$A$2:$A$995,"Not Found")),"")} | E34: {=IF(NOT(ISBLANK($A34)), (_xlfn.XLOOKUP($A34,Index!$B$2:$B$995,Index!$D$2:$D$995,"Not Found")),"")} | F34: {=IF(NOT(ISBLANK($A34)), (_xlfn.XLOOKUP($A34,Index!$B$2:$B$995,Index!$E$2:$E$995,"Not Found")),"")} | G34: {=IF(NOT(ISBLANK(A34)), ((_xlfn.XLOOKUP(A34,Index!$B$2:$B$995,Index!$F$2:$F$995,"Not Found"))*B34),"")}
C35: {=IF(NOT(ISBLANK($A35)), (_xlfn.XLOOKUP($A35,Index!$B$2:$B$995,Index!$C$2:$C$995,"Not Found")),"")} | D35: {=IF(NOT(ISBLANK(A35)), (_xlfn.XLOOKUP($A35,Index!$B$2:B$995,Index!$A$2:$A$995,"Not Found")),"")} | E35: {=IF(NOT(ISBLANK($A35)), (_xlfn.XLOOKUP($A35,Index!$B$2:$B$995,Index!$D$2:$D$995,"Not Found")),"")} | F35: {=IF(NOT(ISBLANK($A35)), (_xlfn.XLOOKUP($A35,Index!$B$2:$B$995,Index!$E$2:$E$995,"Not Found")),"")} | G35: {=IF(NOT(ISBLANK(A35)), ((_xlfn.XLOOKUP(A35,Index!$B$2:$B$995,Index!$F$2:$F$995,"Not Found"))*B35),"")}
C36: {=IF(NOT(ISBLANK($A36)), (_xlfn.XLOOKUP($A36,Index!$B$2:$B$995,Index!$C$2:$C$995,"Not Found")),"")} | D36: {=IF(NOT(ISBLANK(A36)), (_xlfn.XLOOKUP($A36,Index!$B$2:B$995,Index!$A$2:$A$995,"Not Found")),"")} | E36: {=IF(NOT(ISBLANK($A36)), (_xlfn.XLOOKUP($A36,Index!$B$2:$B$995,Index!$D$2:$D$995,"Not Found")),"")} | F36: {=IF(NOT(ISBLANK($A36)), (_xlfn.XLOOKUP($A36,Index!$B$2:$B$995,Index!$E$2:$E$995,"Not Found")),"")} | G36: {=IF(NOT(ISBLANK(A36)), ((_xlfn.XLOOKUP(A36,Index!$B$2:$B$995,Index!$F$2:$F$995,"Not Found"))*B36),"")}
... C77: {=IF(NOT(ISBLANK($A77)), (_xlfn.XLOOKUP($A77,Index!$B$2:$B$995,Index!$C$2:$C$995,"Not Found")),"")} | D77: {=IF(NOT(ISBLANK(A77)), (_xlfn.XLOOKUP($A77,Index!$B$2:B$995,Index!$A$2:$A$995,"Not Found")),"")} | E77: {=IF(NOT(ISBLANK($A77)), (_xlfn.XLOOKUP($A77,Index!$B$2:$B$995,Index!$D$2:$D$995,"Not Found")),"")} | F77: {=IF(NOT(ISBLANK($A77)), (_xlfn.XLOOKUP($A77,Index!$B$2:$B$995,Index!$E$2:$E$995,"Not Found")),"")} | G77: {=IF(NOT(ISBLANK(A77)), ((_xlfn.XLOOKUP(A77,Index!$B$2:$B$995,Index!$F$2:$F$995,"Not Found"))*B77),"")}

Sheet R T2-1
A1: Card | B1: Quantity | C1: Type | D1: ID | E1: Stage / Rarity | F1: Remaining Evo | G1: Feature Weight | I1: Card Total | K1: Type | L1: Num | M1: Basic | N1: S1 Max | O1: S1 Mid | P1: S2 | Q1: No Evolve
A2: Eevee R | B2: 4 | C2: {=IF(NOT(ISBLANK($A2)), (_xlfn.XLOOKUP($A2,Index!$B$2:$B$995,Index!$C$2:$C$995,"Not Found")),"")} -> C | D2: {=IF(NOT(ISBLANK(A2)), (_xlfn.XLOOKUP($A2,Index!$B$2:B$995,Index!$A$2:$A$995,"Not Found")),"")} -> base5-55 | E2: {=IF(NOT(ISBLANK($A2)), (_xlfn.XLOOKUP($A2,Index!$B$2:$B$995,Index!$D$2:$D$995,"Not Found")),"")} -> b | F2: {=IF(NOT(ISBLANK($A2)), (_xlfn.XLOOKUP($A2,Index!$B$2:$B$995,Index!$E$2:$E$995,"Not Found")),"")} -> y | G2: {=IF(NOT(ISBLANK(A2)), ((_xlfn.XLOOKUP(A2,Index!$B$2:$B$995,Index!$F$2:$F$995,"Not Found"))*B2),"")} -> 0 | I2: =SUM(B2:B38) -> 60 | K2: E | L2: =IF(NOT(ISBLANK(K2)), SUM(M2:P2), "") -> 6 | M2: =IF(NOT(ISBLANK($K2)), SUMIFS($B$2:$B$32, $E$2:$E$32, "B", $C$2:$C$32,$K2), "") -> 4 | N2: =IF(NOT(ISBLANK($K2)),SUMIFS($B$2:$B$32,$E$2:$E$32, "1", $C$2:$C$32,$K2,$F$2:$F$32,"N"), "") -> 2 | O2: =IF(NOT(ISBLANK($K2)),SUMIFS($B$2:$B$32,$E$2:$E$32, "1", $C$2:$C$32,$K2,$F$2:$F$32,"Y"), "") -> 0 | P2: =IF(NOT(ISBLANK($K2)),SUMIFS($B$2:$B$32,$E$2:$E$32, "2", $C$2:$C$32,$K2), "") -> 0 | Q2: =IF(NOT(ISBLANK($K2)),SUMIFS($B$2:$B$32,$E$2:$E$32, "B", $C$2:$C$32,$K2,$F$2:$F$32,"N"), "") -> 1
A3: Dark Jolteon | B3: 1 | C3: {=IF(NOT(ISBLANK($A3)), (_xlfn.XLOOKUP($A3,Index!$B$2:$B$995,Index!$C$2:$C$995,"Not Found")),"")} -> E | D3: {=IF(NOT(ISBLANK(A3)), (_xlfn.XLOOKUP($A3,Index!$B$2:B$995,Index!$A$2:$A$995,"Not Found")),"")} -> base5-38 | E3: {=IF(NOT(ISBLANK($A3)), (_xlfn.XLOOKUP($A3,Index!$B$2:$B$995,Index!$D$2:$D$995,"Not Found")),"")} -> 1 | F3: {=IF(NOT(ISBLANK($A3)), (_xlfn.XLOOKUP($A3,Index!$B$2:$B$995,Index!$E$2:$E$995,"Not Found")),"")} -> n | G3: {=IF(NOT(ISBLANK(A3)), ((_xlfn.XLOOKUP(A3,Index!$B$2:$B$995,Index!$F$2:$F$995,"Not Found"))*B3),"")} -> 2 | K3: R | L3: =IF(NOT(ISBLANK(K3)), SUM(M3:P3), "") -> 6 | M3: =IF(NOT(ISBLANK($K3)), SUMIFS($B$2:$B$32, $E$2:$E$32, "B", $C$2:$C$32,$K3), "") -> 4 | N3: =IF(NOT(ISBLANK($K3)),SUMIFS($B$2:$B$32,$E$2:$E$32, "1", $C$2:$C$32,$K3,$F$2:$F$32,"N"), "") -> 2 | O3: =IF(NOT(ISBLANK($K3)),SUMIFS($B$2:$B$32,$E$2:$E$32, "1", $C$2:$C$32,$K3,$F$2:$F$32,"Y"), "") -> 0 | P3: =IF(NOT(ISBLANK($K3)),SUMIFS($B$2:$B$32,$E$2:$E$32, "2", $C$2:$C$32,$K3), "") -> 0 | Q3: =IF(NOT(ISBLANK($K3)),SUMIFS($B$2:$B$32,$E$2:$E$32, "B", $C$2:$C$32,$K3,$F$2:$F$32,"N"), "") -> 1
A4: Dark Flareon | B4: 1 | C4: {=IF(NOT(ISBLANK($A4)), (_xlfn.XLOOKUP($A4,Index!$B$2:$B$995,Index!$C$2:$C$995,"Not Found")),"")} -> R | D4: {=IF(NOT(ISBLANK(A4)), (_xlfn.XLOOKUP($A4,Index!$B$2:B$995,Index!$A$2:$A$995,"Not Found")),"")} -> base5-35 | E4: {=IF(NOT(ISBLANK($A4)), (_xlfn.XLOOKUP($A4,Index!$B$2:$B$995,Index!$D$2:$D$995,"Not Found")),"")} -> 1 | F4: {=IF(NOT(ISBLANK($A4)), (_xlfn.XLOOKUP($A4,Index!$B$2:$B$995,Index!$E$2:$E$995,"Not Found")),"")} -> n | G4: {=IF(NOT(ISBLANK(A4)), ((_xlfn.XLOOKUP(A4,Index!$B$2:$B$995,Index!$F$2:$F$995,"Not Found"))*B4),"")} -> 1.5 | K4: W | L4: =IF(NOT(ISBLANK(K4)), SUM(M4:P4), "") -> 6 | M4: =IF(NOT(ISBLANK($K4)), SUMIFS($B$2:$B$32, $E$2:$E$32, "B", $C$2:$C$32,$K4), "") -> 4 | N4: =IF(NOT(ISBLANK($K4)),SUMIFS($B$2:$B$32,$E$2:$E$32, "1", $C$2:$C$32,$K4,$F$2:$F$32,"N"), "") -> 2 | O4: =IF(NOT(ISBLANK($K4)),SUMIFS($B$2:$B$32,$E$2:$E$32, "1", $C$2:$C$32,$K4,$F$2:$F$32,"Y"), "") -> 0 | P4: =IF(NOT(ISBLANK($K4)),SUMIFS($B$2:$B$32,$E$2:$E$32, "2", $C$2:$C$32,$K4), "") -> 0 | Q4: =IF(NOT(ISBLANK($K4)),SUMIFS($B$2:$B$32,$E$2:$E$32, "B", $C$2:$C$32,$K4,$F$2:$F$32,"N"), "") -> 1
A5: Dark Vaporeon | B5: 1 | C5: {=IF(NOT(ISBLANK($A5)), (_xlfn.XLOOKUP($A5,Index!$B$2:$B$995,Index!$C$2:$C$995,"Not Found")),"")} -> W | D5: {=IF(NOT(ISBLANK(A5)), (_xlfn.XLOOKUP($A5,Index!$B$2:B$995,Index!$A$2:$A$995,"Not Found")),"")} -> base5-45 | E5: {=IF(NOT(ISBLANK($A5)), (_xlfn.XLOOKUP($A5,Index!$B$2:$B$995,Index!$D$2:$D$995,"Not Found")),"")} -> 1 | F5: {=IF(NOT(ISBLANK($A5)), (_xlfn.XLOOKUP($A5,Index!$B$2:$B$995,Index!$E$2:$E$995,"Not Found")),"")} -> n | G5: {=IF(NOT(ISBLANK(A5)), ((_xlfn.XLOOKUP(A5,Index!$B$2:$B$995,Index!$F$2:$F$995,"Not Found"))*B5),"")} -> 1.5 | K5: C | L5: =IF(NOT(ISBLANK(K5)), SUM(M5:P5), "") -> 4 | M5: =IF(NOT(ISBLANK($K5)), SUMIFS($B$2:$B$32, $E$2:$E$32, "B", $C$2:$C$32,$K5), "") -> 4 | N5: =IF(NOT(ISBLANK($K5)),SUMIFS($B$2:$B$32,$E$2:$E$32, "1", $C$2:$C$32,$K5,$F$2:$F$32,"N"), "") -> 0 | O5: =IF(NOT(ISBLANK($K5)),SUMIFS($B$2:$B$32,$E$2:$E$32, "1", $C$2:$C$32,$K5,$F$2:$F$32,"Y"), "") -> 0 | P5: =IF(NOT(ISBLANK($K5)),SUMIFS($B$2:$B$32,$E$2:$E$32, "2", $C$2:$C$32,$K5), "") -> 0 | Q5: =IF(NOT(ISBLANK($K5)),SUMIFS($B$2:$B$32,$E$2:$E$32, "B", $C$2:$C$32,$K5,$F$2:$F$32,"N"), "") -> 0
A6: Magnemite R | B6: 3 | C6: {=IF(NOT(ISBLANK($A6)), (_xlfn.XLOOKUP($A6,Index!$B$2:$B$995,Index!$C$2:$C$995,"Not Found")),"")} -> E | D6: {=IF(NOT(ISBLANK(A6)), (_xlfn.XLOOKUP($A6,Index!$B$2:B$995,Index!$A$2:$A$995,"Not Found")),"")} -> base5-60 | E6: {=IF(NOT(ISBLANK($A6)), (_xlfn.XLOOKUP($A6,Index!$B$2:$B$995,Index!$D$2:$D$995,"Not Found")),"")} -> b | F6: {=IF(NOT(ISBLANK($A6)), (_xlfn.XLOOKUP($A6,Index!$B$2:$B$995,Index!$E$2:$E$995,"Not Found")),"")} -> y | G6: {=IF(NOT(ISBLANK(A6)), ((_xlfn.XLOOKUP(A6,Index!$B$2:$B$995,Index!$F$2:$F$995,"Not Found"))*B6),"")} -> 0 | L6: =IF(NOT(ISBLANK(K6)), SUM(M6:P6), "") | M6: =IF(NOT(ISBLANK($K6)), COUNTIFS($E$2:$E$32, "B", $C$2:$C$32,$K6), "") | N6: =IF(NOT(ISBLANK(K6)),COUNTIFS($E$2:$E$32, "1", $C$2:$C$32,$K6,$F$2:$F$32,"N"), "") | O6: =IF(NOT(ISBLANK($K6)),COUNTIFS($E$2:$E$32, "1", $C$2:$C$32,$K6,$F$2:$F$32,"Y"), "") | P6: =IF(NOT(ISBLANK($K6)),COUNTIFS($E$2:$E$32, "2", $C$2:$C$32,$K6), "") | Q6: =IF(NOT(ISBLANK($K6)),COUNTIFS($E$2:$E$32, "B", $C$2:$C$32,$K6,$F$2:$F$32,"N"), "")
A7: Dark Magneton NH | B7: 1 | C7: {=IF(NOT(ISBLANK($A7)), (_xlfn.XLOOKUP($A7,Index!$B$2:$B$995,Index!$C$2:$C$995,"Not Found")),"")} -> E | D7: {=IF(NOT(ISBLANK(A7)), (_xlfn.XLOOKUP($A7,Index!$B$2:B$995,Index!$A$2:$A$995,"Not Found")),"")} -> base5-28 | E7: {=IF(NOT(ISBLANK($A7)), (_xlfn.XLOOKUP($A7,Index!$B$2:$B$995,Index!$D$2:$D$995,"Not Found")),"")} -> 1 | F7: {=IF(NOT(ISBLANK($A7)), (_xlfn.XLOOKUP($A7,Index!$B$2:$B$995,Index!$E$2:$E$995,"Not Found")),"")} -> n | G7: {=IF(NOT(ISBLANK(A7)), ((_xlfn.XLOOKUP(A7,Index!$B$2:$B$995,Index!$F$2:$F$995,"Not Found"))*B7),"")} -> 2 | K7: Total | L7: =SUM(L2:L6) -> 22 | M7: =SUM(M2:M6) -> 16 | N7: =SUM(N2:N6) -> 6 | O7: =SUM(O2:O6) -> 0 | P7: =SUM(P2:P6) -> 0 | Q7: =SUM(Q2:Q6) -> 3
A8: Ponyta R | B8: 3 | C8: {=IF(NOT(ISBLANK($A8)), (_xlfn.XLOOKUP($A8,Index!$B$2:$B$995,Index!$C$2:$C$995,"Not Found")),"")} -> R | D8: {=IF(NOT(ISBLANK(A8)), (_xlfn.XLOOKUP($A8,Index!$B$2:B$995,Index!$A$2:$A$995,"Not Found")),"")} -> base5-64 | E8: {=IF(NOT(ISBLANK($A8)), (_xlfn.XLOOKUP($A8,Index!$B$2:$B$995,Index!$D$2:$D$995,"Not Found")),"")} -> b | F8: {=IF(NOT(ISBLANK($A8)), (_xlfn.XLOOKUP($A8,Index!$B$2:$B$995,Index!$E$2:$E$995,"Not Found")),"")} -> y | G8: {=IF(NOT(ISBLANK(A8)), ((_xlfn.XLOOKUP(A8,Index!$B$2:$B$995,Index!$F$2:$F$995,"Not Found"))*B8),"")} -> 0
A9: Dark Rapidash | B9: 1 | C9: {=IF(NOT(ISBLANK($A9)), (_xlfn.XLOOKUP($A9,Index!$B$2:$B$995,Index!$C$2:$C$995,"Not Found")),"")} -> R | D9: {=IF(NOT(ISBLANK(A9)), (_xlfn.XLOOKUP($A9,Index!$B$2:B$995,Index!$A$2:$A$995,"Not Found")),"")} -> base5-44 | E9: {=IF(NOT(ISBLANK($A9)), (_xlfn.XLOOKUP($A9,Index!$B$2:$B$995,Index!$D$2:$D$995,"Not Found")),"")} -> 1 | F9: {=IF(NOT(ISBLANK($A9)), (_xlfn.XLOOKUP($A9,Index!$B$2:$B$995,Index!$E$2:$E$995,"Not Found")),"")} -> n | G9: {=IF(NOT(ISBLANK(A9)), ((_xlfn.XLOOKUP(A9,Index!$B$2:$B$995,Index!$F$2:$F$995,"Not Found"))*B9),"")} -> 1.5 | M9: Common | N9: Uncommon | O9: Rare
A10: Tentacool | B10: 3 | C10: {=IF(NOT(ISBLANK($A10)), (_xlfn.XLOOKUP($A10,Index!$B$2:$B$995,Index!$C$2:$C$995,"Not Found")),"")} -> W | D10: {=IF(NOT(ISBLANK(A10)), (_xlfn.XLOOKUP($A10,Index!$B$2:B$995,Index!$A$2:$A$995,"Not Found")),"")} -> base3-56 | E10: {=IF(NOT(ISBLANK($A10)), (_xlfn.XLOOKUP($A10,Index!$B$2:$B$995,Index!$D$2:$D$995,"Not Found")),"")} -> b | F10: {=IF(NOT(ISBLANK($A10)), (_xlfn.XLOOKUP($A10,Index!$B$2:$B$995,Index!$E$2:$E$995,"Not Found")),"")} -> y | G10: {=IF(NOT(ISBLANK(A10)), ((_xlfn.XLOOKUP(A10,Index!$B$2:$B$995,Index!$F$2:$F$995,"Not Found"))*B10),"")} -> 0 | K10: Trainer | L10: =SUM(M10:P10) -> 10 | M10: =IF(NOT(ISBLANK($K10)), SUMIFS($B$2:$B$32,$E$2:$E$32, "C", $C$2:$C$32,"T"), "") -> 6 | N10: =IF(NOT(ISBLANK($K10)), SUMIFS($B$2:$B$32,$E$2:$E$32, "U", $C$2:$C$32,"T"), "") -> 3 | O10: =IF(NOT(ISBLANK($K$2)), SUMIFS($B$2:$B$32,$E$2:$E$32, "R", $C$2:$C$32,"T"), "") -> 1
A11: Tentacruel | B11: 1 | C11: {=IF(NOT(ISBLANK($A11)), (_xlfn.XLOOKUP($A11,Index!$B$2:$B$995,Index!$C$2:$C$995,"Not Found")),"")} -> W | D11: {=IF(NOT(ISBLANK(A11)), (_xlfn.XLOOKUP($A11,Index!$B$2:B$995,Index!$A$2:$A$995,"Not Found")),"")} -> base3-44 | E11: {=IF(NOT(ISBLANK($A11)), (_xlfn.XLOOKUP($A11,Index!$B$2:$B$995,Index!$D$2:$D$995,"Not Found")),"")} -> 1 | F11: {=IF(NOT(ISBLANK($A11)), (_xlfn.XLOOKUP($A11,Index!$B$2:$B$995,Index!$E$2:$E$995,"Not Found")),"")} -> n | G11: {=IF(NOT(ISBLANK(A11)), ((_xlfn.XLOOKUP(A11,Index!$B$2:$B$995,Index!$F$2:$F$995,"Not Found"))*B11),"")} -> 1.5 | K11: Energy | L11: =IF(NOT(ISBLANK($K$2)), SUMIFS($B$2:$B$32, $C$2:$C$32,"Energy"), "") -> 28
A12: E Energy | B12: 8 | C12: {=IF(NOT(ISBLANK($A12)), (_xlfn.XLOOKUP($A12,Index!$B$2:$B$995,Index!$C$2:$C$995,"Not Found")),"")} -> Energy | D12: {=IF(NOT(ISBLANK(A12)), (_xlfn.XLOOKUP($A12,Index!$B$2:B$995,Index!$A$2:$A$995,"Not Found")),"")} -> base1-100 | E12: {=IF(NOT(ISBLANK($A12)), (_xlfn.XLOOKUP($A12,Index!$B$2:$B$995,Index!$D$2:$D$995,"Not Found")),"")} | F12: {=IF(NOT(ISBLANK($A12)), (_xlfn.XLOOKUP($A12,Index!$B$2:$B$995,Index!$E$2:$E$995,"Not Found")),"")} | G12: {=IF(NOT(ISBLANK(A12)), ((_xlfn.XLOOKUP(A12,Index!$B$2:$B$995,Index!$F$2:$F$995,"Not Found"))*B12),"")} -> 0 | K12: Pokemon | L12: =L7 -> 22
A13: R Energy | B13: 8 | C13: {=IF(NOT(ISBLANK($A13)), (_xlfn.XLOOKUP($A13,Index!$B$2:$B$995,Index!$C$2:$C$995,"Not Found")),"")} -> Energy | D13: {=IF(NOT(ISBLANK(A13)), (_xlfn.XLOOKUP($A13,Index!$B$2:B$995,Index!$A$2:$A$995,"Not Found")),"")} -> base1-98 | E13: {=IF(NOT(ISBLANK($A13)), (_xlfn.XLOOKUP($A13,Index!$B$2:$B$995,Index!$D$2:$D$995,"Not Found")),"")} | F13: {=IF(NOT(ISBLANK($A13)), (_xlfn.XLOOKUP($A13,Index!$B$2:$B$995,Index!$E$2:$E$995,"Not Found")),"")} | G13: {=IF(NOT(ISBLANK(A13)), ((_xlfn.XLOOKUP(A13,Index!$B$2:$B$995,Index!$F$2:$F$995,"Not Found"))*B13),"")} -> 0
A14: W Energy | B14: 8 | C14: {=IF(NOT(ISBLANK($A14)), (_xlfn.XLOOKUP($A14,Index!$B$2:$B$995,Index!$C$2:$C$995,"Not Found")),"")} -> Energy | D14: {=IF(NOT(ISBLANK(A14)), (_xlfn.XLOOKUP($A14,Index!$B$2:B$995,Index!$A$2:$A$995,"Not Found")),"")} -> base1-102 | E14: {=IF(NOT(ISBLANK($A14)), (_xlfn.XLOOKUP($A14,Index!$B$2:$B$995,Index!$D$2:$D$995,"Not Found")),"")} | F14: {=IF(NOT(ISBLANK($A14)), (_xlfn.XLOOKUP($A14,Index!$B$2:$B$995,Index!$E$2:$E$995,"Not Found")),"")} | G14: {=IF(NOT(ISBLANK(A14)), ((_xlfn.XLOOKUP(A14,Index!$B$2:$B$995,Index!$F$2:$F$995,"Not Found"))*B14),"")} -> 0
A15: DC Energy | B15: 2 | C15: {=IF(NOT(ISBLANK($A15)), (_xlfn.XLOOKUP($A15,Index!$B$2:$B$995,Index!$C$2:$C$995,"Not Found")),"")} -> Energy | D15: {=IF(NOT(ISBLANK(A15)), (_xlfn.XLOOKUP($A15,Index!$B$2:B$995,Index!$A$2:$A$995,"Not Found")),"")} -> base1-96 | E15: {=IF(NOT(ISBLANK($A15)), (_xlfn.XLOOKUP($A15,Index!$B$2:$B$995,Index!$D$2:$D$995,"Not Found")),"")} | F15: {=IF(NOT(ISBLANK($A15)), (_xlfn.XLOOKUP($A15,Index!$B$2:$B$995,Index!$E$2:$E$995,"Not Found")),"")} | G15: {=IF(NOT(ISBLANK(A15)), ((_xlfn.XLOOKUP(A15,Index!$B$2:$B$995,Index!$F$2:$F$995,"Not Found"))*B15),"")} -> 0 | K15: Feature Weight:
A16: Magmar | B16: 1 | C16: {=IF(NOT(ISBLANK($A16)), (_xlfn.XLOOKUP($A16,Index!$B$2:$B$995,Index!$C$2:$C$995,"Not Found")),"")} -> R | D16: {=IF(NOT(ISBLANK(A16)), (_xlfn.XLOOKUP($A16,Index!$B$2:B$995,Index!$A$2:$A$995,"Not Found")),"")} -> base1-36 | E16: {=IF(NOT(ISBLANK($A16)), (_xlfn.XLOOKUP($A16,Index!$B$2:$B$995,Index!$D$2:$D$995,"Not Found")),"")} -> b | F16: {=IF(NOT(ISBLANK($A16)), (_xlfn.XLOOKUP($A16,Index!$B$2:$B$995,Index!$E$2:$E$995,"Not Found")),"")} -> n | G16: {=IF(NOT(ISBLANK(A16)), ((_xlfn.XLOOKUP(A16,Index!$B$2:$B$995,Index!$F$2:$F$995,"Not Found"))*B16),"")} -> 0 | K16: =K2 -> E | L16: =IF(NOT(ISBLANK($K2)), SUMIFS($G$2:$G$32, $C$2:$C$32,$K2), "") -> 5
A17: Electabuzz | B17: 1 | C17: {=IF(NOT(ISBLANK($A17)), (_xlfn.XLOOKUP($A17,Index!$B$2:$B$995,Index!$C$2:$C$995,"Not Found")),"")} -> E | D17: {=IF(NOT(ISBLANK(A17)), (_xlfn.XLOOKUP($A17,Index!$B$2:B$995,Index!$A$2:$A$995,"Not Found")),"")} -> base1-20 | E17: {=IF(NOT(ISBLANK($A17)), (_xlfn.XLOOKUP($A17,Index!$B$2:$B$995,Index!$D$2:$D$995,"Not Found")),"")} -> b | F17: {=IF(NOT(ISBLANK($A17)), (_xlfn.XLOOKUP($A17,Index!$B$2:$B$995,Index!$E$2:$E$995,"Not Found")),"")} -> n | G17: {=IF(NOT(ISBLANK(A17)), ((_xlfn.XLOOKUP(A17,Index!$B$2:$B$995,Index!$F$2:$F$995,"Not Found"))*B17),"")} -> 1 | K17: =K3 -> R | L17: =IF(NOT(ISBLANK($K3)), SUMIFS($G$2:$G$32, $C$2:$C$32,$K3), "") -> 3
A18: Lapras | B18: 1 | C18: {=IF(NOT(ISBLANK($A18)), (_xlfn.XLOOKUP($A18,Index!$B$2:$B$995,Index!$C$2:$C$995,"Not Found")),"")} -> W | D18: {=IF(NOT(ISBLANK(A18)), (_xlfn.XLOOKUP($A18,Index!$B$2:B$995,Index!$A$2:$A$995,"Not Found")),"")} -> base3-10 | E18: {=IF(NOT(ISBLANK($A18)), (_xlfn.XLOOKUP($A18,Index!$B$2:$B$995,Index!$D$2:$D$995,"Not Found")),"")} -> b | F18: {=IF(NOT(ISBLANK($A18)), (_xlfn.XLOOKUP($A18,Index!$B$2:$B$995,Index!$E$2:$E$995,"Not Found")),"")} -> n | G18: {=IF(NOT(ISBLANK(A18)), ((_xlfn.XLOOKUP(A18,Index!$B$2:$B$995,Index!$F$2:$F$995,"Not Found"))*B18),"")} -> 1 | K18: =K4 -> W | L18: =IF(NOT(ISBLANK($K4)), SUMIFS($G$2:$G$32, $C$2:$C$32,$K4), "") -> 4
A19: Rainbow Energy NH | B19: 2 | C19: {=IF(NOT(ISBLANK($A19)), (_xlfn.XLOOKUP($A19,Index!$B$2:$B$995,Index!$C$2:$C$995,"Not Found")),"")} -> Energy | D19: {=IF(NOT(ISBLANK(A19)), (_xlfn.XLOOKUP($A19,Index!$B$2:B$995,Index!$A$2:$A$995,"Not Found")),"")} -> base5-80 | E19: {=IF(NOT(ISBLANK($A19)), (_xlfn.XLOOKUP($A19,Index!$B$2:$B$995,Index!$D$2:$D$995,"Not Found")),"")} | F19: {=IF(NOT(ISBLANK($A19)), (_xlfn.XLOOKUP($A19,Index!$B$2:$B$995,Index!$E$2:$E$995,"Not Found")),"")} | G19: {=IF(NOT(ISBLANK(A19)), ((_xlfn.XLOOKUP(A19,Index!$B$2:$B$995,Index!$F$2:$F$995,"Not Found"))*B19),"")} -> 0 | K19: =K5 -> C | L19: =IF(NOT(ISBLANK($K5)), SUMIFS($G$2:$G$32, $C$2:$C$32,$K5), "") -> 0
A20: Energy Search | B20: 2 | C20: {=IF(NOT(ISBLANK($A20)), (_xlfn.XLOOKUP($A20,Index!$B$2:$B$995,Index!$C$2:$C$995,"Not Found")),"")} -> T | D20: {=IF(NOT(ISBLANK(A20)), (_xlfn.XLOOKUP($A20,Index!$B$2:B$995,Index!$A$2:$A$995,"Not Found")),"")} -> base3-59 | E20: {=IF(NOT(ISBLANK($A20)), (_xlfn.XLOOKUP($A20,Index!$B$2:$B$995,Index!$D$2:$D$995,"Not Found")),"")} -> c | F20: {=IF(NOT(ISBLANK($A20)), (_xlfn.XLOOKUP($A20,Index!$B$2:$B$995,Index!$E$2:$E$995,"Not Found")),"")} | G20: {=IF(NOT(ISBLANK(A20)), ((_xlfn.XLOOKUP(A20,Index!$B$2:$B$995,Index!$F$2:$F$995,"Not Found"))*B20),"")} -> #VALUE! | K20: =K6
A21: Energy Retrieval | B21: 2 | C21: {=IF(NOT(ISBLANK($A21)), (_xlfn.XLOOKUP($A21,Index!$B$2:$B$995,Index!$C$2:$C$995,"Not Found")),"")} -> T | D21: {=IF(NOT(ISBLANK(A21)), (_xlfn.XLOOKUP($A21,Index!$B$2:B$995,Index!$A$2:$A$995,"Not Found")),"")} -> base1-81 | E21: {=IF(NOT(ISBLANK($A21)), (_xlfn.XLOOKUP($A21,Index!$B$2:$B$995,Index!$D$2:$D$995,"Not Found")),"")} -> u | F21: {=IF(NOT(ISBLANK($A21)), (_xlfn.XLOOKUP($A21,Index!$B$2:$B$995,Index!$E$2:$E$995,"Not Found")),"")} | G21: {=IF(NOT(ISBLANK(A21)), ((_xlfn.XLOOKUP(A21,Index!$B$2:$B$995,Index!$F$2:$F$995,"Not Found"))*B21),"")} -> #VALUE! | K21: Total: | L21: =SUM(L15:L19) -> 12
A22: Bill | B22: 2 | C22: {=IF(NOT(ISBLANK($A22)), (_xlfn.XLOOKUP($A22,Index!$B$2:$B$995,Index!$C$2:$C$995,"Not Found")),"")} -> T | D22: {=IF(NOT(ISBLANK(A22)), (_xlfn.XLOOKUP($A22,Index!$B$2:B$995,Index!$A$2:$A$995,"Not Found")),"")} -> base1-91 | E22: {=IF(NOT(ISBLANK($A22)), (_xlfn.XLOOKUP($A22,Index!$B$2:$B$995,Index!$D$2:$D$995,"Not Found")),"")} -> c | F22: {=IF(NOT(ISBLANK($A22)), (_xlfn.XLOOKUP($A22,Index!$B$2:$B$995,Index!$E$2:$E$995,"Not Found")),"")} | G22: {=IF(NOT(ISBLANK(A22)), ((_xlfn.XLOOKUP(A22,Index!$B$2:$B$995,Index!$F$2:$F$995,"Not Found"))*B22),"")} -> #VALUE!
A23: Professor Oak | B23: 1 | C23: {=IF(NOT(ISBLANK($A23)), (_xlfn.XLOOKUP($A23,Index!$B$2:$B$995,Index!$C$2:$C$995,"Not Found")),"")} -> T | D23: {=IF(NOT(ISBLANK(A23)), (_xlfn.XLOOKUP($A23,Index!$B$2:B$995,Index!$A$2:$A$995,"Not Found")),"")} -> base1-88 | E23: {=IF(NOT(ISBLANK($A23)), (_xlfn.XLOOKUP($A23,Index!$B$2:$B$995,Index!$D$2:$D$995,"Not Found")),"")} -> u | F23: {=IF(NOT(ISBLANK($A23)), (_xlfn.XLOOKUP($A23,Index!$B$2:$B$995,Index!$E$2:$E$995,"Not Found")),"")} | G23: {=IF(NOT(ISBLANK(A23)), ((_xlfn.XLOOKUP(A23,Index!$B$2:$B$995,Index!$F$2:$F$995,"Not Found"))*B23),"")} -> #VALUE!
A24: Sleep! | B24: 1 | C24: {=IF(NOT(ISBLANK($A24)), (_xlfn.XLOOKUP($A24,Index!$B$2:$B$995,Index!$C$2:$C$995,"Not Found")),"")} -> T | D24: {=IF(NOT(ISBLANK(A24)), (_xlfn.XLOOKUP($A24,Index!$B$2:B$995,Index!$A$2:$A$995,"Not Found")),"")} -> base5-79 | E24: {=IF(NOT(ISBLANK($A24)), (_xlfn.XLOOKUP($A24,Index!$B$2:$B$995,Index!$D$2:$D$995,"Not Found")),"")} -> c | F24: {=IF(NOT(ISBLANK($A24)), (_xlfn.XLOOKUP($A24,Index!$B$2:$B$995,Index!$E$2:$E$995,"Not Found")),"")} | G24: {=IF(NOT(ISBLANK(A24)), ((_xlfn.XLOOKUP(A24,Index!$B$2:$B$995,Index!$F$2:$F$995,"Not Found"))*B24),"")} -> #VALUE! | K24: Cover Card: | L24: Eevee R
A25: Switch | B25: 1 | C25: {=IF(NOT(ISBLANK($A25)), (_xlfn.XLOOKUP($A25,Index!$B$2:$B$995,Index!$C$2:$C$995,"Not Found")),"")} -> T | D25: {=IF(NOT(ISBLANK(A25)), (_xlfn.XLOOKUP($A25,Index!$B$2:B$995,Index!$A$2:$A$995,"Not Found")),"")} -> base1-95 | E25: {=IF(NOT(ISBLANK($A25)), (_xlfn.XLOOKUP($A25,Index!$B$2:$B$995,Index!$D$2:$D$995,"Not Found")),"")} -> c | F25: {=IF(NOT(ISBLANK($A25)), (_xlfn.XLOOKUP($A25,Index!$B$2:$B$995,Index!$E$2:$E$995,"Not Found")),"")} | G25: {=IF(NOT(ISBLANK(A25)), ((_xlfn.XLOOKUP(A25,Index!$B$2:$B$995,Index!$F$2:$F$995,"Not Found"))*B25),"")} -> #VALUE!
A26: Pokemon Trader | B26: 1 | C26: {=IF(NOT(ISBLANK($A26)), (_xlfn.XLOOKUP($A26,Index!$B$2:$B$995,Index!$C$2:$C$995,"Not Found")),"")} -> T | D26: {=IF(NOT(ISBLANK(A26)), (_xlfn.XLOOKUP($A26,Index!$B$2:B$995,Index!$A$2:$A$995,"Not Found")),"")} -> base1-77 | E26: {=IF(NOT(ISBLANK($A26)), (_xlfn.XLOOKUP($A26,Index!$B$2:$B$995,Index!$D$2:$D$995,"Not Found")),"")} -> r | F26: {=IF(NOT(ISBLANK($A26)), (_xlfn.XLOOKUP($A26,Index!$B$2:$B$995,Index!$E$2:$E$995,"Not Found")),"")} | G26: {=IF(NOT(ISBLANK(A26)), ((_xlfn.XLOOKUP(A26,Index!$B$2:$B$995,Index!$F$2:$F$995,"Not Found"))*B26),"")} -> #VALUE!
C27: {=IF(NOT(ISBLANK($A27)), (_xlfn.XLOOKUP($A27,Index!$B$2:$B$995,Index!$C$2:$C$995,"Not Found")),"")} | D27: {=IF(NOT(ISBLANK(A27)), (_xlfn.XLOOKUP($A27,Index!$B$2:B$995,Index!$A$2:$A$995,"Not Found")),"")} | E27: {=IF(NOT(ISBLANK($A27)), (_xlfn.XLOOKUP($A27,Index!$B$2:$B$995,Index!$D$2:$D$995,"Not Found")),"")} | F27: {=IF(NOT(ISBLANK($A27)), (_xlfn.XLOOKUP($A27,Index!$B$2:$B$995,Index!$E$2:$E$995,"Not Found")),"")} | G27: {=IF(NOT(ISBLANK(A27)), ((_xlfn.XLOOKUP(A27,Index!$B$2:$B$995,Index!$F$2:$F$995,"Not Found"))*B27),"")}
C28: {=IF(NOT(ISBLANK($A28)), (_xlfn.XLOOKUP($A28,Index!$B$2:$B$995,Index!$C$2:$C$995,"Not Found")),"")} | D28: {=IF(NOT(ISBLANK(A28)), (_xlfn.XLOOKUP($A28,Index!$B$2:B$995,Index!$A$2:$A$995,"Not Found")),"")} | E28: {=IF(NOT(ISBLANK($A28)), (_xlfn.XLOOKUP($A28,Index!$B$2:$B$995,Index!$D$2:$D$995,"Not Found")),"")} | F28: {=IF(NOT(ISBLANK($A28)), (_xlfn.XLOOKUP($A28,Index!$B$2:$B$995,Index!$E$2:$E$995,"Not Found")),"")} | G28: {=IF(NOT(ISBLANK(A28)), ((_xlfn.XLOOKUP(A28,Index!$B$2:$B$995,Index!$F$2:$F$995,"Not Found"))*B28),"")}
C29: {=IF(NOT(ISBLANK($A29)), (_xlfn.XLOOKUP($A29,Index!$B$2:$B$995,Index!$C$2:$C$995,"Not Found")),"")} | D29: {=IF(NOT(ISBLANK(A29)), (_xlfn.XLOOKUP($A29,Index!$B$2:B$995,Index!$A$2:$A$995,"Not Found")),"")} | E29: {=IF(NOT(ISBLANK($A29)), (_xlfn.XLOOKUP($A29,Index!$B$2:$B$995,Index!$D$2:$D$995,"Not Found")),"")} | F29: {=IF(NOT(ISBLANK($A29)), (_xlfn.XLOOKUP($A29,Index!$B$2:$B$995,Index!$E$2:$E$995,"Not Found")),"")} | G29: {=IF(NOT(ISBLANK(A29)), ((_xlfn.XLOOKUP(A29,Index!$B$2:$B$995,Index!$F$2:$F$995,"Not Found"))*B29),"")}
C30: {=IF(NOT(ISBLANK($A30)), (_xlfn.XLOOKUP($A30,Index!$B$2:$B$995,Index!$C$2:$C$995,"Not Found")),"")} | D30: {=IF(NOT(ISBLANK(A30)), (_xlfn.XLOOKUP($A30,Index!$B$2:B$995,Index!$A$2:$A$995,"Not Found")),"")} | E30: {=IF(NOT(ISBLANK($A30)), (_xlfn.XLOOKUP($A30,Index!$B$2:$B$995,Index!$D$2:$D$995,"Not Found")),"")} | F30: {=IF(NOT(ISBLANK($A30)), (_xlfn.XLOOKUP($A30,Index!$B$2:$B$995,Index!$E$2:$E$995,"Not Found")),"")} | G30: {=IF(NOT(ISBLANK(A30)), ((_xlfn.XLOOKUP(A30,Index!$B$2:$B$995,Index!$F$2:$F$995,"Not Found"))*B30),"")}
C31: {=IF(NOT(ISBLANK($A31)), (_xlfn.XLOOKUP($A31,Index!$B$2:$B$995,Index!$C$2:$C$995,"Not Found")),"")} | D31: {=IF(NOT(ISBLANK(A31)), (_xlfn.XLOOKUP($A31,Index!$B$2:B$995,Index!$A$2:$A$995,"Not Found")),"")} | E31: {=IF(NOT(ISBLANK($A31)), (_xlfn.XLOOKUP($A31,Index!$B$2:$B$995,Index!$D$2:$D$995,"Not Found")),"")} | F31: {=IF(NOT(ISBLANK($A31)), (_xlfn.XLOOKUP($A31,Index!$B$2:$B$995,Index!$E$2:$E$995,"Not Found")),"")} | G31: {=IF(NOT(ISBLANK(A31)), ((_xlfn.XLOOKUP(A31,Index!$B$2:$B$995,Index!$F$2:$F$995,"Not Found"))*B31),"")}
C32: {=IF(NOT(ISBLANK($A32)), (_xlfn.XLOOKUP($A32,Index!$B$2:$B$995,Index!$C$2:$C$995,"Not Found")),"")} | D32: {=IF(NOT(ISBLANK(A32)), (_xlfn.XLOOKUP($A32,Index!$B$2:B$995,Index!$A$2:$A$995,"Not Found")),"")} | E32: {=IF(NOT(ISBLANK($A32)), (_xlfn.XLOOKUP($A32,Index!$B$2:$B$995,Index!$D$2:$D$995,"Not Found")),"")} | F32: {=IF(NOT(ISBLANK($A32)), (_xlfn.XLOOKUP($A32,Index!$B$2:$B$995,Index!$E$2:$E$995,"Not Found")),"")} | G32: {=IF(NOT(ISBLANK(A32)), ((_xlfn.XLOOKUP(A32,Index!$B$2:$B$995,Index!$F$2:$F$995,"Not Found"))*B32),"")}
C33: {=IF(NOT(ISBLANK($A33)), (_xlfn.XLOOKUP($A33,Index!$B$2:$B$995,Index!$C$2:$C$995,"Not Found")),"")} | D33: {=IF(NOT(ISBLANK(A33)), (_xlfn.XLOOKUP($A33,Index!$B$2:B$995,Index!$A$2:$A$995,"Not Found")),"")} | E33: {=IF(NOT(ISBLANK($A33)), (_xlfn.XLOOKUP($A33,Index!$B$2:$B$995,Index!$D$2:$D$995,"Not Found")),"")} | F33: {=IF(NOT(ISBLANK($A33)), (_xlfn.XLOOKUP($A33,Index!$B$2:$B$995,Index!$E$2:$E$995,"Not Found")),"")} | G33: {=IF(NOT(ISBLANK(A33)), ((_xlfn.XLOOKUP(A33,Index!$B$2:$B$995,Index!$F$2:$F$995,"Not Found"))*B33),"")}
C34: {=IF(NOT(ISBLANK($A34)), (_xlfn.XLOOKUP($A34,Index!$B$2:$B$995,Index!$C$2:$C$995,"Not Found")),"")} | D34: {=IF(NOT(ISBLANK(A34)), (_xlfn.XLOOKUP($A34,Index!$B$2:B$995,Index!$A$2:$A$995,"Not Found")),"")} | E34: {=IF(NOT(ISBLANK($A34)), (_xlfn.XLOOKUP($A34,Index!$B$2:$B$995,Index!$D$2:$D$995,"Not Found")),"")} | F34: {=IF(NOT(ISBLANK($A34)), (_xlfn.XLOOKUP($A34,Index!$B$2:$B$995,Index!$E$2:$E$995,"Not Found")),"")} | G34: {=IF(NOT(ISBLANK(A34)), ((_xlfn.XLOOKUP(A34,Index!$B$2:$B$995,Index!$F$2:$F$995,"Not Found"))*B34),"")}
C35: {=IF(NOT(ISBLANK($A35)), (_xlfn.XLOOKUP($A35,Index!$B$2:$B$995,Index!$C$2:$C$995,"Not Found")),"")} | D35: {=IF(NOT(ISBLANK(A35)), (_xlfn.XLOOKUP($A35,Index!$B$2:B$995,Index!$A$2:$A$995,"Not Found")),"")} | E35: {=IF(NOT(ISBLANK($A35)), (_xlfn.XLOOKUP($A35,Index!$B$2:$B$995,Index!$D$2:$D$995,"Not Found")),"")} | F35: {=IF(NOT(ISBLANK($A35)), (_xlfn.XLOOKUP($A35,Index!$B$2:$B$995,Index!$E$2:$E$995,"Not Found")),"")} | G35: {=IF(NOT(ISBLANK(A35)), ((_xlfn.XLOOKUP(A35,Index!$B$2:$B$995,Index!$F$2:$F$995,"Not Found"))*B35),"")}
C36: {=IF(NOT(ISBLANK($A36)), (_xlfn.XLOOKUP($A36,Index!$B$2:$B$995,Index!$C$2:$C$995,"Not Found")),"")} | D36: {=IF(NOT(ISBLANK(A36)), (_xlfn.XLOOKUP($A36,Index!$B$2:B$995,Index!$A$2:$A$995,"Not Found")),"")} | E36: {=IF(NOT(ISBLANK($A36)), (_xlfn.XLOOKUP($A36,Index!$B$2:$B$995,Index!$D$2:$D$995,"Not Found")),"")} | F36: {=IF(NOT(ISBLANK($A36)), (_xlfn.XLOOKUP($A36,Index!$B$2:$B$995,Index!$E$2:$E$995,"Not Found")),"")} | G36: {=IF(NOT(ISBLANK(A36)), ((_xlfn.XLOOKUP(A36,Index!$B$2:$B$995,Index!$F$2:$F$995,"Not Found"))*B36),"")}
C37: {=IF(NOT(ISBLANK($A37)), (_xlfn.XLOOKUP($A37,Index!$B$2:$B$995,Index!$C$2:$C$995,"Not Found")),"")} | D37: {=IF(NOT(ISBLANK(A37)), (_xlfn.XLOOKUP($A37,Index!$B$2:B$995,Index!$A$2:$A$995,"Not Found")),"")} | E37: {=IF(NOT(ISBLANK($A37)), (_xlfn.XLOOKUP($A37,Index!$B$2:$B$995,Index!$D$2:$D$995,"Not Found")),"")} | F37: {=IF(NOT(ISBLANK($A37)), (_xlfn.XLOOKUP($A37,Index!$B$2:$B$995,Index!$E$2:$E$995,"Not Found")),"")} | G37: {=IF(NOT(ISBLANK(A37)), ((_xlfn.XLOOKUP(A37,Index!$B$2:$B$995,Index!$F$2:$F$995,"Not Found"))*B37),"")}
C38: {=IF(NOT(ISBLANK($A38)), (_xlfn.XLOOKUP($A38,Index!$B$2:$B$995,Index!$C$2:$C$995,"Not Found")),"")} | D38: {=IF(NOT(ISBLANK(A38)), (_xlfn.XLOOKUP($A38,Index!$B$2:B$995,Index!$A$2:$A$995,"Not Found")),"")} | E38: {=IF(NOT(ISBLANK($A38)), (_xlfn.XLOOKUP($A38,Index!$B$2:$B$995,Index!$D$2:$D$995,"Not Found")),"")} | F38: {=IF(NOT(ISBLANK($A38)), (_xlfn.XLOOKUP($A38,Index!$B$2:$B$995,Index!$E$2:$E$995,"Not Found")),"")} | G38: {=IF(NOT(ISBLANK(A38)), ((_xlfn.XLOOKUP(A38,Index!$B$2:$B$995,Index!$F$2:$F$995,"Not Found"))*B38),"")}
... C77: {=IF(NOT(ISBLANK($A77)), (_xlfn.XLOOKUP($A77,Index!$B$2:$B$995,Index!$C$2:$C$995,"Not Found")),"")} | D77: {=IF(NOT(ISBLANK(A77)), (_xlfn.XLOOKUP($A77,Index!$B$2:B$995,Index!$A$2:$A$995,"Not Found")),"")} | E77: {=IF(NOT(ISBLANK($A77)), (_xlfn.XLOOKUP($A77,Index!$B$2:$B$995,Index!$D$2:$D$995,"Not Found")),"")} | F77: {=IF(NOT(ISBLANK($A77)), (_xlfn.XLOOKUP($A77,Index!$B$2:$B$995,Index!$E$2:$E$995,"Not Found")),"")} | G77: {=IF(NOT(ISBLANK(A77)), ((_xlfn.XLOOKUP(A77,Index!$B$2:$B$995,Index!$F$2:$F$995,"Not Found"))*B77),"")}

Sheet R T2-2
A1: Card | B1: Quantity | C1: Type | D1: ID | E1: Stage / Rarity | F1: Remaining Evo | G1: Feature Weight | I1: Card Total | K1: Type | L1: Num | M1: Basic | N1: S1 Max | O1: S1 Mid | P1: S2 | Q1: No Evolve
A2: Pikachu B2 | B2: 2 | C2: {=IF(NOT(ISBLANK($A2)), (_xlfn.XLOOKUP($A2,Index!$B$2:$B$995,Index!$C$2:$C$995,"Not Found")),"")} -> E | D2: {=IF(NOT(ISBLANK(A2)), (_xlfn.XLOOKUP($A2,Index!$B$2:B$995,Index!$A$2:$A$995,"Not Found")),"")} -> base2-60 | E2: {=IF(NOT(ISBLANK($A2)), (_xlfn.XLOOKUP($A2,Index!$B$2:$B$995,Index!$D$2:$D$995,"Not Found")),"")} -> b | F2: {=IF(NOT(ISBLANK($A2)), (_xlfn.XLOOKUP($A2,Index!$B$2:$B$995,Index!$E$2:$E$995,"Not Found")),"")} -> y | G2: {=IF(NOT(ISBLANK(A2)), ((_xlfn.XLOOKUP(A2,Index!$B$2:$B$995,Index!$F$2:$F$995,"Not Found"))*B2),"")} -> 0 | I2: =SUM(B2:B38) -> 60 | K2: E | L2: =IF(NOT(ISBLANK(K2)), SUM(M2:P2), "") -> 10 | M2: =IF(NOT(ISBLANK($K2)), SUMIFS($B$2:$B$32, $E$2:$E$32, "B", $C$2:$C$32,$K2), "") -> 7 | N2: =IF(NOT(ISBLANK($K2)),SUMIFS($B$2:$B$32,$E$2:$E$32, "1", $C$2:$C$32,$K2,$F$2:$F$32,"N"), "") -> 3 | O2: =IF(NOT(ISBLANK($K2)),SUMIFS($B$2:$B$32,$E$2:$E$32, "1", $C$2:$C$32,$K2,$F$2:$F$32,"Y"), "") -> 0 | P2: =IF(NOT(ISBLANK($K2)),SUMIFS($B$2:$B$32,$E$2:$E$32, "2", $C$2:$C$32,$K2), "") -> 0 | Q2: =IF(NOT(ISBLANK($K2)),SUMIFS($B$2:$B$32,$E$2:$E$32, "B", $C$2:$C$32,$K2,$F$2:$F$32,"N"), "") -> 0
A3: Pikachu | B3: 2 | C3: {=IF(NOT(ISBLANK($A3)), (_xlfn.XLOOKUP($A3,Index!$B$2:$B$995,Index!$C$2:$C$995,"Not Found")),"")} -> E | D3: {=IF(NOT(ISBLANK(A3)), (_xlfn.XLOOKUP($A3,Index!$B$2:B$995,Index!$A$2:$A$995,"Not Found")),"")} -> base1-58 | E3: {=IF(NOT(ISBLANK($A3)), (_xlfn.XLOOKUP($A3,Index!$B$2:$B$995,Index!$D$2:$D$995,"Not Found")),"")} -> b | F3: {=IF(NOT(ISBLANK($A3)), (_xlfn.XLOOKUP($A3,Index!$B$2:$B$995,Index!$E$2:$E$995,"Not Found")),"")} -> y | G3: {=IF(NOT(ISBLANK(A3)), ((_xlfn.XLOOKUP(A3,Index!$B$2:$B$995,Index!$F$2:$F$995,"Not Found"))*B3),"")} -> 0 | K3: G | L3: =IF(NOT(ISBLANK(K3)), SUM(M3:P3), "") -> 9 | M3: =IF(NOT(ISBLANK($K3)), SUMIFS($B$2:$B$32, $E$2:$E$32, "B", $C$2:$C$32,$K3), "") -> 6 | N3: =IF(NOT(ISBLANK($K3)),SUMIFS($B$2:$B$32,$E$2:$E$32, "1", $C$2:$C$32,$K3,$F$2:$F$32,"N"), "") -> 3 | O3: =IF(NOT(ISBLANK($K3)),SUMIFS($B$2:$B$32,$E$2:$E$32, "1", $C$2:$C$32,$K3,$F$2:$F$32,"Y"), "") -> 0 | P3: =IF(NOT(ISBLANK($K3)),SUMIFS($B$2:$B$32,$E$2:$E$32, "2", $C$2:$C$32,$K3), "") -> 0 | Q3: =IF(NOT(ISBLANK($K3)),SUMIFS($B$2:$B$32,$E$2:$E$32, "B", $C$2:$C$32,$K3,$F$2:$F$32,"N"), "") -> 0
A4: Dark Raichu | B4: 2 | C4: {=IF(NOT(ISBLANK($A4)), (_xlfn.XLOOKUP($A4,Index!$B$2:$B$995,Index!$C$2:$C$995,"Not Found")),"")} -> E | D4: {=IF(NOT(ISBLANK(A4)), (_xlfn.XLOOKUP($A4,Index!$B$2:B$995,Index!$A$2:$A$995,"Not Found")),"")} -> base5-83 | E4: {=IF(NOT(ISBLANK($A4)), (_xlfn.XLOOKUP($A4,Index!$B$2:$B$995,Index!$D$2:$D$995,"Not Found")),"")} -> 1 | F4: {=IF(NOT(ISBLANK($A4)), (_xlfn.XLOOKUP($A4,Index!$B$2:$B$995,Index!$E$2:$E$995,"Not Found")),"")} -> n | G4: {=IF(NOT(ISBLANK(A4)), ((_xlfn.XLOOKUP(A4,Index!$B$2:$B$995,Index!$F$2:$F$995,"Not Found"))*B4),"")} -> 3 | K4: C | L4: =IF(NOT(ISBLANK(K4)), SUM(M4:P4), "") -> 3 | M4: =IF(NOT(ISBLANK($K4)), SUMIFS($B$2:$B$32, $E$2:$E$32, "B", $C$2:$C$32,$K4), "") -> 2 | N4: =IF(NOT(ISBLANK($K4)),SUMIFS($B$2:$B$32,$E$2:$E$32, "1", $C$2:$C$32,$K4,$F$2:$F$32,"N"), "") -> 1 | O4: =IF(NOT(ISBLANK($K4)),SUMIFS($B$2:$B$32,$E$2:$E$32, "1", $C$2:$C$32,$K4,$F$2:$F$32,"Y"), "") -> 0 | P4: =IF(NOT(ISBLANK($K4)),SUMIFS($B$2:$B$32,$E$2:$E$32, "2", $C$2:$C$32,$K4), "") -> 0 | Q4: =IF(NOT(ISBLANK($K4)),SUMIFS($B$2:$B$32,$E$2:$E$32, "B", $C$2:$C$32,$K4,$F$2:$F$32,"N"), "") -> 0
A5: Voltorb R | B5: 3 | C5: {=IF(NOT(ISBLANK($A5)), (_xlfn.XLOOKUP($A5,Index!$B$2:$B$995,Index!$C$2:$C$995,"Not Found")),"")} -> E | D5: {=IF(NOT(ISBLANK(A5)), (_xlfn.XLOOKUP($A5,Index!$B$2:B$995,Index!$A$2:$A$995,"Not Found")),"")} -> base5-69 | E5: {=IF(NOT(ISBLANK($A5)), (_xlfn.XLOOKUP($A5,Index!$B$2:$B$995,Index!$D$2:$D$995,"Not Found")),"")} -> b | F5: {=IF(NOT(ISBLANK($A5)), (_xlfn.XLOOKUP($A5,Index!$B$2:$B$995,Index!$E$2:$E$995,"Not Found")),"")} -> y | G5: {=IF(NOT(ISBLANK(A5)), ((_xlfn.XLOOKUP(A5,Index!$B$2:$B$995,Index!$F$2:$F$995,"Not Found"))*B5),"")} -> 0 | L5: =IF(NOT(ISBLANK(K5)), SUM(M5:P5), "") | M5: =IF(NOT(ISBLANK($K5)), SUMIFS($B$2:$B$32, $E$2:$E$32, "B", $C$2:$C$32,$K5), "") | N5: =IF(NOT(ISBLANK($K5)),SUMIFS($B$2:$B$32,$E$2:$E$32, "1", $C$2:$C$32,$K5,$F$2:$F$32,"N"), "") | O5: =IF(NOT(ISBLANK($K5)),SUMIFS($B$2:$B$32,$E$2:$E$32, "1", $C$2:$C$32,$K5,$F$2:$F$32,"Y"), "") | P5: =IF(NOT(ISBLANK($K5)),SUMIFS($B$2:$B$32,$E$2:$E$32, "2", $C$2:$C$32,$K5), "") | Q5: =IF(NOT(ISBLANK($K5)),SUMIFS($B$2:$B$32,$E$2:$E$32, "B", $C$2:$C$32,$K5,$F$2:$F$32,"N"), "")
A6: Dark Electrode | B6: 1 | C6: {=IF(NOT(ISBLANK($A6)), (_xlfn.XLOOKUP($A6,Index!$B$2:$B$995,Index!$C$2:$C$995,"Not Found")),"")} -> E | D6: {=IF(NOT(ISBLANK(A6)), (_xlfn.XLOOKUP($A6,Index!$B$2:B$995,Index!$A$2:$A$995,"Not Found")),"")} -> base5-34 | E6: {=IF(NOT(ISBLANK($A6)), (_xlfn.XLOOKUP($A6,Index!$B$2:$B$995,Index!$D$2:$D$995,"Not Found")),"")} -> 1 | F6: {=IF(NOT(ISBLANK($A6)), (_xlfn.XLOOKUP($A6,Index!$B$2:$B$995,Index!$E$2:$E$995,"Not Found")),"")} -> n | G6: {=IF(NOT(ISBLANK(A6)), ((_xlfn.XLOOKUP(A6,Index!$B$2:$B$995,Index!$F$2:$F$995,"Not Found"))*B6),"")} -> 1 | L6: =IF(NOT(ISBLANK(K6)), SUM(M6:P6), "") | M6: =IF(NOT(ISBLANK($K6)), COUNTIFS($E$2:$E$32, "B", $C$2:$C$32,$K6), "") | N6: =IF(NOT(ISBLANK(K6)),COUNTIFS($E$2:$E$32, "1", $C$2:$C$32,$K6,$F$2:$F$32,"N"), "") | O6: =IF(NOT(ISBLANK($K6)),COUNTIFS($E$2:$E$32, "1", $C$2:$C$32,$K6,$F$2:$F$32,"Y"), "") | P6: =IF(NOT(ISBLANK($K6)),COUNTIFS($E$2:$E$32, "2", $C$2:$C$32,$K6), "") | Q6: =IF(NOT(ISBLANK($K6)),COUNTIFS($E$2:$E$32, "B", $C$2:$C$32,$K6,$F$2:$F$32,"N"), "")
A7: Ekans R | B7: 3 | C7: {=IF(NOT(ISBLANK($A7)), (_xlfn.XLOOKUP($A7,Index!$B$2:$B$995,Index!$C$2:$C$995,"Not Found")),"")} -> G | D7: {=IF(NOT(ISBLANK(A7)), (_xlfn.XLOOKUP($A7,Index!$B$2:B$995,Index!$A$2:$A$995,"Not Found")),"")} -> base5-56 | E7: {=IF(NOT(ISBLANK($A7)), (_xlfn.XLOOKUP($A7,Index!$B$2:$B$995,Index!$D$2:$D$995,"Not Found")),"")} -> b | F7: {=IF(NOT(ISBLANK($A7)), (_xlfn.XLOOKUP($A7,Index!$B$2:$B$995,Index!$E$2:$E$995,"Not Found")),"")} -> y | G7: {=IF(NOT(ISBLANK(A7)), ((_xlfn.XLOOKUP(A7,Index!$B$2:$B$995,Index!$F$2:$F$995,"Not Found"))*B7),"")} -> 0 | K7: Total | L7: =SUM(L2:L6) -> 22 | M7: =SUM(M2:M6) -> 15 | N7: =SUM(N2:N6) -> 7 | O7: =SUM(O2:O6) -> 0 | P7: =SUM(P2:P6) -> 0 | Q7: =SUM(Q2:Q6) -> 0
A8: Dark Arbok | B8: 2 | C8: {=IF(NOT(ISBLANK($A8)), (_xlfn.XLOOKUP($A8,Index!$B$2:$B$995,Index!$C$2:$C$995,"Not Found")),"")} -> G | D8: {=IF(NOT(ISBLANK(A8)), (_xlfn.XLOOKUP($A8,Index!$B$2:B$995,Index!$A$2:$A$995,"Not Found")),"")} -> base5-2 | E8: {=IF(NOT(ISBLANK($A8)), (_xlfn.XLOOKUP($A8,Index!$B$2:$B$995,Index!$D$2:$D$995,"Not Found")),"")} -> 1 | F8: {=IF(NOT(ISBLANK($A8)), (_xlfn.XLOOKUP($A8,Index!$B$2:$B$995,Index!$E$2:$E$995,"Not Found")),"")} -> n | G8: {=IF(NOT(ISBLANK(A8)), ((_xlfn.XLOOKUP(A8,Index!$B$2:$B$995,Index!$F$2:$F$995,"Not Found"))*B8),"")} -> 4
A9: Zubat R | B9: 3 | C9: {=IF(NOT(ISBLANK($A9)), (_xlfn.XLOOKUP($A9,Index!$B$2:$B$995,Index!$C$2:$C$995,"Not Found")),"")} -> G | D9: {=IF(NOT(ISBLANK(A9)), (_xlfn.XLOOKUP($A9,Index!$B$2:B$995,Index!$A$2:$A$995,"Not Found")),"")} -> base5-70 | E9: {=IF(NOT(ISBLANK($A9)), (_xlfn.XLOOKUP($A9,Index!$B$2:$B$995,Index!$D$2:$D$995,"Not Found")),"")} -> b | F9: {=IF(NOT(ISBLANK($A9)), (_xlfn.XLOOKUP($A9,Index!$B$2:$B$995,Index!$E$2:$E$995,"Not Found")),"")} -> y | G9: {=IF(NOT(ISBLANK(A9)), ((_xlfn.XLOOKUP(A9,Index!$B$2:$B$995,Index!$F$2:$F$995,"Not Found"))*B9),"")} -> 0 | M9: Common | N9: Uncommon | O9: Rare
A10: Dark Golbat NH | B10: 1 | C10: {=IF(NOT(ISBLANK($A10)), (_xlfn.XLOOKUP($A10,Index!$B$2:$B$995,Index!$C$2:$C$995,"Not Found")),"")} -> G | D10: {=IF(NOT(ISBLANK(A10)), (_xlfn.XLOOKUP($A10,Index!$B$2:B$995,Index!$A$2:$A$995,"Not Found")),"")} -> base5-24 | E10: {=IF(NOT(ISBLANK($A10)), (_xlfn.XLOOKUP($A10,Index!$B$2:$B$995,Index!$D$2:$D$995,"Not Found")),"")} -> 1 | F10: {=IF(NOT(ISBLANK($A10)), (_xlfn.XLOOKUP($A10,Index!$B$2:$B$995,Index!$E$2:$E$995,"Not Found")),"")} -> n | G10: {=IF(NOT(ISBLANK(A10)), ((_xlfn.XLOOKUP(A10,Index!$B$2:$B$995,Index!$F$2:$F$995,"Not Found"))*B10),"")} -> 1.5 | K10: Trainer | L10: =SUM(M10:P10) -> 10 | M10: =IF(NOT(ISBLANK($K10)), SUMIFS($B$2:$B$32,$E$2:$E$32, "C", $C$2:$C$32,"T"), "") -> 5 | N10: =IF(NOT(ISBLANK($K10)), SUMIFS($B$2:$B$32,$E$2:$E$32, "U", $C$2:$C$32,"T"), "") -> 4 | O10: =IF(NOT(ISBLANK($K$2)), SUMIFS($B$2:$B$32,$E$2:$E$32, "R", $C$2:$C$32,"T"), "") -> 1
A11: Rattata R | B11: 2 | C11: {=IF(NOT(ISBLANK($A11)), (_xlfn.XLOOKUP($A11,Index!$B$2:$B$995,Index!$C$2:$C$995,"Not Found")),"")} -> C | D11: {=IF(NOT(ISBLANK(A11)), (_xlfn.XLOOKUP($A11,Index!$B$2:B$995,Index!$A$2:$A$995,"Not Found")),"")} -> base5-66 | E11: {=IF(NOT(ISBLANK($A11)), (_xlfn.XLOOKUP($A11,Index!$B$2:$B$995,Index!$D$2:$D$995,"Not Found")),"")} -> b | F11: {=IF(NOT(ISBLANK($A11)), (_xlfn.XLOOKUP($A11,Index!$B$2:$B$995,Index!$E$2:$E$995,"Not Found")),"")} -> y | G11: {=IF(NOT(ISBLANK(A11)), ((_xlfn.XLOOKUP(A11,Index!$B$2:$B$995,Index!$F$2:$F$995,"Not Found"))*B11),"")} -> 0 | K11: Energy | L11: =IF(NOT(ISBLANK($K$2)), SUMIFS($B$2:$B$32, $C$2:$C$32,"Energy"), "") -> 28
A12: Dark Raticate | B12: 1 | C12: {=IF(NOT(ISBLANK($A12)), (_xlfn.XLOOKUP($A12,Index!$B$2:$B$995,Index!$C$2:$C$995,"Not Found")),"")} -> C | D12: {=IF(NOT(ISBLANK(A12)), (_xlfn.XLOOKUP($A12,Index!$B$2:B$995,Index!$A$2:$A$995,"Not Found")),"")} -> base5-51 | E12: {=IF(NOT(ISBLANK($A12)), (_xlfn.XLOOKUP($A12,Index!$B$2:$B$995,Index!$D$2:$D$995,"Not Found")),"")} -> 1 | F12: {=IF(NOT(ISBLANK($A12)), (_xlfn.XLOOKUP($A12,Index!$B$2:$B$995,Index!$E$2:$E$995,"Not Found")),"")} -> n | G12: {=IF(NOT(ISBLANK(A12)), ((_xlfn.XLOOKUP(A12,Index!$B$2:$B$995,Index!$F$2:$F$995,"Not Found"))*B12),"")} -> 1.5 | K12: Pokemon | L12: =L7 -> 22
A13: E Energy | B13: 15 | C13: {=IF(NOT(ISBLANK($A13)), (_xlfn.XLOOKUP($A13,Index!$B$2:$B$995,Index!$C$2:$C$995,"Not Found")),"")} -> Energy | D13: {=IF(NOT(ISBLANK(A13)), (_xlfn.XLOOKUP($A13,Index!$B$2:B$995,Index!$A$2:$A$995,"Not Found")),"")} -> base1-100 | E13: {=IF(NOT(ISBLANK($A13)), (_xlfn.XLOOKUP($A13,Index!$B$2:$B$995,Index!$D$2:$D$995,"Not Found")),"")} | F13: {=IF(NOT(ISBLANK($A13)), (_xlfn.XLOOKUP($A13,Index!$B$2:$B$995,Index!$E$2:$E$995,"Not Found")),"")} | G13: {=IF(NOT(ISBLANK(A13)), ((_xlfn.XLOOKUP(A13,Index!$B$2:$B$995,Index!$F$2:$F$995,"Not Found"))*B13),"")} -> 0
A14: G Energy | B14: 12 | C14: {=IF(NOT(ISBLANK($A14)), (_xlfn.XLOOKUP($A14,Index!$B$2:$B$995,Index!$C$2:$C$995,"Not Found")),"")} -> Energy | D14: {=IF(NOT(ISBLANK(A14)), (_xlfn.XLOOKUP($A14,Index!$B$2:B$995,Index!$A$2:$A$995,"Not Found")),"")} -> base1-99 | E14: {=IF(NOT(ISBLANK($A14)), (_xlfn.XLOOKUP($A14,Index!$B$2:$B$995,Index!$D$2:$D$995,"Not Found")),"")} | F14: {=IF(NOT(ISBLANK($A14)), (_xlfn.XLOOKUP($A14,Index!$B$2:$B$995,Index!$E$2:$E$995,"Not Found")),"")} | G14: {=IF(NOT(ISBLANK(A14)), ((_xlfn.XLOOKUP(A14,Index!$B$2:$B$995,Index!$F$2:$F$995,"Not Found"))*B14),"")} -> 0
A15: Energy Search | B15: 1 | C15: {=IF(NOT(ISBLANK($A15)), (_xlfn.XLOOKUP($A15,Index!$B$2:$B$995,Index!$C$2:$C$995,"Not Found")),"")} -> T | D15: {=IF(NOT(ISBLANK(A15)), (_xlfn.XLOOKUP($A15,Index!$B$2:B$995,Index!$A$2:$A$995,"Not Found")),"")} -> base3-59 | E15: {=IF(NOT(ISBLANK($A15)), (_xlfn.XLOOKUP($A15,Index!$B$2:$B$995,Index!$D$2:$D$995,"Not Found")),"")} -> c | F15: {=IF(NOT(ISBLANK($A15)), (_xlfn.XLOOKUP($A15,Index!$B$2:$B$995,Index!$E$2:$E$995,"Not Found")),"")} | G15: {=IF(NOT(ISBLANK(A15)), ((_xlfn.XLOOKUP(A15,Index!$B$2:$B$995,Index!$F$2:$F$995,"Not Found"))*B15),"")} -> #VALUE! | K15: Feature Weight:
A16: Bill | B16: 2 | C16: {=IF(NOT(ISBLANK($A16)), (_xlfn.XLOOKUP($A16,Index!$B$2:$B$995,Index!$C$2:$C$995,"Not Found")),"")} -> T | D16: {=IF(NOT(ISBLANK(A16)), (_xlfn.XLOOKUP($A16,Index!$B$2:B$995,Index!$A$2:$A$995,"Not Found")),"")} -> base1-91 | E16: {=IF(NOT(ISBLANK($A16)), (_xlfn.XLOOKUP($A16,Index!$B$2:$B$995,Index!$D$2:$D$995,"Not Found")),"")} -> c | F16: {=IF(NOT(ISBLANK($A16)), (_xlfn.XLOOKUP($A16,Index!$B$2:$B$995,Index!$E$2:$E$995,"Not Found")),"")} | G16: {=IF(NOT(ISBLANK(A16)), ((_xlfn.XLOOKUP(A16,Index!$B$2:$B$995,Index!$F$2:$F$995,"Not Found"))*B16),"")} -> #VALUE! | K16: =K2 -> E | L16: =IF(NOT(ISBLANK($K2)), SUMIFS($G$2:$G$32, $C$2:$C$32,$K2), "") -> 4
A17: Professor Oak | B17: 1 | C17: {=IF(NOT(ISBLANK($A17)), (_xlfn.XLOOKUP($A17,Index!$B$2:$B$995,Index!$C$2:$C$995,"Not Found")),"")} -> T | D17: {=IF(NOT(ISBLANK(A17)), (_xlfn.XLOOKUP($A17,Index!$B$2:B$995,Index!$A$2:$A$995,"Not Found")),"")} -> base1-88 | E17: {=IF(NOT(ISBLANK($A17)), (_xlfn.XLOOKUP($A17,Index!$B$2:$B$995,Index!$D$2:$D$995,"Not Found")),"")} -> u | F17: {=IF(NOT(ISBLANK($A17)), (_xlfn.XLOOKUP($A17,Index!$B$2:$B$995,Index!$E$2:$E$995,"Not Found")),"")} | G17: {=IF(NOT(ISBLANK(A17)), ((_xlfn.XLOOKUP(A17,Index!$B$2:$B$995,Index!$F$2:$F$995,"Not Found"))*B17),"")} -> #VALUE! | K17: =K3 -> G | L17: =IF(NOT(ISBLANK($K3)), SUMIFS($G$2:$G$32, $C$2:$C$32,$K3), "") -> 5.5
A18: Sleep! | B18: 1 | C18: {=IF(NOT(ISBLANK($A18)), (_xlfn.XLOOKUP($A18,Index!$B$2:$B$995,Index!$C$2:$C$995,"Not Found")),"")} -> T | D18: {=IF(NOT(ISBLANK(A18)), (_xlfn.XLOOKUP($A18,Index!$B$2:B$995,Index!$A$2:$A$995,"Not Found")),"")} -> base5-79 | E18: {=IF(NOT(ISBLANK($A18)), (_xlfn.XLOOKUP($A18,Index!$B$2:$B$995,Index!$D$2:$D$995,"Not Found")),"")} -> c | F18: {=IF(NOT(ISBLANK($A18)), (_xlfn.XLOOKUP($A18,Index!$B$2:$B$995,Index!$E$2:$E$995,"Not Found")),"")} | G18: {=IF(NOT(ISBLANK(A18)), ((_xlfn.XLOOKUP(A18,Index!$B$2:$B$995,Index!$F$2:$F$995,"Not Found"))*B18),"")} -> #VALUE! | K18: =K4 -> C | L18: =IF(NOT(ISBLANK($K4)), SUMIFS($G$2:$G$32, $C$2:$C$32,$K4), "") -> 1.5
A19: Challenge! | B19: 1 | C19: {=IF(NOT(ISBLANK($A19)), (_xlfn.XLOOKUP($A19,Index!$B$2:$B$995,Index!$C$2:$C$995,"Not Found")),"")} -> T | D19: {=IF(NOT(ISBLANK(A19)), (_xlfn.XLOOKUP($A19,Index!$B$2:B$995,Index!$A$2:$A$995,"Not Found")),"")} -> base5-74 | E19: {=IF(NOT(ISBLANK($A19)), (_xlfn.XLOOKUP($A19,Index!$B$2:$B$995,Index!$D$2:$D$995,"Not Found")),"")} -> u | F19: {=IF(NOT(ISBLANK($A19)), (_xlfn.XLOOKUP($A19,Index!$B$2:$B$995,Index!$E$2:$E$995,"Not Found")),"")} | G19: {=IF(NOT(ISBLANK(A19)), ((_xlfn.XLOOKUP(A19,Index!$B$2:$B$995,Index!$F$2:$F$995,"Not Found"))*B19),"")} -> #VALUE! | K19: =K5 | L19: =IF(NOT(ISBLANK($K5)), SUMIFS($G$2:$G$32, $C$2:$C$32,$K5), "")
A20: Impostor Professor Oak | B20: 1 | C20: {=IF(NOT(ISBLANK($A20)), (_xlfn.XLOOKUP($A20,Index!$B$2:$B$995,Index!$C$2:$C$995,"Not Found")),"")} -> T | D20: {=IF(NOT(ISBLANK(A20)), (_xlfn.XLOOKUP($A20,Index!$B$2:B$995,Index!$A$2:$A$995,"Not Found")),"")} -> base1-73 | E20: {=IF(NOT(ISBLANK($A20)), (_xlfn.XLOOKUP($A20,Index!$B$2:$B$995,Index!$D$2:$D$995,"Not Found")),"")} -> r | F20: {=IF(NOT(ISBLANK($A20)), (_xlfn.XLOOKUP($A20,Index!$B$2:$B$995,Index!$E$2:$E$995,"Not Found")),"")} | G20: {=IF(NOT(ISBLANK(A20)), ((_xlfn.XLOOKUP(A20,Index!$B$2:$B$995,Index!$F$2:$F$995,"Not Found"))*B20),"")} -> #VALUE! | K20: =K6
A21: Imposter Oak's Revenge | B21: 1 | C21: {=IF(NOT(ISBLANK($A21)), (_xlfn.XLOOKUP($A21,Index!$B$2:$B$995,Index!$C$2:$C$995,"Not Found")),"")} -> T | D21: {=IF(NOT(ISBLANK(A21)), (_xlfn.XLOOKUP($A21,Index!$B$2:B$995,Index!$A$2:$A$995,"Not Found")),"")} -> base5-76 | E21: {=IF(NOT(ISBLANK($A21)), (_xlfn.XLOOKUP($A21,Index!$B$2:$B$995,Index!$D$2:$D$995,"Not Found")),"")} -> u | F21: {=IF(NOT(ISBLANK($A21)), (_xlfn.XLOOKUP($A21,Index!$B$2:$B$995,Index!$E$2:$E$995,"Not Found")),"")} | G21: {=IF(NOT(ISBLANK(A21)), ((_xlfn.XLOOKUP(A21,Index!$B$2:$B$995,Index!$F$2:$F$995,"Not Found"))*B21),"")} -> #VALUE! | K21: Total: | L21: =SUM(L15:L19) -> 11
A22: Potion | B22: 1 | C22: {=IF(NOT(ISBLANK($A22)), (_xlfn.XLOOKUP($A22,Index!$B$2:$B$995,Index!$C$2:$C$995,"Not Found")),"")} -> T | D22: {=IF(NOT(ISBLANK(A22)), (_xlfn.XLOOKUP($A22,Index!$B$2:B$995,Index!$A$2:$A$995,"Not Found")),"")} -> base1-94 | E22: {=IF(NOT(ISBLANK($A22)), (_xlfn.XLOOKUP($A22,Index!$B$2:$B$995,Index!$D$2:$D$995,"Not Found")),"")} -> c | F22: {=IF(NOT(ISBLANK($A22)), (_xlfn.XLOOKUP($A22,Index!$B$2:$B$995,Index!$E$2:$E$995,"Not Found")),"")} | G22: {=IF(NOT(ISBLANK(A22)), ((_xlfn.XLOOKUP(A22,Index!$B$2:$B$995,Index!$F$2:$F$995,"Not Found"))*B22),"")} -> #VALUE!
A23: Potion Energy | B23: 1 | C23: {=IF(NOT(ISBLANK($A23)), (_xlfn.XLOOKUP($A23,Index!$B$2:$B$995,Index!$C$2:$C$995,"Not Found")),"")} -> Energy | D23: {=IF(NOT(ISBLANK(A23)), (_xlfn.XLOOKUP($A23,Index!$B$2:B$995,Index!$A$2:$A$995,"Not Found")),"")} -> base5-82 | E23: {=IF(NOT(ISBLANK($A23)), (_xlfn.XLOOKUP($A23,Index!$B$2:$B$995,Index!$D$2:$D$995,"Not Found")),"")} | F23: {=IF(NOT(ISBLANK($A23)), (_xlfn.XLOOKUP($A23,Index!$B$2:$B$995,Index!$E$2:$E$995,"Not Found")),"")} | G23: {=IF(NOT(ISBLANK(A23)), ((_xlfn.XLOOKUP(A23,Index!$B$2:$B$995,Index!$F$2:$F$995,"Not Found"))*B23),"")} -> 0
A24: Full Heal | B24: 1 | C24: {=IF(NOT(ISBLANK($A24)), (_xlfn.XLOOKUP($A24,Index!$B$2:$B$995,Index!$C$2:$C$995,"Not Found")),"")} -> T | D24: {=IF(NOT(ISBLANK(A24)), (_xlfn.XLOOKUP($A24,Index!$B$2:B$995,Index!$A$2:$A$995,"Not Found")),"")} -> base1-82 | E24: {=IF(NOT(ISBLANK($A24)), (_xlfn.XLOOKUP($A24,Index!$B$2:$B$995,Index!$D$2:$D$995,"Not Found")),"")} -> u | F24: {=IF(NOT(ISBLANK($A24)), (_xlfn.XLOOKUP($A24,Index!$B$2:$B$995,Index!$E$2:$E$995,"Not Found")),"")} | G24: {=IF(NOT(ISBLANK(A24)), ((_xlfn.XLOOKUP(A24,Index!$B$2:$B$995,Index!$F$2:$F$995,"Not Found"))*B24),"")} -> #VALUE! | K24: Cover Card: | L24: Dark Raichu
C25: {=IF(NOT(ISBLANK($A25)), (_xlfn.XLOOKUP($A25,Index!$B$2:$B$995,Index!$C$2:$C$995,"Not Found")),"")} | D25: {=IF(NOT(ISBLANK(A25)), (_xlfn.XLOOKUP($A25,Index!$B$2:B$995,Index!$A$2:$A$995,"Not Found")),"")} | E25: {=IF(NOT(ISBLANK($A25)), (_xlfn.XLOOKUP($A25,Index!$B$2:$B$995,Index!$D$2:$D$995,"Not Found")),"")} | F25: {=IF(NOT(ISBLANK($A25)), (_xlfn.XLOOKUP($A25,Index!$B$2:$B$995,Index!$E$2:$E$995,"Not Found")),"")} | G25: {=IF(NOT(ISBLANK(A25)), ((_xlfn.XLOOKUP(A25,Index!$B$2:$B$995,Index!$F$2:$F$995,"Not Found"))*B25),"")}
C26: {=IF(NOT(ISBLANK($A26)), (_xlfn.XLOOKUP($A26,Index!$B$2:$B$995,Index!$C$2:$C$995,"Not Found")),"")} | D26: {=IF(NOT(ISBLANK(A26)), (_xlfn.XLOOKUP($A26,Index!$B$2:B$995,Index!$A$2:$A$995,"Not Found")),"")} | E26: {=IF(NOT(ISBLANK($A26)), (_xlfn.XLOOKUP($A26,Index!$B$2:$B$995,Index!$D$2:$D$995,"Not Found")),"")} | F26: {=IF(NOT(ISBLANK($A26)), (_xlfn.XLOOKUP($A26,Index!$B$2:$B$995,Index!$E$2:$E$995,"Not Found")),"")} | G26: {=IF(NOT(ISBLANK(A26)), ((_xlfn.XLOOKUP(A26,Index!$B$2:$B$995,Index!$F$2:$F$995,"Not Found"))*B26),"")}
C27: {=IF(NOT(ISBLANK($A27)), (_xlfn.XLOOKUP($A27,Index!$B$2:$B$995,Index!$C$2:$C$995,"Not Found")),"")} | D27: {=IF(NOT(ISBLANK(A27)), (_xlfn.XLOOKUP($A27,Index!$B$2:B$995,Index!$A$2:$A$995,"Not Found")),"")} | E27: {=IF(NOT(ISBLANK($A27)), (_xlfn.XLOOKUP($A27,Index!$B$2:$B$995,Index!$D$2:$D$995,"Not Found")),"")} | F27: {=IF(NOT(ISBLANK($A27)), (_xlfn.XLOOKUP($A27,Index!$B$2:$B$995,Index!$E$2:$E$995,"Not Found")),"")} | G27: {=IF(NOT(ISBLANK(A27)), ((_xlfn.XLOOKUP(A27,Index!$B$2:$B$995,Index!$F$2:$F$995,"Not Found"))*B27),"")}
C28: {=IF(NOT(ISBLANK($A28)), (_xlfn.XLOOKUP($A28,Index!$B$2:$B$995,Index!$C$2:$C$995,"Not Found")),"")} | D28: {=IF(NOT(ISBLANK(A28)), (_xlfn.XLOOKUP($A28,Index!$B$2:B$995,Index!$A$2:$A$995,"Not Found")),"")} | E28: {=IF(NOT(ISBLANK($A28)), (_xlfn.XLOOKUP($A28,Index!$B$2:$B$995,Index!$D$2:$D$995,"Not Found")),"")} | F28: {=IF(NOT(ISBLANK($A28)), (_xlfn.XLOOKUP($A28,Index!$B$2:$B$995,Index!$E$2:$E$995,"Not Found")),"")} | G28: {=IF(NOT(ISBLANK(A28)), ((_xlfn.XLOOKUP(A28,Index!$B$2:$B$995,Index!$F$2:$F$995,"Not Found"))*B28),"")}
C29: {=IF(NOT(ISBLANK($A29)), (_xlfn.XLOOKUP($A29,Index!$B$2:$B$995,Index!$C$2:$C$995,"Not Found")),"")} | D29: {=IF(NOT(ISBLANK(A29)), (_xlfn.XLOOKUP($A29,Index!$B$2:B$995,Index!$A$2:$A$995,"Not Found")),"")} | E29: {=IF(NOT(ISBLANK($A29)), (_xlfn.XLOOKUP($A29,Index!$B$2:$B$995,Index!$D$2:$D$995,"Not Found")),"")} | F29: {=IF(NOT(ISBLANK($A29)), (_xlfn.XLOOKUP($A29,Index!$B$2:$B$995,Index!$E$2:$E$995,"Not Found")),"")} | G29: {=IF(NOT(ISBLANK(A29)), ((_xlfn.XLOOKUP(A29,Index!$B$2:$B$995,Index!$F$2:$F$995,"Not Found"))*B29),"")}
C30: {=IF(NOT(ISBLANK($A30)), (_xlfn.XLOOKUP($A30,Index!$B$2:$B$995,Index!$C$2:$C$995,"Not Found")),"")} | D30: {=IF(NOT(ISBLANK(A30)), (_xlfn.XLOOKUP($A30,Index!$B$2:B$995,Index!$A$2:$A$995,"Not Found")),"")} | E30: {=IF(NOT(ISBLANK($A30)), (_xlfn.XLOOKUP($A30,Index!$B$2:$B$995,Index!$D$2:$D$995,"Not Found")),"")} | F30: {=IF(NOT(ISBLANK($A30)), (_xlfn.XLOOKUP($A30,Index!$B$2:$B$995,Index!$E$2:$E$995,"Not Found")),"")} | G30: {=IF(NOT(ISBLANK(A30)), ((_xlfn.XLOOKUP(A30,Index!$B$2:$B$995,Index!$F$2:$F$995,"Not Found"))*B30),"")}
C31: {=IF(NOT(ISBLANK($A31)), (_xlfn.XLOOKUP($A31,Index!$B$2:$B$995,Index!$C$2:$C$995,"Not Found")),"")} | D31: {=IF(NOT(ISBLANK(A31)), (_xlfn.XLOOKUP($A31,Index!$B$2:B$995,Index!$A$2:$A$995,"Not Found")),"")} | E31: {=IF(NOT(ISBLANK($A31)), (_xlfn.XLOOKUP($A31,Index!$B$2:$B$995,Index!$D$2:$D$995,"Not Found")),"")} | F31: {=IF(NOT(ISBLANK($A31)), (_xlfn.XLOOKUP($A31,Index!$B$2:$B$995,Index!$E$2:$E$995,"Not Found")),"")} | G31: {=IF(NOT(ISBLANK(A31)), ((_xlfn.XLOOKUP(A31,Index!$B$2:$B$995,Index!$F$2:$F$995,"Not Found"))*B31),"")}
C32: {=IF(NOT(ISBLANK($A32)), (_xlfn.XLOOKUP($A32,Index!$B$2:$B$995,Index!$C$2:$C$995,"Not Found")),"")} | D32: {=IF(NOT(ISBLANK(A32)), (_xlfn.XLOOKUP($A32,Index!$B$2:B$995,Index!$A$2:$A$995,"Not Found")),"")} | E32: {=IF(NOT(ISBLANK($A32)), (_xlfn.XLOOKUP($A32,Index!$B$2:$B$995,Index!$D$2:$D$995,"Not Found")),"")} | F32: {=IF(NOT(ISBLANK($A32)), (_xlfn.XLOOKUP($A32,Index!$B$2:$B$995,Index!$E$2:$E$995,"Not Found")),"")} | G32: {=IF(NOT(ISBLANK(A32)), ((_xlfn.XLOOKUP(A32,Index!$B$2:$B$995,Index!$F$2:$F$995,"Not Found"))*B32),"")}
C33: {=IF(NOT(ISBLANK($A33)), (_xlfn.XLOOKUP($A33,Index!$B$2:$B$995,Index!$C$2:$C$995,"Not Found")),"")} | D33: {=IF(NOT(ISBLANK(A33)), (_xlfn.XLOOKUP($A33,Index!$B$2:B$995,Index!$A$2:$A$995,"Not Found")),"")} | E33: {=IF(NOT(ISBLANK($A33)), (_xlfn.XLOOKUP($A33,Index!$B$2:$B$995,Index!$D$2:$D$995,"Not Found")),"")} | F33: {=IF(NOT(ISBLANK($A33)), (_xlfn.XLOOKUP($A33,Index!$B$2:$B$995,Index!$E$2:$E$995,"Not Found")),"")} | G33: {=IF(NOT(ISBLANK(A33)), ((_xlfn.XLOOKUP(A33,Index!$B$2:$B$995,Index!$F$2:$F$995,"Not Found"))*B33),"")}
C34: {=IF(NOT(ISBLANK($A34)), (_xlfn.XLOOKUP($A34,Index!$B$2:$B$995,Index!$C$2:$C$995,"Not Found")),"")} | D34: {=IF(NOT(ISBLANK(A34)), (_xlfn.XLOOKUP($A34,Index!$B$2:B$995,Index!$A$2:$A$995,"Not Found")),"")} | E34: {=IF(NOT(ISBLANK($A34)), (_xlfn.XLOOKUP($A34,Index!$B$2:$B$995,Index!$D$2:$D$995,"Not Found")),"")} | F34: {=IF(NOT(ISBLANK($A34)), (_xlfn.XLOOKUP($A34,Index!$B$2:$B$995,Index!$E$2:$E$995,"Not Found")),"")} | G34: {=IF(NOT(ISBLANK(A34)), ((_xlfn.XLOOKUP(A34,Index!$B$2:$B$995,Index!$F$2:$F$995,"Not Found"))*B34),"")}
C35: {=IF(NOT(ISBLANK($A35)), (_xlfn.XLOOKUP($A35,Index!$B$2:$B$995,Index!$C$2:$C$995,"Not Found")),"")} | D35: {=IF(NOT(ISBLANK(A35)), (_xlfn.XLOOKUP($A35,Index!$B$2:B$995,Index!$A$2:$A$995,"Not Found")),"")} | E35: {=IF(NOT(ISBLANK($A35)), (_xlfn.XLOOKUP($A35,Index!$B$2:$B$995,Index!$D$2:$D$995,"Not Found")),"")} | F35: {=IF(NOT(ISBLANK($A35)), (_xlfn.XLOOKUP($A35,Index!$B$2:$B$995,Index!$E$2:$E$995,"Not Found")),"")} | G35: {=IF(NOT(ISBLANK(A35)), ((_xlfn.XLOOKUP(A35,Index!$B$2:$B$995,Index!$F$2:$F$995,"Not Found"))*B35),"")}
C36: {=IF(NOT(ISBLANK($A36)), (_xlfn.XLOOKUP($A36,Index!$B$2:$B$995,Index!$C$2:$C$995,"Not Found")),"")} | D36: {=IF(NOT(ISBLANK(A36)), (_xlfn.XLOOKUP($A36,Index!$B$2:B$995,Index!$A$2:$A$995,"Not Found")),"")} | E36: {=IF(NOT(ISBLANK($A36)), (_xlfn.XLOOKUP($A36,Index!$B$2:$B$995,Index!$D$2:$D$995,"Not Found")),"")} | F36: {=IF(NOT(ISBLANK($A36)), (_xlfn.XLOOKUP($A36,Index!$B$2:$B$995,Index!$E$2:$E$995,"Not Found")),"")} | G36: {=IF(NOT(ISBLANK(A36)), ((_xlfn.XLOOKUP(A36,Index!$B$2:$B$995,Index!$F$2:$F$995,"Not Found"))*B36),"")}
... C77: {=IF(NOT(ISBLANK($A77)), (_xlfn.XLOOKUP($A77,Index!$B$2:$B$995,Index!$C$2:$C$995,"Not Found")),"")} | D77: {=IF(NOT(ISBLANK(A77)), (_xlfn.XLOOKUP($A77,Index!$B$2:B$995,Index!$A$2:$A$995,"Not Found")),"")} | E77: {=IF(NOT(ISBLANK($A77)), (_xlfn.XLOOKUP($A77,Index!$B$2:$B$995,Index!$D$2:$D$995,"Not Found")),"")} | F77: {=IF(NOT(ISBLANK($A77)), (_xlfn.XLOOKUP($A77,Index!$B$2:$B$995,Index!$E$2:$E$995,"Not Found")),"")} | G77: {=IF(NOT(ISBLANK(A77)), ((_xlfn.XLOOKUP(A77,Index!$B$2:$B$995,Index!$F$2:$F$995,"Not Found"))*B77),"")}

Sheet R T2-3
A1: Card | B1: Quantity | C1: Type | D1: ID | E1: Stage / Rarity | F1: Remaining Evo | G1: Feature Weight | I1: Card Total | K1: Type | L1: Num | M1: Basic | N1: S1 Max | O1: S1 Mid | P1: S2 | Q1: No Evolve
A2: R Energy | B2: 16 | C2: {=IF(NOT(ISBLANK($A2)), (_xlfn.XLOOKUP($A2,Index!$B$2:$B$995,Index!$C$2:$C$995,"Not Found")),"")} -> Energy | D2: {=IF(NOT(ISBLANK(A2)), (_xlfn.XLOOKUP($A2,Index!$B$2:B$995,Index!$A$2:$A$995,"Not Found")),"")} -> base1-98 | E2: {=IF(NOT(ISBLANK($A2)), (_xlfn.XLOOKUP($A2,Index!$B$2:$B$995,Index!$D$2:$D$995,"Not Found")),"")} | F2: {=IF(NOT(ISBLANK($A2)), (_xlfn.XLOOKUP($A2,Index!$B$2:$B$995,Index!$E$2:$E$995,"Not Found")),"")} | G2: {=IF(NOT(ISBLANK(A2)), ((_xlfn.XLOOKUP(A2,Index!$B$2:$B$995,Index!$F$2:$F$995,"Not Found"))*B2),"")} -> 0 | I2: =SUM(B2:B38) -> 60 | K2: R | L2: =IF(NOT(ISBLANK(K2)), SUM(M2:P2), "") -> 13 | M2: =IF(NOT(ISBLANK($K2)), SUMIFS($B$2:$B$32, $E$2:$E$32, "B", $C$2:$C$32,$K2), "") -> 7 | N2: =IF(NOT(ISBLANK($K2)),SUMIFS($B$2:$B$32,$E$2:$E$32, "1", $C$2:$C$32,$K2,$F$2:$F$32,"N"), "") -> 2 | O2: =IF(NOT(ISBLANK($K2)),SUMIFS($B$2:$B$32,$E$2:$E$32, "1", $C$2:$C$32,$K2,$F$2:$F$32,"Y"), "") -> 3 | P2: =IF(NOT(ISBLANK($K2)),SUMIFS($B$2:$B$32,$E$2:$E$32, "2", $C$2:$C$32,$K2), "") -> 1 | Q2: =IF(NOT(ISBLANK($K2)),SUMIFS($B$2:$B$32,$E$2:$E$32, "B", $C$2:$C$32,$K2,$F$2:$F$32,"N"), "") -> 0
A3: P Energy | B3: 10 | C3: {=IF(NOT(ISBLANK($A3)), (_xlfn.XLOOKUP($A3,Index!$B$2:$B$995,Index!$C$2:$C$995,"Not Found")),"")} -> Energy | D3: {=IF(NOT(ISBLANK(A3)), (_xlfn.XLOOKUP($A3,Index!$B$2:B$995,Index!$A$2:$A$995,"Not Found")),"")} -> base1-101 | E3: {=IF(NOT(ISBLANK($A3)), (_xlfn.XLOOKUP($A3,Index!$B$2:$B$995,Index!$D$2:$D$995,"Not Found")),"")} | F3: {=IF(NOT(ISBLANK($A3)), (_xlfn.XLOOKUP($A3,Index!$B$2:$B$995,Index!$E$2:$E$995,"Not Found")),"")} | G3: {=IF(NOT(ISBLANK(A3)), ((_xlfn.XLOOKUP(A3,Index!$B$2:$B$995,Index!$F$2:$F$995,"Not Found"))*B3),"")} -> 0 | K3: P | L3: =IF(NOT(ISBLANK(K3)), SUM(M3:P3), "") -> 5 | M3: =IF(NOT(ISBLANK($K3)), SUMIFS($B$2:$B$32, $E$2:$E$32, "B", $C$2:$C$32,$K3), "") -> 3 | N3: =IF(NOT(ISBLANK($K3)),SUMIFS($B$2:$B$32,$E$2:$E$32, "1", $C$2:$C$32,$K3,$F$2:$F$32,"N"), "") -> 2 | O3: =IF(NOT(ISBLANK($K3)),SUMIFS($B$2:$B$32,$E$2:$E$32, "1", $C$2:$C$32,$K3,$F$2:$F$32,"Y"), "") -> 0 | P3: =IF(NOT(ISBLANK($K3)),SUMIFS($B$2:$B$32,$E$2:$E$32, "2", $C$2:$C$32,$K3), "") -> 0 | Q3: =IF(NOT(ISBLANK($K3)),SUMIFS($B$2:$B$32,$E$2:$E$32, "B", $C$2:$C$32,$K3,$F$2:$F$32,"N"), "") -> 0
A4: Charmander R | B4: 4 | C4: {=IF(NOT(ISBLANK($A4)), (_xlfn.XLOOKUP($A4,Index!$B$2:$B$995,Index!$C$2:$C$995,"Not Found")),"")} -> R | D4: {=IF(NOT(ISBLANK(A4)), (_xlfn.XLOOKUP($A4,Index!$B$2:B$995,Index!$A$2:$A$995,"Not Found")),"")} -> base5-50 | E4: {=IF(NOT(ISBLANK($A4)), (_xlfn.XLOOKUP($A4,Index!$B$2:$B$995,Index!$D$2:$D$995,"Not Found")),"")} -> b | F4: {=IF(NOT(ISBLANK($A4)), (_xlfn.XLOOKUP($A4,Index!$B$2:$B$995,Index!$E$2:$E$995,"Not Found")),"")} -> y | G4: {=IF(NOT(ISBLANK(A4)), ((_xlfn.XLOOKUP(A4,Index!$B$2:$B$995,Index!$F$2:$F$995,"Not Found"))*B4),"")} -> 0 | K4: W | L4: =IF(NOT(ISBLANK(K4)), SUM(M4:P4), "") -> 4 | M4: =IF(NOT(ISBLANK($K4)), SUMIFS($B$2:$B$32, $E$2:$E$32, "B", $C$2:$C$32,$K4), "") -> 3 | N4: =IF(NOT(ISBLANK($K4)),SUMIFS($B$2:$B$32,$E$2:$E$32, "1", $C$2:$C$32,$K4,$F$2:$F$32,"N"), "") -> 1 | O4: =IF(NOT(ISBLANK($K4)),SUMIFS($B$2:$B$32,$E$2:$E$32, "1", $C$2:$C$32,$K4,$F$2:$F$32,"Y"), "") -> 0 | P4: =IF(NOT(ISBLANK($K4)),SUMIFS($B$2:$B$32,$E$2:$E$32, "2", $C$2:$C$32,$K4), "") -> 0 | Q4: =IF(NOT(ISBLANK($K4)),SUMIFS($B$2:$B$32,$E$2:$E$32, "B", $C$2:$C$32,$K4,$F$2:$F$32,"N"), "") -> 0
A5: Dark Charmeleon | B5: 3 | C5: {=IF(NOT(ISBLANK($A5)), (_xlfn.XLOOKUP($A5,Index!$B$2:$B$995,Index!$C$2:$C$995,"Not Found")),"")} -> R | D5: {=IF(NOT(ISBLANK(A5)), (_xlfn.XLOOKUP($A5,Index!$B$2:B$995,Index!$A$2:$A$995,"Not Found")),"")} -> base5-32 | E5: {=IF(NOT(ISBLANK($A5)), (_xlfn.XLOOKUP($A5,Index!$B$2:$B$995,Index!$D$2:$D$995,"Not Found")),"")} -> 1 | F5: {=IF(NOT(ISBLANK($A5)), (_xlfn.XLOOKUP($A5,Index!$B$2:$B$995,Index!$E$2:$E$995,"Not Found")),"")} -> y | G5: {=IF(NOT(ISBLANK(A5)), ((_xlfn.XLOOKUP(A5,Index!$B$2:$B$995,Index!$F$2:$F$995,"Not Found"))*B5),"")} -> 1.5 | K5: C | L5: =IF(NOT(ISBLANK(K5)), SUM(M5:P5), "") -> 0 | M5: =IF(NOT(ISBLANK($K5)), SUMIFS($B$2:$B$32, $E$2:$E$32, "B", $C$2:$C$32,$K5), "") -> 0 | N5: =IF(NOT(ISBLANK($K5)),SUMIFS($B$2:$B$32,$E$2:$E$32, "1", $C$2:$C$32,$K5,$F$2:$F$32,"N"), "") -> 0 | O5: =IF(NOT(ISBLANK($K5)),SUMIFS($B$2:$B$32,$E$2:$E$32, "1", $C$2:$C$32,$K5,$F$2:$F$32,"Y"), "") -> 0 | P5: =IF(NOT(ISBLANK($K5)),SUMIFS($B$2:$B$32,$E$2:$E$32, "2", $C$2:$C$32,$K5), "") -> 0 | Q5: =IF(NOT(ISBLANK($K5)),SUMIFS($B$2:$B$32,$E$2:$E$32, "B", $C$2:$C$32,$K5,$F$2:$F$32,"N"), "") -> 0
A6: Dark Charizard | B6: 1 | C6: {=IF(NOT(ISBLANK($A6)), (_xlfn.XLOOKUP($A6,Index!$B$2:$B$995,Index!$C$2:$C$995,"Not Found")),"")} -> R | D6: {=IF(NOT(ISBLANK(A6)), (_xlfn.XLOOKUP($A6,Index!$B$2:B$995,Index!$A$2:$A$995,"Not Found")),"")} -> base5-4 | E6: {=IF(NOT(ISBLANK($A6)), (_xlfn.XLOOKUP($A6,Index!$B$2:$B$995,Index!$D$2:$D$995,"Not Found")),"")} -> 2 | F6: {=IF(NOT(ISBLANK($A6)), (_xlfn.XLOOKUP($A6,Index!$B$2:$B$995,Index!$E$2:$E$995,"Not Found")),"")} | G6: {=IF(NOT(ISBLANK(A6)), ((_xlfn.XLOOKUP(A6,Index!$B$2:$B$995,Index!$F$2:$F$995,"Not Found"))*B6),"")} -> 3 | L6: =IF(NOT(ISBLANK(K6)), SUM(M6:P6), "") | M6: =IF(NOT(ISBLANK($K6)), COUNTIFS($E$2:$E$32, "B", $C$2:$C$32,$K6), "") | N6: =IF(NOT(ISBLANK(K6)),COUNTIFS($E$2:$E$32, "1", $C$2:$C$32,$K6,$F$2:$F$32,"N"), "") | O6: =IF(NOT(ISBLANK($K6)),COUNTIFS($E$2:$E$32, "1", $C$2:$C$32,$K6,$F$2:$F$32,"Y"), "") | P6: =IF(NOT(ISBLANK($K6)),COUNTIFS($E$2:$E$32, "2", $C$2:$C$32,$K6), "") | Q6: =IF(NOT(ISBLANK($K6)),COUNTIFS($E$2:$E$32, "B", $C$2:$C$32,$K6,$F$2:$F$32,"N"), "")
A7: Ponyta R | B7: 3 | C7: {=IF(NOT(ISBLANK($A7)), (_xlfn.XLOOKUP($A7,Index!$B$2:$B$995,Index!$C$2:$C$995,"Not Found")),"")} -> R | D7: {=IF(NOT(ISBLANK(A7)), (_xlfn.XLOOKUP($A7,Index!$B$2:B$995,Index!$A$2:$A$995,"Not Found")),"")} -> base5-64 | E7: {=IF(NOT(ISBLANK($A7)), (_xlfn.XLOOKUP($A7,Index!$B$2:$B$995,Index!$D$2:$D$995,"Not Found")),"")} -> b | F7: {=IF(NOT(ISBLANK($A7)), (_xlfn.XLOOKUP($A7,Index!$B$2:$B$995,Index!$E$2:$E$995,"Not Found")),"")} -> y | G7: {=IF(NOT(ISBLANK(A7)), ((_xlfn.XLOOKUP(A7,Index!$B$2:$B$995,Index!$F$2:$F$995,"Not Found"))*B7),"")} -> 0 | K7: Total | L7: =SUM(L2:L6) -> 22 | M7: =SUM(M2:M6) -> 13 | N7: =SUM(N2:N6) -> 5 | O7: =SUM(O2:O6) -> 3 | P7: =SUM(P2:P6) -> 1 | Q7: =SUM(Q2:Q6) -> 0
A8: Dark Rapidash | B8: 2 | C8: {=IF(NOT(ISBLANK($A8)), (_xlfn.XLOOKUP($A8,Index!$B$2:$B$995,Index!$C$2:$C$995,"Not Found")),"")} -> R | D8: {=IF(NOT(ISBLANK(A8)), (_xlfn.XLOOKUP($A8,Index!$B$2:B$995,Index!$A$2:$A$995,"Not Found")),"")} -> base5-44 | E8: {=IF(NOT(ISBLANK($A8)), (_xlfn.XLOOKUP($A8,Index!$B$2:$B$995,Index!$D$2:$D$995,"Not Found")),"")} -> 1 | F8: {=IF(NOT(ISBLANK($A8)), (_xlfn.XLOOKUP($A8,Index!$B$2:$B$995,Index!$E$2:$E$995,"Not Found")),"")} -> n | G8: {=IF(NOT(ISBLANK(A8)), ((_xlfn.XLOOKUP(A8,Index!$B$2:$B$995,Index!$F$2:$F$995,"Not Found"))*B8),"")} -> 3
A9: Drowzee R | B9: 3 | C9: {=IF(NOT(ISBLANK($A9)), (_xlfn.XLOOKUP($A9,Index!$B$2:$B$995,Index!$C$2:$C$995,"Not Found")),"")} -> P | D9: {=IF(NOT(ISBLANK(A9)), (_xlfn.XLOOKUP($A9,Index!$B$2:B$995,Index!$A$2:$A$995,"Not Found")),"")} -> base5-54 | E9: {=IF(NOT(ISBLANK($A9)), (_xlfn.XLOOKUP($A9,Index!$B$2:$B$995,Index!$D$2:$D$995,"Not Found")),"")} -> b | F9: {=IF(NOT(ISBLANK($A9)), (_xlfn.XLOOKUP($A9,Index!$B$2:$B$995,Index!$E$2:$E$995,"Not Found")),"")} -> y | G9: {=IF(NOT(ISBLANK(A9)), ((_xlfn.XLOOKUP(A9,Index!$B$2:$B$995,Index!$F$2:$F$995,"Not Found"))*B9),"")} -> 0 | M9: Common | N9: Uncommon | O9: Rare
A10: Dark Hypno NH | B10: 2 | C10: {=IF(NOT(ISBLANK($A10)), (_xlfn.XLOOKUP($A10,Index!$B$2:$B$995,Index!$C$2:$C$995,"Not Found")),"")} -> P | D10: {=IF(NOT(ISBLANK(A10)), (_xlfn.XLOOKUP($A10,Index!$B$2:B$995,Index!$A$2:$A$995,"Not Found")),"")} -> base5-26 | E10: {=IF(NOT(ISBLANK($A10)), (_xlfn.XLOOKUP($A10,Index!$B$2:$B$995,Index!$D$2:$D$995,"Not Found")),"")} -> 1 | F10: {=IF(NOT(ISBLANK($A10)), (_xlfn.XLOOKUP($A10,Index!$B$2:$B$995,Index!$E$2:$E$995,"Not Found")),"")} -> n | G10: {=IF(NOT(ISBLANK(A10)), ((_xlfn.XLOOKUP(A10,Index!$B$2:$B$995,Index!$F$2:$F$995,"Not Found"))*B10),"")} -> 4 | K10: Trainer | L10: =SUM(M10:P10) -> 10 | M10: =IF(NOT(ISBLANK($K10)), SUMIFS($B$2:$B$32,$E$2:$E$32, "C", $C$2:$C$32,"T"), "") -> 5 | N10: =IF(NOT(ISBLANK($K10)), SUMIFS($B$2:$B$32,$E$2:$E$32, "U", $C$2:$C$32,"T"), "") -> 4 | O10: =IF(NOT(ISBLANK($K$2)), SUMIFS($B$2:$B$32,$E$2:$E$32, "R", $C$2:$C$32,"T"), "") -> 1
A11: Psyduck R | B11: 3 | C11: {=IF(NOT(ISBLANK($A11)), (_xlfn.XLOOKUP($A11,Index!$B$2:$B$995,Index!$C$2:$C$995,"Not Found")),"")} -> W | D11: {=IF(NOT(ISBLANK(A11)), (_xlfn.XLOOKUP($A11,Index!$B$2:B$995,Index!$A$2:$A$995,"Not Found")),"")} -> base5-65 | E11: {=IF(NOT(ISBLANK($A11)), (_xlfn.XLOOKUP($A11,Index!$B$2:$B$995,Index!$D$2:$D$995,"Not Found")),"")} -> b | F11: {=IF(NOT(ISBLANK($A11)), (_xlfn.XLOOKUP($A11,Index!$B$2:$B$995,Index!$E$2:$E$995,"Not Found")),"")} -> y | G11: {=IF(NOT(ISBLANK(A11)), ((_xlfn.XLOOKUP(A11,Index!$B$2:$B$995,Index!$F$2:$F$995,"Not Found"))*B11),"")} -> 0 | K11: Energy | L11: =IF(NOT(ISBLANK($K$2)), SUMIFS($B$2:$B$32, $C$2:$C$32,"Energy"), "") -> 28
A12: Dark Golduck | B12: 1 | C12: {=IF(NOT(ISBLANK($A12)), (_xlfn.XLOOKUP($A12,Index!$B$2:$B$995,Index!$C$2:$C$995,"Not Found")),"")} -> W | D12: {=IF(NOT(ISBLANK(A12)), (_xlfn.XLOOKUP($A12,Index!$B$2:B$995,Index!$A$2:$A$995,"Not Found")),"")} -> base5-37 | E12: {=IF(NOT(ISBLANK($A12)), (_xlfn.XLOOKUP($A12,Index!$B$2:$B$995,Index!$D$2:$D$995,"Not Found")),"")} -> 1 | F12: {=IF(NOT(ISBLANK($A12)), (_xlfn.XLOOKUP($A12,Index!$B$2:$B$995,Index!$E$2:$E$995,"Not Found")),"")} -> n | G12: {=IF(NOT(ISBLANK(A12)), ((_xlfn.XLOOKUP(A12,Index!$B$2:$B$995,Index!$F$2:$F$995,"Not Found"))*B12),"")} -> 1.5 | K12: Pokemon | L12: =L7 -> 22
A13: Rainbow Energy NH | B13: 2 | C13: {=IF(NOT(ISBLANK($A13)), (_xlfn.XLOOKUP($A13,Index!$B$2:$B$995,Index!$C$2:$C$995,"Not Found")),"")} -> Energy | D13: {=IF(NOT(ISBLANK(A13)), (_xlfn.XLOOKUP($A13,Index!$B$2:B$995,Index!$A$2:$A$995,"Not Found")),"")} -> base5-80 | E13: {=IF(NOT(ISBLANK($A13)), (_xlfn.XLOOKUP($A13,Index!$B$2:$B$995,Index!$D$2:$D$995,"Not Found")),"")} | F13: {=IF(NOT(ISBLANK($A13)), (_xlfn.XLOOKUP($A13,Index!$B$2:$B$995,Index!$E$2:$E$995,"Not Found")),"")} | G13: {=IF(NOT(ISBLANK(A13)), ((_xlfn.XLOOKUP(A13,Index!$B$2:$B$995,Index!$F$2:$F$995,"Not Found"))*B13),"")} -> 0
A14: Bill | B14: 2 | C14: {=IF(NOT(ISBLANK($A14)), (_xlfn.XLOOKUP($A14,Index!$B$2:$B$995,Index!$C$2:$C$995,"Not Found")),"")} -> T | D14: {=IF(NOT(ISBLANK(A14)), (_xlfn.XLOOKUP($A14,Index!$B$2:B$995,Index!$A$2:$A$995,"Not Found")),"")} -> base1-91 | E14: {=IF(NOT(ISBLANK($A14)), (_xlfn.XLOOKUP($A14,Index!$B$2:$B$995,Index!$D$2:$D$995,"Not Found")),"")} -> c | F14: {=IF(NOT(ISBLANK($A14)), (_xlfn.XLOOKUP($A14,Index!$B$2:$B$995,Index!$E$2:$E$995,"Not Found")),"")} | G14: {=IF(NOT(ISBLANK(A14)), ((_xlfn.XLOOKUP(A14,Index!$B$2:$B$995,Index!$F$2:$F$995,"Not Found"))*B14),"")} -> #VALUE!
A15: Professor Oak | B15: 1 | C15: {=IF(NOT(ISBLANK($A15)), (_xlfn.XLOOKUP($A15,Index!$B$2:$B$995,Index!$C$2:$C$995,"Not Found")),"")} -> T | D15: {=IF(NOT(ISBLANK(A15)), (_xlfn.XLOOKUP($A15,Index!$B$2:B$995,Index!$A$2:$A$995,"Not Found")),"")} -> base1-88 | E15: {=IF(NOT(ISBLANK($A15)), (_xlfn.XLOOKUP($A15,Index!$B$2:$B$995,Index!$D$2:$D$995,"Not Found")),"")} -> u | F15: {=IF(NOT(ISBLANK($A15)), (_xlfn.XLOOKUP($A15,Index!$B$2:$B$995,Index!$E$2:$E$995,"Not Found")),"")} | G15: {=IF(NOT(ISBLANK(A15)), ((_xlfn.XLOOKUP(A15,Index!$B$2:$B$995,Index!$F$2:$F$995,"Not Found"))*B15),"")} -> #VALUE! | K15: Feature Weight:
A16: Digger | B16: 1 | C16: {=IF(NOT(ISBLANK($A16)), (_xlfn.XLOOKUP($A16,Index!$B$2:$B$995,Index!$C$2:$C$995,"Not Found")),"")} -> T | D16: {=IF(NOT(ISBLANK(A16)), (_xlfn.XLOOKUP($A16,Index!$B$2:B$995,Index!$A$2:$A$995,"Not Found")),"")} -> base5-75 | E16: {=IF(NOT(ISBLANK($A16)), (_xlfn.XLOOKUP($A16,Index!$B$2:$B$995,Index!$D$2:$D$995,"Not Found")),"")} -> u | F16: {=IF(NOT(ISBLANK($A16)), (_xlfn.XLOOKUP($A16,Index!$B$2:$B$995,Index!$E$2:$E$995,"Not Found")),"")} | G16: {=IF(NOT(ISBLANK(A16)), ((_xlfn.XLOOKUP(A16,Index!$B$2:$B$995,Index!$F$2:$F$995,"Not Found"))*B16),"")} -> #VALUE! | K16: =K2 -> R | L16: =IF(NOT(ISBLANK($K2)), SUMIFS($G$2:$G$32, $C$2:$C$32,$K2), "") -> 7.5
A17: Potion | B17: 1 | C17: {=IF(NOT(ISBLANK($A17)), (_xlfn.XLOOKUP($A17,Index!$B$2:$B$995,Index!$C$2:$C$995,"Not Found")),"")} -> T | D17: {=IF(NOT(ISBLANK(A17)), (_xlfn.XLOOKUP($A17,Index!$B$2:B$995,Index!$A$2:$A$995,"Not Found")),"")} -> base1-94 | E17: {=IF(NOT(ISBLANK($A17)), (_xlfn.XLOOKUP($A17,Index!$B$2:$B$995,Index!$D$2:$D$995,"Not Found")),"")} -> c | F17: {=IF(NOT(ISBLANK($A17)), (_xlfn.XLOOKUP($A17,Index!$B$2:$B$995,Index!$E$2:$E$995,"Not Found")),"")} | G17: {=IF(NOT(ISBLANK(A17)), ((_xlfn.XLOOKUP(A17,Index!$B$2:$B$995,Index!$F$2:$F$995,"Not Found"))*B17),"")} -> #VALUE! | K17: =K3 -> P | L17: =IF(NOT(ISBLANK($K3)), SUMIFS($G$2:$G$32, $C$2:$C$32,$K3), "") -> 4
A18: Lass | B18: 1 | C18: {=IF(NOT(ISBLANK($A18)), (_xlfn.XLOOKUP($A18,Index!$B$2:$B$995,Index!$C$2:$C$995,"Not Found")),"")} -> T | D18: {=IF(NOT(ISBLANK(A18)), (_xlfn.XLOOKUP($A18,Index!$B$2:B$995,Index!$A$2:$A$995,"Not Found")),"")} -> base1-75 | E18: {=IF(NOT(ISBLANK($A18)), (_xlfn.XLOOKUP($A18,Index!$B$2:$B$995,Index!$D$2:$D$995,"Not Found")),"")} -> r | F18: {=IF(NOT(ISBLANK($A18)), (_xlfn.XLOOKUP($A18,Index!$B$2:$B$995,Index!$E$2:$E$995,"Not Found")),"")} | G18: {=IF(NOT(ISBLANK(A18)), ((_xlfn.XLOOKUP(A18,Index!$B$2:$B$995,Index!$F$2:$F$995,"Not Found"))*B18),"")} -> #VALUE! | K18: =K4 -> W | L18: =IF(NOT(ISBLANK($K4)), SUMIFS($G$2:$G$32, $C$2:$C$32,$K4), "") -> 1.5
A19: Sleep! | B19: 1 | C19: {=IF(NOT(ISBLANK($A19)), (_xlfn.XLOOKUP($A19,Index!$B$2:$B$995,Index!$C$2:$C$995,"Not Found")),"")} -> T | D19: {=IF(NOT(ISBLANK(A19)), (_xlfn.XLOOKUP($A19,Index!$B$2:B$995,Index!$A$2:$A$995,"Not Found")),"")} -> base5-79 | E19: {=IF(NOT(ISBLANK($A19)), (_xlfn.XLOOKUP($A19,Index!$B$2:$B$995,Index!$D$2:$D$995,"Not Found")),"")} -> c | F19: {=IF(NOT(ISBLANK($A19)), (_xlfn.XLOOKUP($A19,Index!$B$2:$B$995,Index!$E$2:$E$995,"Not Found")),"")} | G19: {=IF(NOT(ISBLANK(A19)), ((_xlfn.XLOOKUP(A19,Index!$B$2:$B$995,Index!$F$2:$F$995,"Not Found"))*B19),"")} -> #VALUE! | K19: =K5 -> C | L19: =IF(NOT(ISBLANK($K5)), SUMIFS($G$2:$G$32, $C$2:$C$32,$K5), "") -> 0
A20: Energy Search | B20: 1 | C20: {=IF(NOT(ISBLANK($A20)), (_xlfn.XLOOKUP($A20,Index!$B$2:$B$995,Index!$C$2:$C$995,"Not Found")),"")} -> T | D20: {=IF(NOT(ISBLANK(A20)), (_xlfn.XLOOKUP($A20,Index!$B$2:B$995,Index!$A$2:$A$995,"Not Found")),"")} -> base3-59 | E20: {=IF(NOT(ISBLANK($A20)), (_xlfn.XLOOKUP($A20,Index!$B$2:$B$995,Index!$D$2:$D$995,"Not Found")),"")} -> c | F20: {=IF(NOT(ISBLANK($A20)), (_xlfn.XLOOKUP($A20,Index!$B$2:$B$995,Index!$E$2:$E$995,"Not Found")),"")} | G20: {=IF(NOT(ISBLANK(A20)), ((_xlfn.XLOOKUP(A20,Index!$B$2:$B$995,Index!$F$2:$F$995,"Not Found"))*B20),"")} -> #VALUE! | K20: =K6
A21: Imposter Oak's Revenge | B21: 1 | C21: {=IF(NOT(ISBLANK($A21)), (_xlfn.XLOOKUP($A21,Index!$B$2:$B$995,Index!$C$2:$C$995,"Not Found")),"")} -> T | D21: {=IF(NOT(ISBLANK(A21)), (_xlfn.XLOOKUP($A21,Index!$B$2:B$995,Index!$A$2:$A$995,"Not Found")),"")} -> base5-76 | E21: {=IF(NOT(ISBLANK($A21)), (_xlfn.XLOOKUP($A21,Index!$B$2:$B$995,Index!$D$2:$D$995,"Not Found")),"")} -> u | F21: {=IF(NOT(ISBLANK($A21)), (_xlfn.XLOOKUP($A21,Index!$B$2:$B$995,Index!$E$2:$E$995,"Not Found")),"")} | G21: {=IF(NOT(ISBLANK(A21)), ((_xlfn.XLOOKUP(A21,Index!$B$2:$B$995,Index!$F$2:$F$995,"Not Found"))*B21),"")} -> #VALUE! | K21: Total: | L21: =SUM(L15:L19) -> 13
A22: Defender | B22: 1 | C22: {=IF(NOT(ISBLANK($A22)), (_xlfn.XLOOKUP($A22,Index!$B$2:$B$995,Index!$C$2:$C$995,"Not Found")),"")} -> T | D22: {=IF(NOT(ISBLANK(A22)), (_xlfn.XLOOKUP($A22,Index!$B$2:B$995,Index!$A$2:$A$995,"Not Found")),"")} -> base1-80 | E22: {=IF(NOT(ISBLANK($A22)), (_xlfn.XLOOKUP($A22,Index!$B$2:$B$995,Index!$D$2:$D$995,"Not Found")),"")} -> u | F22: {=IF(NOT(ISBLANK($A22)), (_xlfn.XLOOKUP($A22,Index!$B$2:$B$995,Index!$E$2:$E$995,"Not Found")),"")} | G22: {=IF(NOT(ISBLANK(A22)), ((_xlfn.XLOOKUP(A22,Index!$B$2:$B$995,Index!$F$2:$F$995,"Not Found"))*B22),"")} -> #VALUE!
C23: {=IF(NOT(ISBLANK($A23)), (_xlfn.XLOOKUP($A23,Index!$B$2:$B$995,Index!$C$2:$C$995,"Not Found")),"")} | D23: {=IF(NOT(ISBLANK(A23)), (_xlfn.XLOOKUP($A23,Index!$B$2:B$995,Index!$A$2:$A$995,"Not Found")),"")} | E23: {=IF(NOT(ISBLANK($A23)), (_xlfn.XLOOKUP($A23,Index!$B$2:$B$995,Index!$D$2:$D$995,"Not Found")),"")} | F23: {=IF(NOT(ISBLANK($A23)), (_xlfn.XLOOKUP($A23,Index!$B$2:$B$995,Index!$E$2:$E$995,"Not Found")),"")} | G23: {=IF(NOT(ISBLANK(A23)), ((_xlfn.XLOOKUP(A23,Index!$B$2:$B$995,Index!$F$2:$F$995,"Not Found"))*B23),"")}
C24: {=IF(NOT(ISBLANK($A24)), (_xlfn.XLOOKUP($A24,Index!$B$2:$B$995,Index!$C$2:$C$995,"Not Found")),"")} | D24: {=IF(NOT(ISBLANK(A24)), (_xlfn.XLOOKUP($A24,Index!$B$2:B$995,Index!$A$2:$A$995,"Not Found")),"")} | E24: {=IF(NOT(ISBLANK($A24)), (_xlfn.XLOOKUP($A24,Index!$B$2:$B$995,Index!$D$2:$D$995,"Not Found")),"")} | F24: {=IF(NOT(ISBLANK($A24)), (_xlfn.XLOOKUP($A24,Index!$B$2:$B$995,Index!$E$2:$E$995,"Not Found")),"")} | G24: {=IF(NOT(ISBLANK(A24)), ((_xlfn.XLOOKUP(A24,Index!$B$2:$B$995,Index!$F$2:$F$995,"Not Found"))*B24),"")} | K24: Cover Card: | L24: Dark Charizard
C25: {=IF(NOT(ISBLANK($A25)), (_xlfn.XLOOKUP($A25,Index!$B$2:$B$995,Index!$C$2:$C$995,"Not Found")),"")} | D25: {=IF(NOT(ISBLANK(A25)), (_xlfn.XLOOKUP($A25,Index!$B$2:B$995,Index!$A$2:$A$995,"Not Found")),"")} | E25: {=IF(NOT(ISBLANK($A25)), (_xlfn.XLOOKUP($A25,Index!$B$2:$B$995,Index!$D$2:$D$995,"Not Found")),"")} | F25: {=IF(NOT(ISBLANK($A25)), (_xlfn.XLOOKUP($A25,Index!$B$2:$B$995,Index!$E$2:$E$995,"Not Found")),"")} | G25: {=IF(NOT(ISBLANK(A25)), ((_xlfn.XLOOKUP(A25,Index!$B$2:$B$995,Index!$F$2:$F$995,"Not Found"))*B25),"")}
C26: {=IF(NOT(ISBLANK($A26)), (_xlfn.XLOOKUP($A26,Index!$B$2:$B$995,Index!$C$2:$C$995,"Not Found")),"")} | D26: {=IF(NOT(ISBLANK(A26)), (_xlfn.XLOOKUP($A26,Index!$B$2:B$995,Index!$A$2:$A$995,"Not Found")),"")} | E26: {=IF(NOT(ISBLANK($A26)), (_xlfn.XLOOKUP($A26,Index!$B$2:$B$995,Index!$D$2:$D$995,"Not Found")),"")} | F26: {=IF(NOT(ISBLANK($A26)), (_xlfn.XLOOKUP($A26,Index!$B$2:$B$995,Index!$E$2:$E$995,"Not Found")),"")} | G26: {=IF(NOT(ISBLANK(A26)), ((_xlfn.XLOOKUP(A26,Index!$B$2:$B$995,Index!$F$2:$F$995,"Not Found"))*B26),"")}
C27: {=IF(NOT(ISBLANK($A27)), (_xlfn.XLOOKUP($A27,Index!$B$2:$B$995,Index!$C$2:$C$995,"Not Found")),"")} | D27: {=IF(NOT(ISBLANK(A27)), (_xlfn.XLOOKUP($A27,Index!$B$2:B$995,Index!$A$2:$A$995,"Not Found")),"")} | E27: {=IF(NOT(ISBLANK($A27)), (_xlfn.XLOOKUP($A27,Index!$B$2:$B$995,Index!$D$2:$D$995,"Not Found")),"")} | F27: {=IF(NOT(ISBLANK($A27)), (_xlfn.XLOOKUP($A27,Index!$B$2:$B$995,Index!$E$2:$E$995,"Not Found")),"")} | G27: {=IF(NOT(ISBLANK(A27)), ((_xlfn.XLOOKUP(A27,Index!$B$2:$B$995,Index!$F$2:$F$995,"Not Found"))*B27),"")}
C28: {=IF(NOT(ISBLANK($A28)), (_xlfn.XLOOKUP($A28,Index!$B$2:$B$995,Index!$C$2:$C$995,"Not Found")),"")} | D28: {=IF(NOT(ISBLANK(A28)), (_xlfn.XLOOKUP($A28,Index!$B$2:B$995,Index!$A$2:$A$995,"Not Found")),"")} | E28: {=IF(NOT(ISBLANK($A28)), (_xlfn.XLOOKUP($A28,Index!$B$2:$B$995,Index!$D$2:$D$995,"Not Found")),"")} | F28: {=IF(NOT(ISBLANK($A28)), (_xlfn.XLOOKUP($A28,Index!$B$2:$B$995,Index!$E$2:$E$995,"Not Found")),"")} | G28: {=IF(NOT(ISBLANK(A28)), ((_xlfn.XLOOKUP(A28,Index!$B$2:$B$995,Index!$F$2:$F$995,"Not Found"))*B28),"")}
C29: {=IF(NOT(ISBLANK($A29)), (_xlfn.XLOOKUP($A29,Index!$B$2:$B$995,Index!$C$2:$C$995,"Not Found")),"")} | D29: {=IF(NOT(ISBLANK(A29)), (_xlfn.XLOOKUP($A29,Index!$B$2:B$995,Index!$A$2:$A$995,"Not Found")),"")} | E29: {=IF(NOT(ISBLANK($A29)), (_xlfn.XLOOKUP($A29,Index!$B$2:$B$995,Index!$D$2:$D$995,"Not Found")),"")} | F29: {=IF(NOT(ISBLANK($A29)), (_xlfn.XLOOKUP($A29,Index!$B$2:$B$995,Index!$E$2:$E$995,"Not Found")),"")} | G29: {=IF(NOT(ISBLANK(A29)), ((_xlfn.XLOOKUP(A29,Index!$B$2:$B$995,Index!$F$2:$F$995,"Not Found"))*B29),"")}
C30: {=IF(NOT(ISBLANK($A30)), (_xlfn.XLOOKUP($A30,Index!$B$2:$B$995,Index!$C$2:$C$995,"Not Found")),"")} | D30: {=IF(NOT(ISBLANK(A30)), (_xlfn.XLOOKUP($A30,Index!$B$2:B$995,Index!$A$2:$A$995,"Not Found")),"")} | E30: {=IF(NOT(ISBLANK($A30)), (_xlfn.XLOOKUP($A30,Index!$B$2:$B$995,Index!$D$2:$D$995,"Not Found")),"")} | F30: {=IF(NOT(ISBLANK($A30)), (_xlfn.XLOOKUP($A30,Index!$B$2:$B$995,Index!$E$2:$E$995,"Not Found")),"")} | G30: {=IF(NOT(ISBLANK(A30)), ((_xlfn.XLOOKUP(A30,Index!$B$2:$B$995,Index!$F$2:$F$995,"Not Found"))*B30),"")}
C31: {=IF(NOT(ISBLANK($A31)), (_xlfn.XLOOKUP($A31,Index!$B$2:$B$995,Index!$C$2:$C$995,"Not Found")),"")} | D31: {=IF(NOT(ISBLANK(A31)), (_xlfn.XLOOKUP($A31,Index!$B$2:B$995,Index!$A$2:$A$995,"Not Found")),"")} | E31: {=IF(NOT(ISBLANK($A31)), (_xlfn.XLOOKUP($A31,Index!$B$2:$B$995,Index!$D$2:$D$995,"Not Found")),"")} | F31: {=IF(NOT(ISBLANK($A31)), (_xlfn.XLOOKUP($A31,Index!$B$2:$B$995,Index!$E$2:$E$995,"Not Found")),"")} | G31: {=IF(NOT(ISBLANK(A31)), ((_xlfn.XLOOKUP(A31,Index!$B$2:$B$995,Index!$F$2:$F$995,"Not Found"))*B31),"")}
C32: {=IF(NOT(ISBLANK($A32)), (_xlfn.XLOOKUP($A32,Index!$B$2:$B$995,Index!$C$2:$C$995,"Not Found")),"")} | D32: {=IF(NOT(ISBLANK(A32)), (_xlfn.XLOOKUP($A32,Index!$B$2:B$995,Index!$A$2:$A$995,"Not Found")),"")} | E32: {=IF(NOT(ISBLANK($A32)), (_xlfn.XLOOKUP($A32,Index!$B$2:$B$995,Index!$D$2:$D$995,"Not Found")),"")} | F32: {=IF(NOT(ISBLANK($A32)), (_xlfn.XLOOKUP($A32,Index!$B$2:$B$995,Index!$E$2:$E$995,"Not Found")),"")} | G32: {=IF(NOT(ISBLANK(A32)), ((_xlfn.XLOOKUP(A32,Index!$B$2:$B$995,Index!$F$2:$F$995,"Not Found"))*B32),"")}
C33: {=IF(NOT(ISBLANK($A33)), (_xlfn.XLOOKUP($A33,Index!$B$2:$B$995,Index!$C$2:$C$995,"Not Found")),"")} | D33: {=IF(NOT(ISBLANK(A33)), (_xlfn.XLOOKUP($A33,Index!$B$2:B$995,Index!$A$2:$A$995,"Not Found")),"")} | E33: {=IF(NOT(ISBLANK($A33)), (_xlfn.XLOOKUP($A33,Index!$B$2:$B$995,Index!$D$2:$D$995,"Not Found")),"")} | F33: {=IF(NOT(ISBLANK($A33)), (_xlfn.XLOOKUP($A33,Index!$B$2:$B$995,Index!$E$2:$E$995,"Not Found")),"")} | G33: {=IF(NOT(ISBLANK(A33)), ((_xlfn.XLOOKUP(A33,Index!$B$2:$B$995,Index!$F$2:$F$995,"Not Found"))*B33),"")}
C34: {=IF(NOT(ISBLANK($A34)), (_xlfn.XLOOKUP($A34,Index!$B$2:$B$995,Index!$C$2:$C$995,"Not Found")),"")} | D34: {=IF(NOT(ISBLANK(A34)), (_xlfn.XLOOKUP($A34,Index!$B$2:B$995,Index!$A$2:$A$995,"Not Found")),"")} | E34: {=IF(NOT(ISBLANK($A34)), (_xlfn.XLOOKUP($A34,Index!$B$2:$B$995,Index!$D$2:$D$995,"Not Found")),"")} | F34: {=IF(NOT(ISBLANK($A34)), (_xlfn.XLOOKUP($A34,Index!$B$2:$B$995,Index!$E$2:$E$995,"Not Found")),"")} | G34: {=IF(NOT(ISBLANK(A34)), ((_xlfn.XLOOKUP(A34,Index!$B$2:$B$995,Index!$F$2:$F$995,"Not Found"))*B34),"")}
C35: {=IF(NOT(ISBLANK($A35)), (_xlfn.XLOOKUP($A35,Index!$B$2:$B$995,Index!$C$2:$C$995,"Not Found")),"")} | D35: {=IF(NOT(ISBLANK(A35)), (_xlfn.XLOOKUP($A35,Index!$B$2:B$995,Index!$A$2:$A$995,"Not Found")),"")} | E35: {=IF(NOT(ISBLANK($A35)), (_xlfn.XLOOKUP($A35,Index!$B$2:$B$995,Index!$D$2:$D$995,"Not Found")),"")} | F35: {=IF(NOT(ISBLANK($A35)), (_xlfn.XLOOKUP($A35,Index!$B$2:$B$995,Index!$E$2:$E$995,"Not Found")),"")} | G35: {=IF(NOT(ISBLANK(A35)), ((_xlfn.XLOOKUP(A35,Index!$B$2:$B$995,Index!$F$2:$F$995,"Not Found"))*B35),"")}
C36: {=IF(NOT(ISBLANK($A36)), (_xlfn.XLOOKUP($A36,Index!$B$2:$B$995,Index!$C$2:$C$995,"Not Found")),"")} | D36: {=IF(NOT(ISBLANK(A36)), (_xlfn.XLOOKUP($A36,Index!$B$2:B$995,Index!$A$2:$A$995,"Not Found")),"")} | E36: {=IF(NOT(ISBLANK($A36)), (_xlfn.XLOOKUP($A36,Index!$B$2:$B$995,Index!$D$2:$D$995,"Not Found")),"")} | F36: {=IF(NOT(ISBLANK($A36)), (_xlfn.XLOOKUP($A36,Index!$B$2:$B$995,Index!$E$2:$E$995,"Not Found")),"")} | G36: {=IF(NOT(ISBLANK(A36)), ((_xlfn.XLOOKUP(A36,Index!$B$2:$B$995,Index!$F$2:$F$995,"Not Found"))*B36),"")}
... C77: {=IF(NOT(ISBLANK($A77)), (_xlfn.XLOOKUP($A77,Index!$B$2:$B$995,Index!$C$2:$C$995,"Not Found")),"")} | D77: {=IF(NOT(ISBLANK(A77)), (_xlfn.XLOOKUP($A77,Index!$B$2:B$995,Index!$A$2:$A$995,"Not Found")),"")} | E77: {=IF(NOT(ISBLANK($A77)), (_xlfn.XLOOKUP($A77,Index!$B$2:$B$995,Index!$D$2:$D$995,"Not Found")),"")} | F77: {=IF(NOT(ISBLANK($A77)), (_xlfn.XLOOKUP($A77,Index!$B$2:$B$995,Index!$E$2:$E$995,"Not Found")),"")} | G77: {=IF(NOT(ISBLANK(A77)), ((_xlfn.XLOOKUP(A77,Index!$B$2:$B$995,Index!$F$2:$F$995,"Not Found"))*B77),"")}

Sheet R T2-4
A1: Card | B1: Quantity | C1: Type | D1: ID | E1: Stage / Rarity | F1: Remaining Evo | G1: Feature Weight | I1: Card Total | K1: Type | L1: Num | M1: Basic | N1: S1 Max | O1: S1 Mid | P1: S2 | Q1: No Evolve
A2: Abra R | B2: 4 | C2: {=IF(NOT(ISBLANK($A2)), (_xlfn.XLOOKUP($A2,Index!$B$2:$B$995,Index!$C$2:$C$995,"Not Found")),"")} -> P | D2: {=IF(NOT(ISBLANK(A2)), (_xlfn.XLOOKUP($A2,Index!$B$2:B$995,Index!$A$2:$A$995,"Not Found")),"")} -> base5-49 | E2: {=IF(NOT(ISBLANK($A2)), (_xlfn.XLOOKUP($A2,Index!$B$2:$B$995,Index!$D$2:$D$995,"Not Found")),"")} -> b | F2: {=IF(NOT(ISBLANK($A2)), (_xlfn.XLOOKUP($A2,Index!$B$2:$B$995,Index!$E$2:$E$995,"Not Found")),"")} -> y | G2: {=IF(NOT(ISBLANK(A2)), ((_xlfn.XLOOKUP(A2,Index!$B$2:$B$995,Index!$F$2:$F$995,"Not Found"))*B2),"")} -> 0 | I2: =SUM(B2:B38) -> 60 | K2: P | L2: =IF(NOT(ISBLANK(K2)), SUM(M2:P2), "") -> 12 | M2: =IF(NOT(ISBLANK($K2)), SUMIFS($B$2:$B$32, $E$2:$E$32, "B", $C$2:$C$32,$K2), "") -> 7 | N2: =IF(NOT(ISBLANK($K2)),SUMIFS($B$2:$B$32,$E$2:$E$32, "1", $C$2:$C$32,$K2,$F$2:$F$32,"N"), "") -> 1 | O2: =IF(NOT(ISBLANK($K2)),SUMIFS($B$2:$B$32,$E$2:$E$32, "1", $C$2:$C$32,$K2,$F$2:$F$32,"Y"), "") -> 3 | P2: =IF(NOT(ISBLANK($K2)),SUMIFS($B$2:$B$32,$E$2:$E$32, "2", $C$2:$C$32,$K2), "") -> 1 | Q2: =IF(NOT(ISBLANK($K2)),SUMIFS($B$2:$B$32,$E$2:$E$32, "B", $C$2:$C$32,$K2,$F$2:$F$32,"N"), "") -> 1
A3: Dark Kadabra | B3: 3 | C3: {=IF(NOT(ISBLANK($A3)), (_xlfn.XLOOKUP($A3,Index!$B$2:$B$995,Index!$C$2:$C$995,"Not Found")),"")} -> P | D3: {=IF(NOT(ISBLANK(A3)), (_xlfn.XLOOKUP($A3,Index!$B$2:B$995,Index!$A$2:$A$995,"Not Found")),"")} -> base5-39 | E3: {=IF(NOT(ISBLANK($A3)), (_xlfn.XLOOKUP($A3,Index!$B$2:$B$995,Index!$D$2:$D$995,"Not Found")),"")} -> 1 | F3: {=IF(NOT(ISBLANK($A3)), (_xlfn.XLOOKUP($A3,Index!$B$2:$B$995,Index!$E$2:$E$995,"Not Found")),"")} -> y | G3: {=IF(NOT(ISBLANK(A3)), ((_xlfn.XLOOKUP(A3,Index!$B$2:$B$995,Index!$F$2:$F$995,"Not Found"))*B3),"")} -> 1.5 | K3: C | L3: =IF(NOT(ISBLANK(K3)), SUM(M3:P3), "") -> 8 | M3: =IF(NOT(ISBLANK($K3)), SUMIFS($B$2:$B$32, $E$2:$E$32, "B", $C$2:$C$32,$K3), "") -> 6 | N3: =IF(NOT(ISBLANK($K3)),SUMIFS($B$2:$B$32,$E$2:$E$32, "1", $C$2:$C$32,$K3,$F$2:$F$32,"N"), "") -> 2 | O3: =IF(NOT(ISBLANK($K3)),SUMIFS($B$2:$B$32,$E$2:$E$32, "1", $C$2:$C$32,$K3,$F$2:$F$32,"Y"), "") -> 0 | P3: =IF(NOT(ISBLANK($K3)),SUMIFS($B$2:$B$32,$E$2:$E$32, "2", $C$2:$C$32,$K3), "") -> 0 | Q3: =IF(NOT(ISBLANK($K3)),SUMIFS($B$2:$B$32,$E$2:$E$32, "B", $C$2:$C$32,$K3,$F$2:$F$32,"N"), "") -> 1
A4: Dark Alakazam | B4: 1 | C4: {=IF(NOT(ISBLANK($A4)), (_xlfn.XLOOKUP($A4,Index!$B$2:$B$995,Index!$C$2:$C$995,"Not Found")),"")} -> P | D4: {=IF(NOT(ISBLANK(A4)), (_xlfn.XLOOKUP($A4,Index!$B$2:B$995,Index!$A$2:$A$995,"Not Found")),"")} -> base5-1 | E4: {=IF(NOT(ISBLANK($A4)), (_xlfn.XLOOKUP($A4,Index!$B$2:$B$995,Index!$D$2:$D$995,"Not Found")),"")} -> 2 | F4: {=IF(NOT(ISBLANK($A4)), (_xlfn.XLOOKUP($A4,Index!$B$2:$B$995,Index!$E$2:$E$995,"Not Found")),"")} | G4: {=IF(NOT(ISBLANK(A4)), ((_xlfn.XLOOKUP(A4,Index!$B$2:$B$995,Index!$F$2:$F$995,"Not Found"))*B4),"")} -> 3 | K4: W | L4: =IF(NOT(ISBLANK(K4)), SUM(M4:P4), "") -> 5 | M4: =IF(NOT(ISBLANK($K4)), SUMIFS($B$2:$B$32, $E$2:$E$32, "B", $C$2:$C$32,$K4), "") -> 3 | N4: =IF(NOT(ISBLANK($K4)),SUMIFS($B$2:$B$32,$E$2:$E$32, "1", $C$2:$C$32,$K4,$F$2:$F$32,"N"), "") -> 2 | O4: =IF(NOT(ISBLANK($K4)),SUMIFS($B$2:$B$32,$E$2:$E$32, "1", $C$2:$C$32,$K4,$F$2:$F$32,"Y"), "") -> 0 | P4: =IF(NOT(ISBLANK($K4)),SUMIFS($B$2:$B$32,$E$2:$E$32, "2", $C$2:$C$32,$K4), "") -> 0 | Q4: =IF(NOT(ISBLANK($K4)),SUMIFS($B$2:$B$32,$E$2:$E$32, "B", $C$2:$C$32,$K4,$F$2:$F$32,"N"), "") -> 0
A5: Slowpoke R | B5: 2 | C5: {=IF(NOT(ISBLANK($A5)), (_xlfn.XLOOKUP($A5,Index!$B$2:$B$995,Index!$C$2:$C$995,"Not Found")),"")} -> P | D5: {=IF(NOT(ISBLANK(A5)), (_xlfn.XLOOKUP($A5,Index!$B$2:B$995,Index!$A$2:$A$995,"Not Found")),"")} -> base5-67 | E5: {=IF(NOT(ISBLANK($A5)), (_xlfn.XLOOKUP($A5,Index!$B$2:$B$995,Index!$D$2:$D$995,"Not Found")),"")} -> b | F5: {=IF(NOT(ISBLANK($A5)), (_xlfn.XLOOKUP($A5,Index!$B$2:$B$995,Index!$E$2:$E$995,"Not Found")),"")} -> y | G5: {=IF(NOT(ISBLANK(A5)), ((_xlfn.XLOOKUP(A5,Index!$B$2:$B$995,Index!$F$2:$F$995,"Not Found"))*B5),"")} -> 0 | L5: =IF(NOT(ISBLANK(K5)), SUM(M5:P5), "") | M5: =IF(NOT(ISBLANK($K5)), SUMIFS($B$2:$B$32, $E$2:$E$32, "B", $C$2:$C$32,$K5), "") | N5: =IF(NOT(ISBLANK($K5)),SUMIFS($B$2:$B$32,$E$2:$E$32, "1", $C$2:$C$32,$K5,$F$2:$F$32,"N"), "") | O5: =IF(NOT(ISBLANK($K5)),SUMIFS($B$2:$B$32,$E$2:$E$32, "1", $C$2:$C$32,$K5,$F$2:$F$32,"Y"), "") | P5: =IF(NOT(ISBLANK($K5)),SUMIFS($B$2:$B$32,$E$2:$E$32, "2", $C$2:$C$32,$K5), "") | Q5: =IF(NOT(ISBLANK($K5)),SUMIFS($B$2:$B$32,$E$2:$E$32, "B", $C$2:$C$32,$K5,$F$2:$F$32,"N"), "")
A6: Dark Slowbro NH | B6: 1 | C6: {=IF(NOT(ISBLANK($A6)), (_xlfn.XLOOKUP($A6,Index!$B$2:$B$995,Index!$C$2:$C$995,"Not Found")),"")} -> P | D6: {=IF(NOT(ISBLANK(A6)), (_xlfn.XLOOKUP($A6,Index!$B$2:B$995,Index!$A$2:$A$995,"Not Found")),"")} -> base5-29 | E6: {=IF(NOT(ISBLANK($A6)), (_xlfn.XLOOKUP($A6,Index!$B$2:$B$995,Index!$D$2:$D$995,"Not Found")),"")} -> 1 | F6: {=IF(NOT(ISBLANK($A6)), (_xlfn.XLOOKUP($A6,Index!$B$2:$B$995,Index!$E$2:$E$995,"Not Found")),"")} -> n | G6: {=IF(NOT(ISBLANK(A6)), ((_xlfn.XLOOKUP(A6,Index!$B$2:$B$995,Index!$F$2:$F$995,"Not Found"))*B6),"")} -> 1 | L6: =IF(NOT(ISBLANK(K6)), SUM(M6:P6), "") | M6: =IF(NOT(ISBLANK($K6)), COUNTIFS($E$2:$E$32, "B", $C$2:$C$32,$K6), "") | N6: =IF(NOT(ISBLANK(K6)),COUNTIFS($E$2:$E$32, "1", $C$2:$C$32,$K6,$F$2:$F$32,"N"), "") | O6: =IF(NOT(ISBLANK($K6)),COUNTIFS($E$2:$E$32, "1", $C$2:$C$32,$K6,$F$2:$F$32,"Y"), "") | P6: =IF(NOT(ISBLANK($K6)),COUNTIFS($E$2:$E$32, "2", $C$2:$C$32,$K6), "") | Q6: =IF(NOT(ISBLANK($K6)),COUNTIFS($E$2:$E$32, "B", $C$2:$C$32,$K6,$F$2:$F$32,"N"), "")
A7: Psyduck R | B7: 3 | C7: {=IF(NOT(ISBLANK($A7)), (_xlfn.XLOOKUP($A7,Index!$B$2:$B$995,Index!$C$2:$C$995,"Not Found")),"")} -> W | D7: {=IF(NOT(ISBLANK(A7)), (_xlfn.XLOOKUP($A7,Index!$B$2:B$995,Index!$A$2:$A$995,"Not Found")),"")} -> base5-65 | E7: {=IF(NOT(ISBLANK($A7)), (_xlfn.XLOOKUP($A7,Index!$B$2:$B$995,Index!$D$2:$D$995,"Not Found")),"")} -> b | F7: {=IF(NOT(ISBLANK($A7)), (_xlfn.XLOOKUP($A7,Index!$B$2:$B$995,Index!$E$2:$E$995,"Not Found")),"")} -> y | G7: {=IF(NOT(ISBLANK(A7)), ((_xlfn.XLOOKUP(A7,Index!$B$2:$B$995,Index!$F$2:$F$995,"Not Found"))*B7),"")} -> 0 | K7: Total | L7: =SUM(L2:L6) -> 25 | M7: =SUM(M2:M6) -> 16 | N7: =SUM(N2:N6) -> 5 | O7: =SUM(O2:O6) -> 3 | P7: =SUM(P2:P6) -> 1 | Q7: =SUM(Q2:Q6) -> 2
A8: Dark Golduck | B8: 2 | C8: {=IF(NOT(ISBLANK($A8)), (_xlfn.XLOOKUP($A8,Index!$B$2:$B$995,Index!$C$2:$C$995,"Not Found")),"")} -> W | D8: {=IF(NOT(ISBLANK(A8)), (_xlfn.XLOOKUP($A8,Index!$B$2:B$995,Index!$A$2:$A$995,"Not Found")),"")} -> base5-37 | E8: {=IF(NOT(ISBLANK($A8)), (_xlfn.XLOOKUP($A8,Index!$B$2:$B$995,Index!$D$2:$D$995,"Not Found")),"")} -> 1 | F8: {=IF(NOT(ISBLANK($A8)), (_xlfn.XLOOKUP($A8,Index!$B$2:$B$995,Index!$E$2:$E$995,"Not Found")),"")} -> n | G8: {=IF(NOT(ISBLANK(A8)), ((_xlfn.XLOOKUP(A8,Index!$B$2:$B$995,Index!$F$2:$F$995,"Not Found"))*B8),"")} -> 3
A9: Rattata R | B9: 3 | C9: {=IF(NOT(ISBLANK($A9)), (_xlfn.XLOOKUP($A9,Index!$B$2:$B$995,Index!$C$2:$C$995,"Not Found")),"")} -> C | D9: {=IF(NOT(ISBLANK(A9)), (_xlfn.XLOOKUP($A9,Index!$B$2:B$995,Index!$A$2:$A$995,"Not Found")),"")} -> base5-66 | E9: {=IF(NOT(ISBLANK($A9)), (_xlfn.XLOOKUP($A9,Index!$B$2:$B$995,Index!$D$2:$D$995,"Not Found")),"")} -> b | F9: {=IF(NOT(ISBLANK($A9)), (_xlfn.XLOOKUP($A9,Index!$B$2:$B$995,Index!$E$2:$E$995,"Not Found")),"")} -> y | G9: {=IF(NOT(ISBLANK(A9)), ((_xlfn.XLOOKUP(A9,Index!$B$2:$B$995,Index!$F$2:$F$995,"Not Found"))*B9),"")} -> 0 | M9: Common | N9: Uncommon | O9: Rare
A10: Dark Raticate | B10: 1 | C10: {=IF(NOT(ISBLANK($A10)), (_xlfn.XLOOKUP($A10,Index!$B$2:$B$995,Index!$C$2:$C$995,"Not Found")),"")} -> C | D10: {=IF(NOT(ISBLANK(A10)), (_xlfn.XLOOKUP($A10,Index!$B$2:B$995,Index!$A$2:$A$995,"Not Found")),"")} -> base5-51 | E10: {=IF(NOT(ISBLANK($A10)), (_xlfn.XLOOKUP($A10,Index!$B$2:$B$995,Index!$D$2:$D$995,"Not Found")),"")} -> 1 | F10: {=IF(NOT(ISBLANK($A10)), (_xlfn.XLOOKUP($A10,Index!$B$2:$B$995,Index!$E$2:$E$995,"Not Found")),"")} -> n | G10: {=IF(NOT(ISBLANK(A10)), ((_xlfn.XLOOKUP(A10,Index!$B$2:$B$995,Index!$F$2:$F$995,"Not Found"))*B10),"")} -> 1.5 | K10: Trainer | L10: =SUM(M10:P10) -> 10 | M10: =IF(NOT(ISBLANK($K10)), SUMIFS($B$2:$B$32,$E$2:$E$32, "C", $C$2:$C$32,"T"), "") -> 6 | N10: =IF(NOT(ISBLANK($K10)), SUMIFS($B$2:$B$32,$E$2:$E$32, "U", $C$2:$C$32,"T"), "") -> 3 | O10: =IF(NOT(ISBLANK($K$2)), SUMIFS($B$2:$B$32,$E$2:$E$32, "R", $C$2:$C$32,"T"), "") -> 1
A11: Meowth R | B11: 2 | C11: {=IF(NOT(ISBLANK($A11)), (_xlfn.XLOOKUP($A11,Index!$B$2:$B$995,Index!$C$2:$C$995,"Not Found")),"")} -> C | D11: {=IF(NOT(ISBLANK(A11)), (_xlfn.XLOOKUP($A11,Index!$B$2:B$995,Index!$A$2:$A$995,"Not Found")),"")} -> base5-62 | E11: {=IF(NOT(ISBLANK($A11)), (_xlfn.XLOOKUP($A11,Index!$B$2:$B$995,Index!$D$2:$D$995,"Not Found")),"")} -> b | F11: {=IF(NOT(ISBLANK($A11)), (_xlfn.XLOOKUP($A11,Index!$B$2:$B$995,Index!$E$2:$E$995,"Not Found")),"")} -> y | G11: {=IF(NOT(ISBLANK(A11)), ((_xlfn.XLOOKUP(A11,Index!$B$2:$B$995,Index!$F$2:$F$995,"Not Found"))*B11),"")} -> 0 | K11: Energy | L11: =IF(NOT(ISBLANK($K$2)), SUMIFS($B$2:$B$32, $C$2:$C$32,"Energy"), "") -> 25
A12: Dark Persian | B12: 1 | C12: {=IF(NOT(ISBLANK($A12)), (_xlfn.XLOOKUP($A12,Index!$B$2:$B$995,Index!$C$2:$C$995,"Not Found")),"")} -> C | D12: {=IF(NOT(ISBLANK(A12)), (_xlfn.XLOOKUP($A12,Index!$B$2:B$995,Index!$A$2:$A$995,"Not Found")),"")} -> base5-42 | E12: {=IF(NOT(ISBLANK($A12)), (_xlfn.XLOOKUP($A12,Index!$B$2:$B$995,Index!$D$2:$D$995,"Not Found")),"")} -> 1 | F12: {=IF(NOT(ISBLANK($A12)), (_xlfn.XLOOKUP($A12,Index!$B$2:$B$995,Index!$E$2:$E$995,"Not Found")),"")} -> n | G12: {=IF(NOT(ISBLANK(A12)), ((_xlfn.XLOOKUP(A12,Index!$B$2:$B$995,Index!$F$2:$F$995,"Not Found"))*B12),"")} -> 0.5 | K12: Pokemon | L12: =L7 -> 25
A13: DC Energy | B13: 1 | C13: {=IF(NOT(ISBLANK($A13)), (_xlfn.XLOOKUP($A13,Index!$B$2:$B$995,Index!$C$2:$C$995,"Not Found")),"")} -> Energy | D13: {=IF(NOT(ISBLANK(A13)), (_xlfn.XLOOKUP($A13,Index!$B$2:B$995,Index!$A$2:$A$995,"Not Found")),"")} -> base1-96 | E13: {=IF(NOT(ISBLANK($A13)), (_xlfn.XLOOKUP($A13,Index!$B$2:$B$995,Index!$D$2:$D$995,"Not Found")),"")} | F13: {=IF(NOT(ISBLANK($A13)), (_xlfn.XLOOKUP($A13,Index!$B$2:$B$995,Index!$E$2:$E$995,"Not Found")),"")} | G13: {=IF(NOT(ISBLANK(A13)), ((_xlfn.XLOOKUP(A13,Index!$B$2:$B$995,Index!$F$2:$F$995,"Not Found"))*B13),"")} -> 0
A14: Potion Energy | B14: 1 | C14: {=IF(NOT(ISBLANK($A14)), (_xlfn.XLOOKUP($A14,Index!$B$2:$B$995,Index!$C$2:$C$995,"Not Found")),"")} -> Energy | D14: {=IF(NOT(ISBLANK(A14)), (_xlfn.XLOOKUP($A14,Index!$B$2:B$995,Index!$A$2:$A$995,"Not Found")),"")} -> base5-82 | E14: {=IF(NOT(ISBLANK($A14)), (_xlfn.XLOOKUP($A14,Index!$B$2:$B$995,Index!$D$2:$D$995,"Not Found")),"")} | F14: {=IF(NOT(ISBLANK($A14)), (_xlfn.XLOOKUP($A14,Index!$B$2:$B$995,Index!$E$2:$E$995,"Not Found")),"")} | G14: {=IF(NOT(ISBLANK(A14)), ((_xlfn.XLOOKUP(A14,Index!$B$2:$B$995,Index!$F$2:$F$995,"Not Found"))*B14),"")} -> 0
A15: Full Heal Energy | B15: 1 | C15: {=IF(NOT(ISBLANK($A15)), (_xlfn.XLOOKUP($A15,Index!$B$2:$B$995,Index!$C$2:$C$995,"Not Found")),"")} -> Energy | D15: {=IF(NOT(ISBLANK(A15)), (_xlfn.XLOOKUP($A15,Index!$B$2:B$995,Index!$A$2:$A$995,"Not Found")),"")} -> base5-81 | E15: {=IF(NOT(ISBLANK($A15)), (_xlfn.XLOOKUP($A15,Index!$B$2:$B$995,Index!$D$2:$D$995,"Not Found")),"")} | F15: {=IF(NOT(ISBLANK($A15)), (_xlfn.XLOOKUP($A15,Index!$B$2:$B$995,Index!$E$2:$E$995,"Not Found")),"")} | G15: {=IF(NOT(ISBLANK(A15)), ((_xlfn.XLOOKUP(A15,Index!$B$2:$B$995,Index!$F$2:$F$995,"Not Found"))*B15),"")} -> 0 | K15: Feature Weight:
A16: P Energy | B16: 22 | C16: {=IF(NOT(ISBLANK($A16)), (_xlfn.XLOOKUP($A16,Index!$B$2:$B$995,Index!$C$2:$C$995,"Not Found")),"")} -> Energy | D16: {=IF(NOT(ISBLANK(A16)), (_xlfn.XLOOKUP($A16,Index!$B$2:B$995,Index!$A$2:$A$995,"Not Found")),"")} -> base1-101 | E16: {=IF(NOT(ISBLANK($A16)), (_xlfn.XLOOKUP($A16,Index!$B$2:$B$995,Index!$D$2:$D$995,"Not Found")),"")} | F16: {=IF(NOT(ISBLANK($A16)), (_xlfn.XLOOKUP($A16,Index!$B$2:$B$995,Index!$E$2:$E$995,"Not Found")),"")} | G16: {=IF(NOT(ISBLANK(A16)), ((_xlfn.XLOOKUP(A16,Index!$B$2:$B$995,Index!$F$2:$F$995,"Not Found"))*B16),"")} -> 0 | K16: =K2 -> P | L16: =IF(NOT(ISBLANK($K2)), SUMIFS($G$2:$G$32, $C$2:$C$32,$K2), "") -> 6
A17: Mewtwo | B17: 1 | C17: {=IF(NOT(ISBLANK($A17)), (_xlfn.XLOOKUP($A17,Index!$B$2:$B$995,Index!$C$2:$C$995,"Not Found")),"")} -> P | D17: {=IF(NOT(ISBLANK(A17)), (_xlfn.XLOOKUP($A17,Index!$B$2:B$995,Index!$A$2:$A$995,"Not Found")),"")} -> base1-10 | E17: {=IF(NOT(ISBLANK($A17)), (_xlfn.XLOOKUP($A17,Index!$B$2:$B$995,Index!$D$2:$D$995,"Not Found")),"")} -> b | F17: {=IF(NOT(ISBLANK($A17)), (_xlfn.XLOOKUP($A17,Index!$B$2:$B$995,Index!$E$2:$E$995,"Not Found")),"")} -> n | G17: {=IF(NOT(ISBLANK(A17)), ((_xlfn.XLOOKUP(A17,Index!$B$2:$B$995,Index!$F$2:$F$995,"Not Found"))*B17),"")} -> 0.5 | K17: =K3 -> C | L17: =IF(NOT(ISBLANK($K3)), SUMIFS($G$2:$G$32, $C$2:$C$32,$K3), "") -> 2
A18: Porygon R | B18: 1 | C18: {=IF(NOT(ISBLANK($A18)), (_xlfn.XLOOKUP($A18,Index!$B$2:$B$995,Index!$C$2:$C$995,"Not Found")),"")} -> C | D18: {=IF(NOT(ISBLANK(A18)), (_xlfn.XLOOKUP($A18,Index!$B$2:B$995,Index!$A$2:$A$995,"Not Found")),"")} -> base5-48 | E18: {=IF(NOT(ISBLANK($A18)), (_xlfn.XLOOKUP($A18,Index!$B$2:$B$995,Index!$D$2:$D$995,"Not Found")),"")} -> b | F18: {=IF(NOT(ISBLANK($A18)), (_xlfn.XLOOKUP($A18,Index!$B$2:$B$995,Index!$E$2:$E$995,"Not Found")),"")} -> n | G18: {=IF(NOT(ISBLANK(A18)), ((_xlfn.XLOOKUP(A18,Index!$B$2:$B$995,Index!$F$2:$F$995,"Not Found"))*B18),"")} -> 0 | K18: =K4 -> W | L18: =IF(NOT(ISBLANK($K4)), SUMIFS($G$2:$G$32, $C$2:$C$32,$K4), "") -> 3
A19: Sleep! | B19: 1 | C19: {=IF(NOT(ISBLANK($A19)), (_xlfn.XLOOKUP($A19,Index!$B$2:$B$995,Index!$C$2:$C$995,"Not Found")),"")} -> T | D19: {=IF(NOT(ISBLANK(A19)), (_xlfn.XLOOKUP($A19,Index!$B$2:B$995,Index!$A$2:$A$995,"Not Found")),"")} -> base5-79 | E19: {=IF(NOT(ISBLANK($A19)), (_xlfn.XLOOKUP($A19,Index!$B$2:$B$995,Index!$D$2:$D$995,"Not Found")),"")} -> c | F19: {=IF(NOT(ISBLANK($A19)), (_xlfn.XLOOKUP($A19,Index!$B$2:$B$995,Index!$E$2:$E$995,"Not Found")),"")} | G19: {=IF(NOT(ISBLANK(A19)), ((_xlfn.XLOOKUP(A19,Index!$B$2:$B$995,Index!$F$2:$F$995,"Not Found"))*B19),"")} -> #VALUE! | K19: =K5 | L19: =IF(NOT(ISBLANK($K5)), SUMIFS($G$2:$G$32, $C$2:$C$32,$K5), "")
A20: Bill | B20: 2 | C20: {=IF(NOT(ISBLANK($A20)), (_xlfn.XLOOKUP($A20,Index!$B$2:$B$995,Index!$C$2:$C$995,"Not Found")),"")} -> T | D20: {=IF(NOT(ISBLANK(A20)), (_xlfn.XLOOKUP($A20,Index!$B$2:B$995,Index!$A$2:$A$995,"Not Found")),"")} -> base1-91 | E20: {=IF(NOT(ISBLANK($A20)), (_xlfn.XLOOKUP($A20,Index!$B$2:$B$995,Index!$D$2:$D$995,"Not Found")),"")} -> c | F20: {=IF(NOT(ISBLANK($A20)), (_xlfn.XLOOKUP($A20,Index!$B$2:$B$995,Index!$E$2:$E$995,"Not Found")),"")} | G20: {=IF(NOT(ISBLANK(A20)), ((_xlfn.XLOOKUP(A20,Index!$B$2:$B$995,Index!$F$2:$F$995,"Not Found"))*B20),"")} -> #VALUE! | K20: =K6
A21: Professor Oak | B21: 1 | C21: {=IF(NOT(ISBLANK($A21)), (_xlfn.XLOOKUP($A21,Index!$B$2:$B$995,Index!$C$2:$C$995,"Not Found")),"")} -> T | D21: {=IF(NOT(ISBLANK(A21)), (_xlfn.XLOOKUP($A21,Index!$B$2:B$995,Index!$A$2:$A$995,"Not Found")),"")} -> base1-88 | E21: {=IF(NOT(ISBLANK($A21)), (_xlfn.XLOOKUP($A21,Index!$B$2:$B$995,Index!$D$2:$D$995,"Not Found")),"")} -> u | F21: {=IF(NOT(ISBLANK($A21)), (_xlfn.XLOOKUP($A21,Index!$B$2:$B$995,Index!$E$2:$E$995,"Not Found")),"")} | G21: {=IF(NOT(ISBLANK(A21)), ((_xlfn.XLOOKUP(A21,Index!$B$2:$B$995,Index!$F$2:$F$995,"Not Found"))*B21),"")} -> #VALUE! | K21: Total: | L21: =SUM(L15:L19) -> 11
A22: Gust of Wind | B22: 1 | C22: {=IF(NOT(ISBLANK($A22)), (_xlfn.XLOOKUP($A22,Index!$B$2:$B$995,Index!$C$2:$C$995,"Not Found")),"")} -> T | D22: {=IF(NOT(ISBLANK(A22)), (_xlfn.XLOOKUP($A22,Index!$B$2:B$995,Index!$A$2:$A$995,"Not Found")),"")} -> base1-93 | E22: {=IF(NOT(ISBLANK($A22)), (_xlfn.XLOOKUP($A22,Index!$B$2:$B$995,Index!$D$2:$D$995,"Not Found")),"")} -> c | F22: {=IF(NOT(ISBLANK($A22)), (_xlfn.XLOOKUP($A22,Index!$B$2:$B$995,Index!$E$2:$E$995,"Not Found")),"")} | G22: {=IF(NOT(ISBLANK(A22)), ((_xlfn.XLOOKUP(A22,Index!$B$2:$B$995,Index!$F$2:$F$995,"Not Found"))*B22),"")} -> #VALUE!
A23: Potion | B23: 1 | C23: {=IF(NOT(ISBLANK($A23)), (_xlfn.XLOOKUP($A23,Index!$B$2:$B$995,Index!$C$2:$C$995,"Not Found")),"")} -> T | D23: {=IF(NOT(ISBLANK(A23)), (_xlfn.XLOOKUP($A23,Index!$B$2:B$995,Index!$A$2:$A$995,"Not Found")),"")} -> base1-94 | E23: {=IF(NOT(ISBLANK($A23)), (_xlfn.XLOOKUP($A23,Index!$B$2:$B$995,Index!$D$2:$D$995,"Not Found")),"")} -> c | F23: {=IF(NOT(ISBLANK($A23)), (_xlfn.XLOOKUP($A23,Index!$B$2:$B$995,Index!$E$2:$E$995,"Not Found")),"")} | G23: {=IF(NOT(ISBLANK(A23)), ((_xlfn.XLOOKUP(A23,Index!$B$2:$B$995,Index!$F$2:$F$995,"Not Found"))*B23),"")} -> #VALUE!
A24: Item Finder | B24: 1 | C24: {=IF(NOT(ISBLANK($A24)), (_xlfn.XLOOKUP($A24,Index!$B$2:$B$995,Index!$C$2:$C$995,"Not Found")),"")} -> T | D24: {=IF(NOT(ISBLANK(A24)), (_xlfn.XLOOKUP($A24,Index!$B$2:B$995,Index!$A$2:$A$995,"Not Found")),"")} -> base1-74 | E24: {=IF(NOT(ISBLANK($A24)), (_xlfn.XLOOKUP($A24,Index!$B$2:$B$995,Index!$D$2:$D$995,"Not Found")),"")} -> r | F24: {=IF(NOT(ISBLANK($A24)), (_xlfn.XLOOKUP($A24,Index!$B$2:$B$995,Index!$E$2:$E$995,"Not Found")),"")} | G24: {=IF(NOT(ISBLANK(A24)), ((_xlfn.XLOOKUP(A24,Index!$B$2:$B$995,Index!$F$2:$F$995,"Not Found"))*B24),"")} -> #VALUE! | K24: Cover Card: | L24: Dark Alakazam
A25: PlusPower | B25: 1 | C25: {=IF(NOT(ISBLANK($A25)), (_xlfn.XLOOKUP($A25,Index!$B$2:$B$995,Index!$C$2:$C$995,"Not Found")),"")} -> T | D25: {=IF(NOT(ISBLANK(A25)), (_xlfn.XLOOKUP($A25,Index!$B$2:B$995,Index!$A$2:$A$995,"Not Found")),"")} -> base1-84 | E25: {=IF(NOT(ISBLANK($A25)), (_xlfn.XLOOKUP($A25,Index!$B$2:$B$995,Index!$D$2:$D$995,"Not Found")),"")} -> u | F25: {=IF(NOT(ISBLANK($A25)), (_xlfn.XLOOKUP($A25,Index!$B$2:$B$995,Index!$E$2:$E$995,"Not Found")),"")} | G25: {=IF(NOT(ISBLANK(A25)), ((_xlfn.XLOOKUP(A25,Index!$B$2:$B$995,Index!$F$2:$F$995,"Not Found"))*B25),"")} -> #VALUE!
A26: Defender | B26: 1 | C26: {=IF(NOT(ISBLANK($A26)), (_xlfn.XLOOKUP($A26,Index!$B$2:$B$995,Index!$C$2:$C$995,"Not Found")),"")} -> T | D26: {=IF(NOT(ISBLANK(A26)), (_xlfn.XLOOKUP($A26,Index!$B$2:B$995,Index!$A$2:$A$995,"Not Found")),"")} -> base1-80 | E26: {=IF(NOT(ISBLANK($A26)), (_xlfn.XLOOKUP($A26,Index!$B$2:$B$995,Index!$D$2:$D$995,"Not Found")),"")} -> u | F26: {=IF(NOT(ISBLANK($A26)), (_xlfn.XLOOKUP($A26,Index!$B$2:$B$995,Index!$E$2:$E$995,"Not Found")),"")} | G26: {=IF(NOT(ISBLANK(A26)), ((_xlfn.XLOOKUP(A26,Index!$B$2:$B$995,Index!$F$2:$F$995,"Not Found"))*B26),"")} -> #VALUE!
A27: Goop Gas Attack | B27: 1 | C27: {=IF(NOT(ISBLANK($A27)), (_xlfn.XLOOKUP($A27,Index!$B$2:$B$995,Index!$C$2:$C$995,"Not Found")),"")} -> T | D27: {=IF(NOT(ISBLANK(A27)), (_xlfn.XLOOKUP($A27,Index!$B$2:B$995,Index!$A$2:$A$995,"Not Found")),"")} -> base5-78 | E27: {=IF(NOT(ISBLANK($A27)), (_xlfn.XLOOKUP($A27,Index!$B$2:$B$995,Index!$D$2:$D$995,"Not Found")),"")} -> c | F27: {=IF(NOT(ISBLANK($A27)), (_xlfn.XLOOKUP($A27,Index!$B$2:$B$995,Index!$E$2:$E$995,"Not Found")),"")} | G27: {=IF(NOT(ISBLANK(A27)), ((_xlfn.XLOOKUP(A27,Index!$B$2:$B$995,Index!$F$2:$F$995,"Not Found"))*B27),"")} -> #VALUE!
C28: {=IF(NOT(ISBLANK($A28)), (_xlfn.XLOOKUP($A28,Index!$B$2:$B$995,Index!$C$2:$C$995,"Not Found")),"")} | D28: {=IF(NOT(ISBLANK(A28)), (_xlfn.XLOOKUP($A28,Index!$B$2:B$995,Index!$A$2:$A$995,"Not Found")),"")} | E28: {=IF(NOT(ISBLANK($A28)), (_xlfn.XLOOKUP($A28,Index!$B$2:$B$995,Index!$D$2:$D$995,"Not Found")),"")} | F28: {=IF(NOT(ISBLANK($A28)), (_xlfn.XLOOKUP($A28,Index!$B$2:$B$995,Index!$E$2:$E$995,"Not Found")),"")} | G28: {=IF(NOT(ISBLANK(A28)), ((_xlfn.XLOOKUP(A28,Index!$B$2:$B$995,Index!$F$2:$F$995,"Not Found"))*B28),"")}
C29: {=IF(NOT(ISBLANK($A29)), (_xlfn.XLOOKUP($A29,Index!$B$2:$B$995,Index!$C$2:$C$995,"Not Found")),"")} | D29: {=IF(NOT(ISBLANK(A29)), (_xlfn.XLOOKUP($A29,Index!$B$2:B$995,Index!$A$2:$A$995,"Not Found")),"")} | E29: {=IF(NOT(ISBLANK($A29)), (_xlfn.XLOOKUP($A29,Index!$B$2:$B$995,Index!$D$2:$D$995,"Not Found")),"")} | F29: {=IF(NOT(ISBLANK($A29)), (_xlfn.XLOOKUP($A29,Index!$B$2:$B$995,Index!$E$2:$E$995,"Not Found")),"")} | G29: {=IF(NOT(ISBLANK(A29)), ((_xlfn.XLOOKUP(A29,Index!$B$2:$B$995,Index!$F$2:$F$995,"Not Found"))*B29),"")}
C30: {=IF(NOT(ISBLANK($A30)), (_xlfn.XLOOKUP($A30,Index!$B$2:$B$995,Index!$C$2:$C$995,"Not Found")),"")} | D30: {=IF(NOT(ISBLANK(A30)), (_xlfn.XLOOKUP($A30,Index!$B$2:B$995,Index!$A$2:$A$995,"Not Found")),"")} | E30: {=IF(NOT(ISBLANK($A30)), (_xlfn.XLOOKUP($A30,Index!$B$2:$B$995,Index!$D$2:$D$995,"Not Found")),"")} | F30: {=IF(NOT(ISBLANK($A30)), (_xlfn.XLOOKUP($A30,Index!$B$2:$B$995,Index!$E$2:$E$995,"Not Found")),"")} | G30: {=IF(NOT(ISBLANK(A30)), ((_xlfn.XLOOKUP(A30,Index!$B$2:$B$995,Index!$F$2:$F$995,"Not Found"))*B30),"")}
C31: {=IF(NOT(ISBLANK($A31)), (_xlfn.XLOOKUP($A31,Index!$B$2:$B$995,Index!$C$2:$C$995,"Not Found")),"")} | D31: {=IF(NOT(ISBLANK(A31)), (_xlfn.XLOOKUP($A31,Index!$B$2:B$995,Index!$A$2:$A$995,"Not Found")),"")} | E31: {=IF(NOT(ISBLANK($A31)), (_xlfn.XLOOKUP($A31,Index!$B$2:$B$995,Index!$D$2:$D$995,"Not Found")),"")} | F31: {=IF(NOT(ISBLANK($A31)), (_xlfn.XLOOKUP($A31,Index!$B$2:$B$995,Index!$E$2:$E$995,"Not Found")),"")} | G31: {=IF(NOT(ISBLANK(A31)), ((_xlfn.XLOOKUP(A31,Index!$B$2:$B$995,Index!$F$2:$F$995,"Not Found"))*B31),"")}
C32: {=IF(NOT(ISBLANK($A32)), (_xlfn.XLOOKUP($A32,Index!$B$2:$B$995,Index!$C$2:$C$995,"Not Found")),"")} | D32: {=IF(NOT(ISBLANK(A32)), (_xlfn.XLOOKUP($A32,Index!$B$2:B$995,Index!$A$2:$A$995,"Not Found")),"")} | E32: {=IF(NOT(ISBLANK($A32)), (_xlfn.XLOOKUP($A32,Index!$B$2:$B$995,Index!$D$2:$D$995,"Not Found")),"")} | F32: {=IF(NOT(ISBLANK($A32)), (_xlfn.XLOOKUP($A32,Index!$B$2:$B$995,Index!$E$2:$E$995,"Not Found")),"")} | G32: {=IF(NOT(ISBLANK(A32)), ((_xlfn.XLOOKUP(A32,Index!$B$2:$B$995,Index!$F$2:$F$995,"Not Found"))*B32),"")}
C33: {=IF(NOT(ISBLANK($A33)), (_xlfn.XLOOKUP($A33,Index!$B$2:$B$995,Index!$C$2:$C$995,"Not Found")),"")} | D33: {=IF(NOT(ISBLANK(A33)), (_xlfn.XLOOKUP($A33,Index!$B$2:B$995,Index!$A$2:$A$995,"Not Found")),"")} | E33: {=IF(NOT(ISBLANK($A33)), (_xlfn.XLOOKUP($A33,Index!$B$2:$B$995,Index!$D$2:$D$995,"Not Found")),"")} | F33: {=IF(NOT(ISBLANK($A33)), (_xlfn.XLOOKUP($A33,Index!$B$2:$B$995,Index!$E$2:$E$995,"Not Found")),"")} | G33: {=IF(NOT(ISBLANK(A33)), ((_xlfn.XLOOKUP(A33,Index!$B$2:$B$995,Index!$F$2:$F$995,"Not Found"))*B33),"")}
C34: {=IF(NOT(ISBLANK($A34)), (_xlfn.XLOOKUP($A34,Index!$B$2:$B$995,Index!$C$2:$C$995,"Not Found")),"")} | D34: {=IF(NOT(ISBLANK(A34)), (_xlfn.XLOOKUP($A34,Index!$B$2:B$995,Index!$A$2:$A$995,"Not Found")),"")} | E34: {=IF(NOT(ISBLANK($A34)), (_xlfn.XLOOKUP($A34,Index!$B$2:$B$995,Index!$D$2:$D$995,"Not Found")),"")} | F34: {=IF(NOT(ISBLANK($A34)), (_xlfn.XLOOKUP($A34,Index!$B$2:$B$995,Index!$E$2:$E$995,"Not Found")),"")} | G34: {=IF(NOT(ISBLANK(A34)), ((_xlfn.XLOOKUP(A34,Index!$B$2:$B$995,Index!$F$2:$F$995,"Not Found"))*B34),"")}
C35: {=IF(NOT(ISBLANK($A35)), (_xlfn.XLOOKUP($A35,Index!$B$2:$B$995,Index!$C$2:$C$995,"Not Found")),"")} | D35: {=IF(NOT(ISBLANK(A35)), (_xlfn.XLOOKUP($A35,Index!$B$2:B$995,Index!$A$2:$A$995,"Not Found")),"")} | E35: {=IF(NOT(ISBLANK($A35)), (_xlfn.XLOOKUP($A35,Index!$B$2:$B$995,Index!$D$2:$D$995,"Not Found")),"")} | F35: {=IF(NOT(ISBLANK($A35)), (_xlfn.XLOOKUP($A35,Index!$B$2:$B$995,Index!$E$2:$E$995,"Not Found")),"")} | G35: {=IF(NOT(ISBLANK(A35)), ((_xlfn.XLOOKUP(A35,Index!$B$2:$B$995,Index!$F$2:$F$995,"Not Found"))*B35),"")}
C36: {=IF(NOT(ISBLANK($A36)), (_xlfn.XLOOKUP($A36,Index!$B$2:$B$995,Index!$C$2:$C$995,"Not Found")),"")} | D36: {=IF(NOT(ISBLANK(A36)), (_xlfn.XLOOKUP($A36,Index!$B$2:B$995,Index!$A$2:$A$995,"Not Found")),"")} | E36: {=IF(NOT(ISBLANK($A36)), (_xlfn.XLOOKUP($A36,Index!$B$2:$B$995,Index!$D$2:$D$995,"Not Found")),"")} | F36: {=IF(NOT(ISBLANK($A36)), (_xlfn.XLOOKUP($A36,Index!$B$2:$B$995,Index!$E$2:$E$995,"Not Found")),"")} | G36: {=IF(NOT(ISBLANK(A36)), ((_xlfn.XLOOKUP(A36,Index!$B$2:$B$995,Index!$F$2:$F$995,"Not Found"))*B36),"")}
C37: {=IF(NOT(ISBLANK($A37)), (_xlfn.XLOOKUP($A37,Index!$B$2:$B$995,Index!$C$2:$C$995,"Not Found")),"")} | D37: {=IF(NOT(ISBLANK(A37)), (_xlfn.XLOOKUP($A37,Index!$B$2:B$995,Index!$A$2:$A$995,"Not Found")),"")} | E37: {=IF(NOT(ISBLANK($A37)), (_xlfn.XLOOKUP($A37,Index!$B$2:$B$995,Index!$D$2:$D$995,"Not Found")),"")} | F37: {=IF(NOT(ISBLANK($A37)), (_xlfn.XLOOKUP($A37,Index!$B$2:$B$995,Index!$E$2:$E$995,"Not Found")),"")} | G37: {=IF(NOT(ISBLANK(A37)), ((_xlfn.XLOOKUP(A37,Index!$B$2:$B$995,Index!$F$2:$F$995,"Not Found"))*B37),"")}
C38: {=IF(NOT(ISBLANK($A38)), (_xlfn.XLOOKUP($A38,Index!$B$2:$B$995,Index!$C$2:$C$995,"Not Found")),"")} | D38: {=IF(NOT(ISBLANK(A38)), (_xlfn.XLOOKUP($A38,Index!$B$2:B$995,Index!$A$2:$A$995,"Not Found")),"")} | E38: {=IF(NOT(ISBLANK($A38)), (_xlfn.XLOOKUP($A38,Index!$B$2:$B$995,Index!$D$2:$D$995,"Not Found")),"")} | F38: {=IF(NOT(ISBLANK($A38)), (_xlfn.XLOOKUP($A38,Index!$B$2:$B$995,Index!$E$2:$E$995,"Not Found")),"")} | G38: {=IF(NOT(ISBLANK(A38)), ((_xlfn.XLOOKUP(A38,Index!$B$2:$B$995,Index!$F$2:$F$995,"Not Found"))*B38),"")}
C39: {=IF(NOT(ISBLANK($A39)), (_xlfn.XLOOKUP($A39,Index!$B$2:$B$995,Index!$C$2:$C$995,"Not Found")),"")} | D39: {=IF(NOT(ISBLANK(A39)), (_xlfn.XLOOKUP($A39,Index!$B$2:B$995,Index!$A$2:$A$995,"Not Found")),"")} | E39: {=IF(NOT(ISBLANK($A39)), (_xlfn.XLOOKUP($A39,Index!$B$2:$B$995,Index!$D$2:$D$995,"Not Found")),"")} | F39: {=IF(NOT(ISBLANK($A39)), (_xlfn.XLOOKUP($A39,Index!$B$2:$B$995,Index!$E$2:$E$995,"Not Found")),"")} | G39: {=IF(NOT(ISBLANK(A39)), ((_xlfn.XLOOKUP(A39,Index!$B$2:$B$995,Index!$F$2:$F$995,"Not Found"))*B39),"")}
... C77: {=IF(NOT(ISBLANK($A77)), (_xlfn.XLOOKUP($A77,Index!$B$2:$B$995,Index!$C$2:$C$995,"Not Found")),"")} | D77: {=IF(NOT(ISBLANK(A77)), (_xlfn.XLOOKUP($A77,Index!$B$2:B$995,Index!$A$2:$A$995,"Not Found")),"")} | E77: {=IF(NOT(ISBLANK($A77)), (_xlfn.XLOOKUP($A77,Index!$B$2:$B$995,Index!$D$2:$D$995,"Not Found")),"")} | F77: {=IF(NOT(ISBLANK($A77)), (_xlfn.XLOOKUP($A77,Index!$B$2:$B$995,Index!$E$2:$E$995,"Not Found")),"")} | G77: {=IF(NOT(ISBLANK(A77)), ((_xlfn.XLOOKUP(A77,Index!$B$2:$B$995,Index!$F$2:$F$995,"Not Found"))*B77),"")}

Sheet R T3-1
A1: Card | B1: Quantity | C1: Type | D1: ID | E1: Stage / Rarity | F1: Remaining Evo | G1: Feature Weight | I1: Card Total | K1: Type | L1: Num | M1: Basic | N1: S1 Max | O1: S1 Mid | P1: S2 | Q1: No Evolve
A2: G Energy | B2: 21 | C2: {=IF(NOT(ISBLANK($A2)), (_xlfn.XLOOKUP($A2,Index!$B$2:$B$995,Index!$C$2:$C$995,"Not Found")),"")} -> Energy | D2: {=IF(NOT(ISBLANK(A2)), (_xlfn.XLOOKUP($A2,Index!$B$2:B$995,Index!$A$2:$A$995,"Not Found")),"")} -> base1-99 | E2: {=IF(NOT(ISBLANK($A2)), (_xlfn.XLOOKUP($A2,Index!$B$2:$B$995,Index!$D$2:$D$995,"Not Found")),"")} | F2: {=IF(NOT(ISBLANK($A2)), (_xlfn.XLOOKUP($A2,Index!$B$2:$B$995,Index!$E$2:$E$995,"Not Found")),"")} | G2: {=IF(NOT(ISBLANK(A2)), ((_xlfn.XLOOKUP(A2,Index!$B$2:$B$995,Index!$F$2:$F$995,"Not Found"))*B2),"")} -> 0 | I2: =SUM(B2:B38) -> 60 | K2: G | L2: =IF(NOT(ISBLANK(K2)), SUM(M2:P2), "") -> 21 | M2: =IF(NOT(ISBLANK($K2)), SUMIFS($B$2:$B$32, $E$2:$E$32, "B", $C$2:$C$32,$K2), "") -> 12 | N2: =IF(NOT(ISBLANK($K2)),SUMIFS($B$2:$B$32,$E$2:$E$32, "1", $C$2:$C$32,$K2,$F$2:$F$32,"N"), "") -> 4 | O2: =IF(NOT(ISBLANK($K2)),SUMIFS($B$2:$B$32,$E$2:$E$32, "1", $C$2:$C$32,$K2,$F$2:$F$32,"Y"), "") -> 3 | P2: =IF(NOT(ISBLANK($K2)),SUMIFS($B$2:$B$32,$E$2:$E$32, "2", $C$2:$C$32,$K2), "") -> 2 | Q2: =IF(NOT(ISBLANK($K2)),SUMIFS($B$2:$B$32,$E$2:$E$32, "B", $C$2:$C$32,$K2,$F$2:$F$32,"N"), "") -> 2
A3: Oddish R | B3: 4 | C3: {=IF(NOT(ISBLANK($A3)), (_xlfn.XLOOKUP($A3,Index!$B$2:$B$995,Index!$C$2:$C$995,"Not Found")),"")} -> G | D3: {=IF(NOT(ISBLANK(A3)), (_xlfn.XLOOKUP($A3,Index!$B$2:B$995,Index!$A$2:$A$995,"Not Found")),"")} -> base5-63 | E3: {=IF(NOT(ISBLANK($A3)), (_xlfn.XLOOKUP($A3,Index!$B$2:$B$995,Index!$D$2:$D$995,"Not Found")),"")} -> b | F3: {=IF(NOT(ISBLANK($A3)), (_xlfn.XLOOKUP($A3,Index!$B$2:$B$995,Index!$E$2:$E$995,"Not Found")),"")} -> y | G3: {=IF(NOT(ISBLANK(A3)), ((_xlfn.XLOOKUP(A3,Index!$B$2:$B$995,Index!$F$2:$F$995,"Not Found"))*B3),"")} -> 0 | K3: C | L3: =IF(NOT(ISBLANK(K3)), SUM(M3:P3), "") -> 0 | M3: =IF(NOT(ISBLANK($K3)), SUMIFS($B$2:$B$32, $E$2:$E$32, "B", $C$2:$C$32,$K3), "") -> 0 | N3: =IF(NOT(ISBLANK($K3)),SUMIFS($B$2:$B$32,$E$2:$E$32, "1", $C$2:$C$32,$K3,$F$2:$F$32,"N"), "") -> 0 | O3: =IF(NOT(ISBLANK($K3)),SUMIFS($B$2:$B$32,$E$2:$E$32, "1", $C$2:$C$32,$K3,$F$2:$F$32,"Y"), "") -> 0 | P3: =IF(NOT(ISBLANK($K3)),SUMIFS($B$2:$B$32,$E$2:$E$32, "2", $C$2:$C$32,$K3), "") -> 0 | Q3: =IF(NOT(ISBLANK($K3)),SUMIFS($B$2:$B$32,$E$2:$E$32, "B", $C$2:$C$32,$K3,$F$2:$F$32,"N"), "") -> 0
A4: Dark Gloom | B4: 3 | C4: {=IF(NOT(ISBLANK($A4)), (_xlfn.XLOOKUP($A4,Index!$B$2:$B$995,Index!$C$2:$C$995,"Not Found")),"")} -> G | D4: {=IF(NOT(ISBLANK(A4)), (_xlfn.XLOOKUP($A4,Index!$B$2:B$995,Index!$A$2:$A$995,"Not Found")),"")} -> base5-36 | E4: {=IF(NOT(ISBLANK($A4)), (_xlfn.XLOOKUP($A4,Index!$B$2:$B$995,Index!$D$2:$D$995,"Not Found")),"")} -> 1 | F4: {=IF(NOT(ISBLANK($A4)), (_xlfn.XLOOKUP($A4,Index!$B$2:$B$995,Index!$E$2:$E$995,"Not Found")),"")} -> y | G4: {=IF(NOT(ISBLANK(A4)), ((_xlfn.XLOOKUP(A4,Index!$B$2:$B$995,Index!$F$2:$F$995,"Not Found"))*B4),"")} -> 0 | L4: =IF(NOT(ISBLANK(K4)), SUM(M4:P4), "") | M4: =IF(NOT(ISBLANK($K4)), SUMIFS($B$2:$B$32, $E$2:$E$32, "B", $C$2:$C$32,$K4), "") | N4: =IF(NOT(ISBLANK($K4)),SUMIFS($B$2:$B$32,$E$2:$E$32, "1", $C$2:$C$32,$K4,$F$2:$F$32,"N"), "") | O4: =IF(NOT(ISBLANK($K4)),SUMIFS($B$2:$B$32,$E$2:$E$32, "1", $C$2:$C$32,$K4,$F$2:$F$32,"Y"), "") | P4: =IF(NOT(ISBLANK($K4)),SUMIFS($B$2:$B$32,$E$2:$E$32, "2", $C$2:$C$32,$K4), "") | Q4: =IF(NOT(ISBLANK($K4)),SUMIFS($B$2:$B$32,$E$2:$E$32, "B", $C$2:$C$32,$K4,$F$2:$F$32,"N"), "")
A5: Dark Vileplume | B5: 2 | C5: {=IF(NOT(ISBLANK($A5)), (_xlfn.XLOOKUP($A5,Index!$B$2:$B$995,Index!$C$2:$C$995,"Not Found")),"")} -> G | D5: {=IF(NOT(ISBLANK(A5)), (_xlfn.XLOOKUP($A5,Index!$B$2:B$995,Index!$A$2:$A$995,"Not Found")),"")} -> base5-13 | E5: {=IF(NOT(ISBLANK($A5)), (_xlfn.XLOOKUP($A5,Index!$B$2:$B$995,Index!$D$2:$D$995,"Not Found")),"")} -> 2 | F5: {=IF(NOT(ISBLANK($A5)), (_xlfn.XLOOKUP($A5,Index!$B$2:$B$995,Index!$E$2:$E$995,"Not Found")),"")} | G5: {=IF(NOT(ISBLANK(A5)), ((_xlfn.XLOOKUP(A5,Index!$B$2:$B$995,Index!$F$2:$F$995,"Not Found"))*B5),"")} -> 4 | L5: =IF(NOT(ISBLANK(K5)), SUM(M5:P5), "") | M5: =IF(NOT(ISBLANK($K5)), SUMIFS($B$2:$B$32, $E$2:$E$32, "B", $C$2:$C$32,$K5), "") | N5: =IF(NOT(ISBLANK($K5)),SUMIFS($B$2:$B$32,$E$2:$E$32, "1", $C$2:$C$32,$K5,$F$2:$F$32,"N"), "") | O5: =IF(NOT(ISBLANK($K5)),SUMIFS($B$2:$B$32,$E$2:$E$32, "1", $C$2:$C$32,$K5,$F$2:$F$32,"Y"), "") | P5: =IF(NOT(ISBLANK($K5)),SUMIFS($B$2:$B$32,$E$2:$E$32, "2", $C$2:$C$32,$K5), "") | Q5: =IF(NOT(ISBLANK($K5)),SUMIFS($B$2:$B$32,$E$2:$E$32, "B", $C$2:$C$32,$K5,$F$2:$F$32,"N"), "")
A6: Grimer R | B6: 3 | C6: {=IF(NOT(ISBLANK($A6)), (_xlfn.XLOOKUP($A6,Index!$B$2:$B$995,Index!$C$2:$C$995,"Not Found")),"")} -> G | D6: {=IF(NOT(ISBLANK(A6)), (_xlfn.XLOOKUP($A6,Index!$B$2:B$995,Index!$A$2:$A$995,"Not Found")),"")} -> base5-57 | E6: {=IF(NOT(ISBLANK($A6)), (_xlfn.XLOOKUP($A6,Index!$B$2:$B$995,Index!$D$2:$D$995,"Not Found")),"")} -> b | F6: {=IF(NOT(ISBLANK($A6)), (_xlfn.XLOOKUP($A6,Index!$B$2:$B$995,Index!$E$2:$E$995,"Not Found")),"")} -> y | G6: {=IF(NOT(ISBLANK(A6)), ((_xlfn.XLOOKUP(A6,Index!$B$2:$B$995,Index!$F$2:$F$995,"Not Found"))*B6),"")} -> 0 | L6: =IF(NOT(ISBLANK(K6)), SUM(M6:P6), "") | M6: =IF(NOT(ISBLANK($K6)), COUNTIFS($E$2:$E$32, "B", $C$2:$C$32,$K6), "") | N6: =IF(NOT(ISBLANK(K6)),COUNTIFS($E$2:$E$32, "1", $C$2:$C$32,$K6,$F$2:$F$32,"N"), "") | O6: =IF(NOT(ISBLANK($K6)),COUNTIFS($E$2:$E$32, "1", $C$2:$C$32,$K6,$F$2:$F$32,"Y"), "") | P6: =IF(NOT(ISBLANK($K6)),COUNTIFS($E$2:$E$32, "2", $C$2:$C$32,$K6), "") | Q6: =IF(NOT(ISBLANK($K6)),COUNTIFS($E$2:$E$32, "B", $C$2:$C$32,$K6,$F$2:$F$32,"N"), "")
A7: Dark Muk | B7: 2 | C7: {=IF(NOT(ISBLANK($A7)), (_xlfn.XLOOKUP($A7,Index!$B$2:$B$995,Index!$C$2:$C$995,"Not Found")),"")} -> G | D7: {=IF(NOT(ISBLANK(A7)), (_xlfn.XLOOKUP($A7,Index!$B$2:B$995,Index!$A$2:$A$995,"Not Found")),"")} -> base5-41 | E7: {=IF(NOT(ISBLANK($A7)), (_xlfn.XLOOKUP($A7,Index!$B$2:$B$995,Index!$D$2:$D$995,"Not Found")),"")} -> 1 | F7: {=IF(NOT(ISBLANK($A7)), (_xlfn.XLOOKUP($A7,Index!$B$2:$B$995,Index!$E$2:$E$995,"Not Found")),"")} -> n | G7: {=IF(NOT(ISBLANK(A7)), ((_xlfn.XLOOKUP(A7,Index!$B$2:$B$995,Index!$F$2:$F$995,"Not Found"))*B7),"")} -> 3 | K7: Total | L7: =SUM(L2:L6) -> 21 | M7: =SUM(M2:M6) -> 12 | N7: =SUM(N2:N6) -> 4 | O7: =SUM(O2:O6) -> 3 | P7: =SUM(P2:P6) -> 2 | Q7: =SUM(Q2:Q6) -> 2
A8: Koffing R | B8: 3 | C8: {=IF(NOT(ISBLANK($A8)), (_xlfn.XLOOKUP($A8,Index!$B$2:$B$995,Index!$C$2:$C$995,"Not Found")),"")} -> G | D8: {=IF(NOT(ISBLANK(A8)), (_xlfn.XLOOKUP($A8,Index!$B$2:B$995,Index!$A$2:$A$995,"Not Found")),"")} -> base5-58 | E8: {=IF(NOT(ISBLANK($A8)), (_xlfn.XLOOKUP($A8,Index!$B$2:$B$995,Index!$D$2:$D$995,"Not Found")),"")} -> b | F8: {=IF(NOT(ISBLANK($A8)), (_xlfn.XLOOKUP($A8,Index!$B$2:$B$995,Index!$E$2:$E$995,"Not Found")),"")} -> y | G8: {=IF(NOT(ISBLANK(A8)), ((_xlfn.XLOOKUP(A8,Index!$B$2:$B$995,Index!$F$2:$F$995,"Not Found"))*B8),"")} -> 0
A9: Dark Weezing NH | B9: 1 | C9: {=IF(NOT(ISBLANK($A9)), (_xlfn.XLOOKUP($A9,Index!$B$2:$B$995,Index!$C$2:$C$995,"Not Found")),"")} -> G | D9: {=IF(NOT(ISBLANK(A9)), (_xlfn.XLOOKUP($A9,Index!$B$2:B$995,Index!$A$2:$A$995,"Not Found")),"")} -> base5-31 | E9: {=IF(NOT(ISBLANK($A9)), (_xlfn.XLOOKUP($A9,Index!$B$2:$B$995,Index!$D$2:$D$995,"Not Found")),"")} -> 1 | F9: {=IF(NOT(ISBLANK($A9)), (_xlfn.XLOOKUP($A9,Index!$B$2:$B$995,Index!$E$2:$E$995,"Not Found")),"")} -> n | G9: {=IF(NOT(ISBLANK(A9)), ((_xlfn.XLOOKUP(A9,Index!$B$2:$B$995,Index!$F$2:$F$995,"Not Found"))*B9),"")} -> 2 | M9: Common | N9: Uncommon | O9: Rare
A10: Dark Weezing | B10: 1 | C10: {=IF(NOT(ISBLANK($A10)), (_xlfn.XLOOKUP($A10,Index!$B$2:$B$995,Index!$C$2:$C$995,"Not Found")),"")} -> G | D10: {=IF(NOT(ISBLANK(A10)), (_xlfn.XLOOKUP($A10,Index!$B$2:B$995,Index!$A$2:$A$995,"Not Found")),"")} -> base5-14 | E10: {=IF(NOT(ISBLANK($A10)), (_xlfn.XLOOKUP($A10,Index!$B$2:$B$995,Index!$D$2:$D$995,"Not Found")),"")} -> 1 | F10: {=IF(NOT(ISBLANK($A10)), (_xlfn.XLOOKUP($A10,Index!$B$2:$B$995,Index!$E$2:$E$995,"Not Found")),"")} -> n | G10: {=IF(NOT(ISBLANK(A10)), ((_xlfn.XLOOKUP(A10,Index!$B$2:$B$995,Index!$F$2:$F$995,"Not Found"))*B10),"")} -> 2 | K10: Trainer | L10: =SUM(M10:P10) -> 15 | M10: =IF(NOT(ISBLANK($K10)), SUMIFS($B$2:$B$32,$E$2:$E$32, "C", $C$2:$C$32,"T"), "") -> 8 | N10: =IF(NOT(ISBLANK($K10)), SUMIFS($B$2:$B$32,$E$2:$E$32, "U", $C$2:$C$32,"T"), "") -> 6 | O10: =IF(NOT(ISBLANK($K$2)), SUMIFS($B$2:$B$32,$E$2:$E$32, "R", $C$2:$C$32,"T"), "") -> 1
A11: Pinsir NH | B11: 1 | C11: {=IF(NOT(ISBLANK($A11)), (_xlfn.XLOOKUP($A11,Index!$B$2:$B$995,Index!$C$2:$C$995,"Not Found")),"")} -> G | D11: {=IF(NOT(ISBLANK(A11)), (_xlfn.XLOOKUP($A11,Index!$B$2:B$995,Index!$A$2:$A$995,"Not Found")),"")} -> base2-25 | E11: {=IF(NOT(ISBLANK($A11)), (_xlfn.XLOOKUP($A11,Index!$B$2:$B$995,Index!$D$2:$D$995,"Not Found")),"")} -> b | F11: {=IF(NOT(ISBLANK($A11)), (_xlfn.XLOOKUP($A11,Index!$B$2:$B$995,Index!$E$2:$E$995,"Not Found")),"")} -> n | G11: {=IF(NOT(ISBLANK(A11)), ((_xlfn.XLOOKUP(A11,Index!$B$2:$B$995,Index!$F$2:$F$995,"Not Found"))*B11),"")} -> 1 | K11: Energy | L11: =IF(NOT(ISBLANK($K$2)), SUMIFS($B$2:$B$32, $C$2:$C$32,"Energy"), "") -> 24
A12: Pinsir | B12: 1 | C12: {=IF(NOT(ISBLANK($A12)), (_xlfn.XLOOKUP($A12,Index!$B$2:$B$995,Index!$C$2:$C$995,"Not Found")),"")} -> G | D12: {=IF(NOT(ISBLANK(A12)), (_xlfn.XLOOKUP($A12,Index!$B$2:B$995,Index!$A$2:$A$995,"Not Found")),"")} -> base2-9 | E12: {=IF(NOT(ISBLANK($A12)), (_xlfn.XLOOKUP($A12,Index!$B$2:$B$995,Index!$D$2:$D$995,"Not Found")),"")} -> b | F12: {=IF(NOT(ISBLANK($A12)), (_xlfn.XLOOKUP($A12,Index!$B$2:$B$995,Index!$E$2:$E$995,"Not Found")),"")} -> n | G12: {=IF(NOT(ISBLANK(A12)), ((_xlfn.XLOOKUP(A12,Index!$B$2:$B$995,Index!$F$2:$F$995,"Not Found"))*B12),"")} -> 1 | K12: Pokemon | L12: =L7 -> 21
A13: Sleep! | B13: 2 | C13: {=IF(NOT(ISBLANK($A13)), (_xlfn.XLOOKUP($A13,Index!$B$2:$B$995,Index!$C$2:$C$995,"Not Found")),"")} -> T | D13: {=IF(NOT(ISBLANK(A13)), (_xlfn.XLOOKUP($A13,Index!$B$2:B$995,Index!$A$2:$A$995,"Not Found")),"")} -> base5-79 | E13: {=IF(NOT(ISBLANK($A13)), (_xlfn.XLOOKUP($A13,Index!$B$2:$B$995,Index!$D$2:$D$995,"Not Found")),"")} -> c | F13: {=IF(NOT(ISBLANK($A13)), (_xlfn.XLOOKUP($A13,Index!$B$2:$B$995,Index!$E$2:$E$995,"Not Found")),"")} | G13: {=IF(NOT(ISBLANK(A13)), ((_xlfn.XLOOKUP(A13,Index!$B$2:$B$995,Index!$F$2:$F$995,"Not Found"))*B13),"")} -> #VALUE!
A14: Bill | B14: 3 | C14: {=IF(NOT(ISBLANK($A14)), (_xlfn.XLOOKUP($A14,Index!$B$2:$B$995,Index!$C$2:$C$995,"Not Found")),"")} -> T | D14: {=IF(NOT(ISBLANK(A14)), (_xlfn.XLOOKUP($A14,Index!$B$2:B$995,Index!$A$2:$A$995,"Not Found")),"")} -> base1-91 | E14: {=IF(NOT(ISBLANK($A14)), (_xlfn.XLOOKUP($A14,Index!$B$2:$B$995,Index!$D$2:$D$995,"Not Found")),"")} -> c | F14: {=IF(NOT(ISBLANK($A14)), (_xlfn.XLOOKUP($A14,Index!$B$2:$B$995,Index!$E$2:$E$995,"Not Found")),"")} | G14: {=IF(NOT(ISBLANK(A14)), ((_xlfn.XLOOKUP(A14,Index!$B$2:$B$995,Index!$F$2:$F$995,"Not Found"))*B14),"")} -> #VALUE!
A15: Professor Oak | B15: 2 | C15: {=IF(NOT(ISBLANK($A15)), (_xlfn.XLOOKUP($A15,Index!$B$2:$B$995,Index!$C$2:$C$995,"Not Found")),"")} -> T | D15: {=IF(NOT(ISBLANK(A15)), (_xlfn.XLOOKUP($A15,Index!$B$2:B$995,Index!$A$2:$A$995,"Not Found")),"")} -> base1-88 | E15: {=IF(NOT(ISBLANK($A15)), (_xlfn.XLOOKUP($A15,Index!$B$2:$B$995,Index!$D$2:$D$995,"Not Found")),"")} -> u | F15: {=IF(NOT(ISBLANK($A15)), (_xlfn.XLOOKUP($A15,Index!$B$2:$B$995,Index!$E$2:$E$995,"Not Found")),"")} | G15: {=IF(NOT(ISBLANK(A15)), ((_xlfn.XLOOKUP(A15,Index!$B$2:$B$995,Index!$F$2:$F$995,"Not Found"))*B15),"")} -> #VALUE! | K15: Feature Weight:
A16: Pokemon Trader | B16: 1 | C16: {=IF(NOT(ISBLANK($A16)), (_xlfn.XLOOKUP($A16,Index!$B$2:$B$995,Index!$C$2:$C$995,"Not Found")),"")} -> T | D16: {=IF(NOT(ISBLANK(A16)), (_xlfn.XLOOKUP($A16,Index!$B$2:B$995,Index!$A$2:$A$995,"Not Found")),"")} -> base1-77 | E16: {=IF(NOT(ISBLANK($A16)), (_xlfn.XLOOKUP($A16,Index!$B$2:$B$995,Index!$D$2:$D$995,"Not Found")),"")} -> r | F16: {=IF(NOT(ISBLANK($A16)), (_xlfn.XLOOKUP($A16,Index!$B$2:$B$995,Index!$E$2:$E$995,"Not Found")),"")} | G16: {=IF(NOT(ISBLANK(A16)), ((_xlfn.XLOOKUP(A16,Index!$B$2:$B$995,Index!$F$2:$F$995,"Not Found"))*B16),"")} -> #VALUE! | K16: =K2 -> G | L16: =IF(NOT(ISBLANK($K2)), SUMIFS($G$2:$G$32, $C$2:$C$32,$K2), "") -> 13
A17: Defender | B17: 2 | C17: {=IF(NOT(ISBLANK($A17)), (_xlfn.XLOOKUP($A17,Index!$B$2:$B$995,Index!$C$2:$C$995,"Not Found")),"")} -> T | D17: {=IF(NOT(ISBLANK(A17)), (_xlfn.XLOOKUP($A17,Index!$B$2:B$995,Index!$A$2:$A$995,"Not Found")),"")} -> base1-80 | E17: {=IF(NOT(ISBLANK($A17)), (_xlfn.XLOOKUP($A17,Index!$B$2:$B$995,Index!$D$2:$D$995,"Not Found")),"")} -> u | F17: {=IF(NOT(ISBLANK($A17)), (_xlfn.XLOOKUP($A17,Index!$B$2:$B$995,Index!$E$2:$E$995,"Not Found")),"")} | G17: {=IF(NOT(ISBLANK(A17)), ((_xlfn.XLOOKUP(A17,Index!$B$2:$B$995,Index!$F$2:$F$995,"Not Found"))*B17),"")} -> #VALUE! | K17: =K3 -> C | L17: =IF(NOT(ISBLANK($K3)), SUMIFS($G$2:$G$32, $C$2:$C$32,$K3), "") -> 0
A18: Potion | B18: 2 | C18: {=IF(NOT(ISBLANK($A18)), (_xlfn.XLOOKUP($A18,Index!$B$2:$B$995,Index!$C$2:$C$995,"Not Found")),"")} -> T | D18: {=IF(NOT(ISBLANK(A18)), (_xlfn.XLOOKUP($A18,Index!$B$2:B$995,Index!$A$2:$A$995,"Not Found")),"")} -> base1-94 | E18: {=IF(NOT(ISBLANK($A18)), (_xlfn.XLOOKUP($A18,Index!$B$2:$B$995,Index!$D$2:$D$995,"Not Found")),"")} -> c | F18: {=IF(NOT(ISBLANK($A18)), (_xlfn.XLOOKUP($A18,Index!$B$2:$B$995,Index!$E$2:$E$995,"Not Found")),"")} | G18: {=IF(NOT(ISBLANK(A18)), ((_xlfn.XLOOKUP(A18,Index!$B$2:$B$995,Index!$F$2:$F$995,"Not Found"))*B18),"")} -> #VALUE! | K18: =K4 | L18: =IF(NOT(ISBLANK($K4)), SUMIFS($G$2:$G$32, $C$2:$C$32,$K4), "")
A19: Potion Energy | B19: 2 | C19: {=IF(NOT(ISBLANK($A19)), (_xlfn.XLOOKUP($A19,Index!$B$2:$B$995,Index!$C$2:$C$995,"Not Found")),"")} -> Energy | D19: {=IF(NOT(ISBLANK(A19)), (_xlfn.XLOOKUP($A19,Index!$B$2:B$995,Index!$A$2:$A$995,"Not Found")),"")} -> base5-82 | E19: {=IF(NOT(ISBLANK($A19)), (_xlfn.XLOOKUP($A19,Index!$B$2:$B$995,Index!$D$2:$D$995,"Not Found")),"")} | F19: {=IF(NOT(ISBLANK($A19)), (_xlfn.XLOOKUP($A19,Index!$B$2:$B$995,Index!$E$2:$E$995,"Not Found")),"")} | G19: {=IF(NOT(ISBLANK(A19)), ((_xlfn.XLOOKUP(A19,Index!$B$2:$B$995,Index!$F$2:$F$995,"Not Found"))*B19),"")} -> 0 | K19: =K5 | L19: =IF(NOT(ISBLANK($K5)), SUMIFS($G$2:$G$32, $C$2:$C$32,$K5), "")
A20: Full Heal | B20: 1 | C20: {=IF(NOT(ISBLANK($A20)), (_xlfn.XLOOKUP($A20,Index!$B$2:$B$995,Index!$C$2:$C$995,"Not Found")),"")} -> T | D20: {=IF(NOT(ISBLANK(A20)), (_xlfn.XLOOKUP($A20,Index!$B$2:B$995,Index!$A$2:$A$995,"Not Found")),"")} -> base1-82 | E20: {=IF(NOT(ISBLANK($A20)), (_xlfn.XLOOKUP($A20,Index!$B$2:$B$995,Index!$D$2:$D$995,"Not Found")),"")} -> u | F20: {=IF(NOT(ISBLANK($A20)), (_xlfn.XLOOKUP($A20,Index!$B$2:$B$995,Index!$E$2:$E$995,"Not Found")),"")} | G20: {=IF(NOT(ISBLANK(A20)), ((_xlfn.XLOOKUP(A20,Index!$B$2:$B$995,Index!$F$2:$F$995,"Not Found"))*B20),"")} -> #VALUE! | K20: =K6
A21: Energy Removal | B21: 1 | C21: {=IF(NOT(ISBLANK($A21)), (_xlfn.XLOOKUP($A21,Index!$B$2:$B$995,Index!$C$2:$C$995,"Not Found")),"")} -> T | D21: {=IF(NOT(ISBLANK(A21)), (_xlfn.XLOOKUP($A21,Index!$B$2:B$995,Index!$A$2:$A$995,"Not Found")),"")} -> base1-92 | E21: {=IF(NOT(ISBLANK($A21)), (_xlfn.XLOOKUP($A21,Index!$B$2:$B$995,Index!$D$2:$D$995,"Not Found")),"")} -> c | F21: {=IF(NOT(ISBLANK($A21)), (_xlfn.XLOOKUP($A21,Index!$B$2:$B$995,Index!$E$2:$E$995,"Not Found")),"")} | G21: {=IF(NOT(ISBLANK(A21)), ((_xlfn.XLOOKUP(A21,Index!$B$2:$B$995,Index!$F$2:$F$995,"Not Found"))*B21),"")} -> #VALUE! | K21: Total: | L21: =SUM(L15:L19) -> 13
A22: Full Heal Energy | B22: 1 | C22: {=IF(NOT(ISBLANK($A22)), (_xlfn.XLOOKUP($A22,Index!$B$2:$B$995,Index!$C$2:$C$995,"Not Found")),"")} -> Energy | D22: {=IF(NOT(ISBLANK(A22)), (_xlfn.XLOOKUP($A22,Index!$B$2:B$995,Index!$A$2:$A$995,"Not Found")),"")} -> base5-81 | E22: {=IF(NOT(ISBLANK($A22)), (_xlfn.XLOOKUP($A22,Index!$B$2:$B$995,Index!$D$2:$D$995,"Not Found")),"")} | F22: {=IF(NOT(ISBLANK($A22)), (_xlfn.XLOOKUP($A22,Index!$B$2:$B$995,Index!$E$2:$E$995,"Not Found")),"")} | G22: {=IF(NOT(ISBLANK(A22)), ((_xlfn.XLOOKUP(A22,Index!$B$2:$B$995,Index!$F$2:$F$995,"Not Found"))*B22),"")} -> 0
A23: Nightly Garbage Run | B23: 1 | C23: {=IF(NOT(ISBLANK($A23)), (_xlfn.XLOOKUP($A23,Index!$B$2:$B$995,Index!$C$2:$C$995,"Not Found")),"")} -> T | D23: {=IF(NOT(ISBLANK(A23)), (_xlfn.XLOOKUP($A23,Index!$B$2:B$995,Index!$A$2:$A$995,"Not Found")),"")} -> base5-77 | E23: {=IF(NOT(ISBLANK($A23)), (_xlfn.XLOOKUP($A23,Index!$B$2:$B$995,Index!$D$2:$D$995,"Not Found")),"")} -> u | F23: {=IF(NOT(ISBLANK($A23)), (_xlfn.XLOOKUP($A23,Index!$B$2:$B$995,Index!$E$2:$E$995,"Not Found")),"")} | G23: {=IF(NOT(ISBLANK(A23)), ((_xlfn.XLOOKUP(A23,Index!$B$2:$B$995,Index!$F$2:$F$995,"Not Found"))*B23),"")} -> #VALUE!
C24: {=IF(NOT(ISBLANK($A24)), (_xlfn.XLOOKUP($A24,Index!$B$2:$B$995,Index!$C$2:$C$995,"Not Found")),"")} | D24: {=IF(NOT(ISBLANK(A24)), (_xlfn.XLOOKUP($A24,Index!$B$2:B$995,Index!$A$2:$A$995,"Not Found")),"")} | E24: {=IF(NOT(ISBLANK($A24)), (_xlfn.XLOOKUP($A24,Index!$B$2:$B$995,Index!$D$2:$D$995,"Not Found")),"")} | F24: {=IF(NOT(ISBLANK($A24)), (_xlfn.XLOOKUP($A24,Index!$B$2:$B$995,Index!$E$2:$E$995,"Not Found")),"")} | G24: {=IF(NOT(ISBLANK(A24)), ((_xlfn.XLOOKUP(A24,Index!$B$2:$B$995,Index!$F$2:$F$995,"Not Found"))*B24),"")} | K24: Cover Card: | L24: Dark Vileplume
C25: {=IF(NOT(ISBLANK($A25)), (_xlfn.XLOOKUP($A25,Index!$B$2:$B$995,Index!$C$2:$C$995,"Not Found")),"")} | D25: {=IF(NOT(ISBLANK(A25)), (_xlfn.XLOOKUP($A25,Index!$B$2:B$995,Index!$A$2:$A$995,"Not Found")),"")} | E25: {=IF(NOT(ISBLANK($A25)), (_xlfn.XLOOKUP($A25,Index!$B$2:$B$995,Index!$D$2:$D$995,"Not Found")),"")} | F25: {=IF(NOT(ISBLANK($A25)), (_xlfn.XLOOKUP($A25,Index!$B$2:$B$995,Index!$E$2:$E$995,"Not Found")),"")} | G25: {=IF(NOT(ISBLANK(A25)), ((_xlfn.XLOOKUP(A25,Index!$B$2:$B$995,Index!$F$2:$F$995,"Not Found"))*B25),"")}
C26: {=IF(NOT(ISBLANK($A26)), (_xlfn.XLOOKUP($A26,Index!$B$2:$B$995,Index!$C$2:$C$995,"Not Found")),"")} | D26: {=IF(NOT(ISBLANK(A26)), (_xlfn.XLOOKUP($A26,Index!$B$2:B$995,Index!$A$2:$A$995,"Not Found")),"")} | E26: {=IF(NOT(ISBLANK($A26)), (_xlfn.XLOOKUP($A26,Index!$B$2:$B$995,Index!$D$2:$D$995,"Not Found")),"")} | F26: {=IF(NOT(ISBLANK($A26)), (_xlfn.XLOOKUP($A26,Index!$B$2:$B$995,Index!$E$2:$E$995,"Not Found")),"")} | G26: {=IF(NOT(ISBLANK(A26)), ((_xlfn.XLOOKUP(A26,Index!$B$2:$B$995,Index!$F$2:$F$995,"Not Found"))*B26),"")}
C27: {=IF(NOT(ISBLANK($A27)), (_xlfn.XLOOKUP($A27,Index!$B$2:$B$995,Index!$C$2:$C$995,"Not Found")),"")} | D27: {=IF(NOT(ISBLANK(A27)), (_xlfn.XLOOKUP($A27,Index!$B$2:B$995,Index!$A$2:$A$995,"Not Found")),"")} | E27: {=IF(NOT(ISBLANK($A27)), (_xlfn.XLOOKUP($A27,Index!$B$2:$B$995,Index!$D$2:$D$995,"Not Found")),"")} | F27: {=IF(NOT(ISBLANK($A27)), (_xlfn.XLOOKUP($A27,Index!$B$2:$B$995,Index!$E$2:$E$995,"Not Found")),"")} | G27: {=IF(NOT(ISBLANK(A27)), ((_xlfn.XLOOKUP(A27,Index!$B$2:$B$995,Index!$F$2:$F$995,"Not Found"))*B27),"")}
C28: {=IF(NOT(ISBLANK($A28)), (_xlfn.XLOOKUP($A28,Index!$B$2:$B$995,Index!$C$2:$C$995,"Not Found")),"")} | D28: {=IF(NOT(ISBLANK(A28)), (_xlfn.XLOOKUP($A28,Index!$B$2:B$995,Index!$A$2:$A$995,"Not Found")),"")} | E28: {=IF(NOT(ISBLANK($A28)), (_xlfn.XLOOKUP($A28,Index!$B$2:$B$995,Index!$D$2:$D$995,"Not Found")),"")} | F28: {=IF(NOT(ISBLANK($A28)), (_xlfn.XLOOKUP($A28,Index!$B$2:$B$995,Index!$E$2:$E$995,"Not Found")),"")} | G28: {=IF(NOT(ISBLANK(A28)), ((_xlfn.XLOOKUP(A28,Index!$B$2:$B$995,Index!$F$2:$F$995,"Not Found"))*B28),"")}
C29: {=IF(NOT(ISBLANK($A29)), (_xlfn.XLOOKUP($A29,Index!$B$2:$B$995,Index!$C$2:$C$995,"Not Found")),"")} | D29: {=IF(NOT(ISBLANK(A29)), (_xlfn.XLOOKUP($A29,Index!$B$2:B$995,Index!$A$2:$A$995,"Not Found")),"")} | E29: {=IF(NOT(ISBLANK($A29)), (_xlfn.XLOOKUP($A29,Index!$B$2:$B$995,Index!$D$2:$D$995,"Not Found")),"")} | F29: {=IF(NOT(ISBLANK($A29)), (_xlfn.XLOOKUP($A29,Index!$B$2:$B$995,Index!$E$2:$E$995,"Not Found")),"")} | G29: {=IF(NOT(ISBLANK(A29)), ((_xlfn.XLOOKUP(A29,Index!$B$2:$B$995,Index!$F$2:$F$995,"Not Found"))*B29),"")}
C30: {=IF(NOT(ISBLANK($A30)), (_xlfn.XLOOKUP($A30,Index!$B$2:$B$995,Index!$C$2:$C$995,"Not Found")),"")} | D30: {=IF(NOT(ISBLANK(A30)), (_xlfn.XLOOKUP($A30,Index!$B$2:B$995,Index!$A$2:$A$995,"Not Found")),"")} | E30: {=IF(NOT(ISBLANK($A30)), (_xlfn.XLOOKUP($A30,Index!$B$2:$B$995,Index!$D$2:$D$995,"Not Found")),"")} | F30: {=IF(NOT(ISBLANK($A30)), (_xlfn.XLOOKUP($A30,Index!$B$2:$B$995,Index!$E$2:$E$995,"Not Found")),"")} | G30: {=IF(NOT(ISBLANK(A30)), ((_xlfn.XLOOKUP(A30,Index!$B$2:$B$995,Index!$F$2:$F$995,"Not Found"))*B30),"")}
C31: {=IF(NOT(ISBLANK($A31)), (_xlfn.XLOOKUP($A31,Index!$B$2:$B$995,Index!$C$2:$C$995,"Not Found")),"")} | D31: {=IF(NOT(ISBLANK(A31)), (_xlfn.XLOOKUP($A31,Index!$B$2:B$995,Index!$A$2:$A$995,"Not Found")),"")} | E31: {=IF(NOT(ISBLANK($A31)), (_xlfn.XLOOKUP($A31,Index!$B$2:$B$995,Index!$D$2:$D$995,"Not Found")),"")} | F31: {=IF(NOT(ISBLANK($A31)), (_xlfn.XLOOKUP($A31,Index!$B$2:$B$995,Index!$E$2:$E$995,"Not Found")),"")} | G31: {=IF(NOT(ISBLANK(A31)), ((_xlfn.XLOOKUP(A31,Index!$B$2:$B$995,Index!$F$2:$F$995,"Not Found"))*B31),"")}
C32: {=IF(NOT(ISBLANK($A32)), (_xlfn.XLOOKUP($A32,Index!$B$2:$B$995,Index!$C$2:$C$995,"Not Found")),"")} | D32: {=IF(NOT(ISBLANK(A32)), (_xlfn.XLOOKUP($A32,Index!$B$2:B$995,Index!$A$2:$A$995,"Not Found")),"")} | E32: {=IF(NOT(ISBLANK($A32)), (_xlfn.XLOOKUP($A32,Index!$B$2:$B$995,Index!$D$2:$D$995,"Not Found")),"")} | F32: {=IF(NOT(ISBLANK($A32)), (_xlfn.XLOOKUP($A32,Index!$B$2:$B$995,Index!$E$2:$E$995,"Not Found")),"")} | G32: {=IF(NOT(ISBLANK(A32)), ((_xlfn.XLOOKUP(A32,Index!$B$2:$B$995,Index!$F$2:$F$995,"Not Found"))*B32),"")}
C33: {=IF(NOT(ISBLANK($A33)), (_xlfn.XLOOKUP($A33,Index!$B$2:$B$995,Index!$C$2:$C$995,"Not Found")),"")} | D33: {=IF(NOT(ISBLANK(A33)), (_xlfn.XLOOKUP($A33,Index!$B$2:B$995,Index!$A$2:$A$995,"Not Found")),"")} | E33: {=IF(NOT(ISBLANK($A33)), (_xlfn.XLOOKUP($A33,Index!$B$2:$B$995,Index!$D$2:$D$995,"Not Found")),"")} | F33: {=IF(NOT(ISBLANK($A33)), (_xlfn.XLOOKUP($A33,Index!$B$2:$B$995,Index!$E$2:$E$995,"Not Found")),"")} | G33: {=IF(NOT(ISBLANK(A33)), ((_xlfn.XLOOKUP(A33,Index!$B$2:$B$995,Index!$F$2:$F$995,"Not Found"))*B33),"")}
C34: {=IF(NOT(ISBLANK($A34)), (_xlfn.XLOOKUP($A34,Index!$B$2:$B$995,Index!$C$2:$C$995,"Not Found")),"")} | D34: {=IF(NOT(ISBLANK(A34)), (_xlfn.XLOOKUP($A34,Index!$B$2:B$995,Index!$A$2:$A$995,"Not Found")),"")} | E34: {=IF(NOT(ISBLANK($A34)), (_xlfn.XLOOKUP($A34,Index!$B$2:$B$995,Index!$D$2:$D$995,"Not Found")),"")} | F34: {=IF(NOT(ISBLANK($A34)), (_xlfn.XLOOKUP($A34,Index!$B$2:$B$995,Index!$E$2:$E$995,"Not Found")),"")} | G34: {=IF(NOT(ISBLANK(A34)), ((_xlfn.XLOOKUP(A34,Index!$B$2:$B$995,Index!$F$2:$F$995,"Not Found"))*B34),"")}
C35: {=IF(NOT(ISBLANK($A35)), (_xlfn.XLOOKUP($A35,Index!$B$2:$B$995,Index!$C$2:$C$995,"Not Found")),"")} | D35: {=IF(NOT(ISBLANK(A35)), (_xlfn.XLOOKUP($A35,Index!$B$2:B$995,Index!$A$2:$A$995,"Not Found")),"")} | E35: {=IF(NOT(ISBLANK($A35)), (_xlfn.XLOOKUP($A35,Index!$B$2:$B$995,Index!$D$2:$D$995,"Not Found")),"")} | F35: {=IF(NOT(ISBLANK($A35)), (_xlfn.XLOOKUP($A35,Index!$B$2:$B$995,Index!$E$2:$E$995,"Not Found")),"")} | G35: {=IF(NOT(ISBLANK(A35)), ((_xlfn.XLOOKUP(A35,Index!$B$2:$B$995,Index!$F$2:$F$995,"Not Found"))*B35),"")}
C36: {=IF(NOT(ISBLANK($A36)), (_xlfn.XLOOKUP($A36,Index!$B$2:$B$995,Index!$C$2:$C$995,"Not Found")),"")} | D36: {=IF(NOT(ISBLANK(A36)), (_xlfn.XLOOKUP($A36,Index!$B$2:B$995,Index!$A$2:$A$995,"Not Found")),"")} | E36: {=IF(NOT(ISBLANK($A36)), (_xlfn.XLOOKUP($A36,Index!$B$2:$B$995,Index!$D$2:$D$995,"Not Found")),"")} | F36: {=IF(NOT(ISBLANK($A36)), (_xlfn.XLOOKUP($A36,Index!$B$2:$B$995,Index!$E$2:$E$995,"Not Found")),"")} | G36: {=IF(NOT(ISBLANK(A36)), ((_xlfn.XLOOKUP(A36,Index!$B$2:$B$995,Index!$F$2:$F$995,"Not Found"))*B36),"")}
... C77: {=IF(NOT(ISBLANK($A77)), (_xlfn.XLOOKUP($A77,Index!$B$2:$B$995,Index!$C$2:$C$995,"Not Found")),"")} | D77: {=IF(NOT(ISBLANK(A77)), (_xlfn.XLOOKUP($A77,Index!$B$2:B$995,Index!$A$2:$A$995,"Not Found")),"")} | E77: {=IF(NOT(ISBLANK($A77)), (_xlfn.XLOOKUP($A77,Index!$B$2:$B$995,Index!$D$2:$D$995,"Not Found")),"")} | F77: {=IF(NOT(ISBLANK($A77)), (_xlfn.XLOOKUP($A77,Index!$B$2:$B$995,Index!$E$2:$E$995,"Not Found")),"")} | G77: {=IF(NOT(ISBLANK(A77)), ((_xlfn.XLOOKUP(A77,Index!$B$2:$B$995,Index!$F$2:$F$995,"Not Found"))*B77),"")}

Sheet R T3-2
A1: Card | B1: Quantity | C1: Type | D1: ID | E1: Stage / Rarity | F1: Remaining Evo | G1: Feature Weight | I1: Card Total | K1: Type | L1: Num | M1: Basic | N1: S1 Max | O1: S1 Mid | P1: S2 | Q1: No Evolve
A2: Machop R | B2: 4 | C2: {=IF(NOT(ISBLANK($A2)), (_xlfn.XLOOKUP($A2,Index!$B$2:$B$995,Index!$C$2:$C$995,"Not Found")),"")} -> F | D2: {=IF(NOT(ISBLANK(A2)), (_xlfn.XLOOKUP($A2,Index!$B$2:B$995,Index!$A$2:$A$995,"Not Found")),"")} -> base5-59 | E2: {=IF(NOT(ISBLANK($A2)), (_xlfn.XLOOKUP($A2,Index!$B$2:$B$995,Index!$D$2:$D$995,"Not Found")),"")} -> b | F2: {=IF(NOT(ISBLANK($A2)), (_xlfn.XLOOKUP($A2,Index!$B$2:$B$995,Index!$E$2:$E$995,"Not Found")),"")} -> y | G2: {=IF(NOT(ISBLANK(A2)), ((_xlfn.XLOOKUP(A2,Index!$B$2:$B$995,Index!$F$2:$F$995,"Not Found"))*B2),"")} -> 0 | I2: =SUM(B2:B38) -> 60 | K2: F | L2: =IF(NOT(ISBLANK(K2)), SUM(M2:P2), "") -> 21 | M2: =IF(NOT(ISBLANK($K2)), SUMIFS($B$2:$B$32, $E$2:$E$32, "B", $C$2:$C$32,$K2), "") -> 12 | N2: =IF(NOT(ISBLANK($K2)),SUMIFS($B$2:$B$32,$E$2:$E$32, "1", $C$2:$C$32,$K2,$F$2:$F$32,"N"), "") -> 4 | O2: =IF(NOT(ISBLANK($K2)),SUMIFS($B$2:$B$32,$E$2:$E$32, "1", $C$2:$C$32,$K2,$F$2:$F$32,"Y"), "") -> 3 | P2: =IF(NOT(ISBLANK($K2)),SUMIFS($B$2:$B$32,$E$2:$E$32, "2", $C$2:$C$32,$K2), "") -> 2 | Q2: =IF(NOT(ISBLANK($K2)),SUMIFS($B$2:$B$32,$E$2:$E$32, "B", $C$2:$C$32,$K2,$F$2:$F$32,"N"), "") -> 2
A3: Dark Machoke | B3: 3 | C3: {=IF(NOT(ISBLANK($A3)), (_xlfn.XLOOKUP($A3,Index!$B$2:$B$995,Index!$C$2:$C$995,"Not Found")),"")} -> F | D3: {=IF(NOT(ISBLANK(A3)), (_xlfn.XLOOKUP($A3,Index!$B$2:B$995,Index!$A$2:$A$995,"Not Found")),"")} -> base5-40 | E3: {=IF(NOT(ISBLANK($A3)), (_xlfn.XLOOKUP($A3,Index!$B$2:$B$995,Index!$D$2:$D$995,"Not Found")),"")} -> 1 | F3: {=IF(NOT(ISBLANK($A3)), (_xlfn.XLOOKUP($A3,Index!$B$2:$B$995,Index!$E$2:$E$995,"Not Found")),"")} -> y | G3: {=IF(NOT(ISBLANK(A3)), ((_xlfn.XLOOKUP(A3,Index!$B$2:$B$995,Index!$F$2:$F$995,"Not Found"))*B3),"")} -> 1.5 | K3: C | L3: =IF(NOT(ISBLANK(K3)), SUM(M3:P3), "") -> 1 | M3: =IF(NOT(ISBLANK($K3)), SUMIFS($B$2:$B$32, $E$2:$E$32, "B", $C$2:$C$32,$K3), "") -> 1 | N3: =IF(NOT(ISBLANK($K3)),SUMIFS($B$2:$B$32,$E$2:$E$32, "1", $C$2:$C$32,$K3,$F$2:$F$32,"N"), "") -> 0 | O3: =IF(NOT(ISBLANK($K3)),SUMIFS($B$2:$B$32,$E$2:$E$32, "1", $C$2:$C$32,$K3,$F$2:$F$32,"Y"), "") -> 0 | P3: =IF(NOT(ISBLANK($K3)),SUMIFS($B$2:$B$32,$E$2:$E$32, "2", $C$2:$C$32,$K3), "") -> 0 | Q3: =IF(NOT(ISBLANK($K3)),SUMIFS($B$2:$B$32,$E$2:$E$32, "B", $C$2:$C$32,$K3,$F$2:$F$32,"N"), "") -> 1
A4: Dark Machamp | B4: 2 | C4: {=IF(NOT(ISBLANK($A4)), (_xlfn.XLOOKUP($A4,Index!$B$2:$B$995,Index!$C$2:$C$995,"Not Found")),"")} -> F | D4: {=IF(NOT(ISBLANK(A4)), (_xlfn.XLOOKUP($A4,Index!$B$2:B$995,Index!$A$2:$A$995,"Not Found")),"")} -> base5-10 | E4: {=IF(NOT(ISBLANK($A4)), (_xlfn.XLOOKUP($A4,Index!$B$2:$B$995,Index!$D$2:$D$995,"Not Found")),"")} -> 2 | F4: {=IF(NOT(ISBLANK($A4)), (_xlfn.XLOOKUP($A4,Index!$B$2:$B$995,Index!$E$2:$E$995,"Not Found")),"")} | G4: {=IF(NOT(ISBLANK(A4)), ((_xlfn.XLOOKUP(A4,Index!$B$2:$B$995,Index!$F$2:$F$995,"Not Found"))*B4),"")} -> 4 | L4: =IF(NOT(ISBLANK(K4)), SUM(M4:P4), "") | M4: =IF(NOT(ISBLANK($K4)), SUMIFS($B$2:$B$32, $E$2:$E$32, "B", $C$2:$C$32,$K4), "") | N4: =IF(NOT(ISBLANK($K4)),SUMIFS($B$2:$B$32,$E$2:$E$32, "1", $C$2:$C$32,$K4,$F$2:$F$32,"N"), "") | O4: =IF(NOT(ISBLANK($K4)),SUMIFS($B$2:$B$32,$E$2:$E$32, "1", $C$2:$C$32,$K4,$F$2:$F$32,"Y"), "") | P4: =IF(NOT(ISBLANK($K4)),SUMIFS($B$2:$B$32,$E$2:$E$32, "2", $C$2:$C$32,$K4), "") | Q4: =IF(NOT(ISBLANK($K4)),SUMIFS($B$2:$B$32,$E$2:$E$32, "B", $C$2:$C$32,$K4,$F$2:$F$32,"N"), "")
A5: Mankey R | B5: 3 | C5: {=IF(NOT(ISBLANK($A5)), (_xlfn.XLOOKUP($A5,Index!$B$2:$B$995,Index!$C$2:$C$995,"Not Found")),"")} -> F | D5: {=IF(NOT(ISBLANK(A5)), (_xlfn.XLOOKUP($A5,Index!$B$2:B$995,Index!$A$2:$A$995,"Not Found")),"")} -> base5-61 | E5: {=IF(NOT(ISBLANK($A5)), (_xlfn.XLOOKUP($A5,Index!$B$2:$B$995,Index!$D$2:$D$995,"Not Found")),"")} -> b | F5: {=IF(NOT(ISBLANK($A5)), (_xlfn.XLOOKUP($A5,Index!$B$2:$B$995,Index!$E$2:$E$995,"Not Found")),"")} -> y | G5: {=IF(NOT(ISBLANK(A5)), ((_xlfn.XLOOKUP(A5,Index!$B$2:$B$995,Index!$F$2:$F$995,"Not Found"))*B5),"")} -> 0 | L5: =IF(NOT(ISBLANK(K5)), SUM(M5:P5), "") | M5: =IF(NOT(ISBLANK($K5)), SUMIFS($B$2:$B$32, $E$2:$E$32, "B", $C$2:$C$32,$K5), "") | N5: =IF(NOT(ISBLANK($K5)),SUMIFS($B$2:$B$32,$E$2:$E$32, "1", $C$2:$C$32,$K5,$F$2:$F$32,"N"), "") | O5: =IF(NOT(ISBLANK($K5)),SUMIFS($B$2:$B$32,$E$2:$E$32, "1", $C$2:$C$32,$K5,$F$2:$F$32,"Y"), "") | P5: =IF(NOT(ISBLANK($K5)),SUMIFS($B$2:$B$32,$E$2:$E$32, "2", $C$2:$C$32,$K5), "") | Q5: =IF(NOT(ISBLANK($K5)),SUMIFS($B$2:$B$32,$E$2:$E$32, "B", $C$2:$C$32,$K5,$F$2:$F$32,"N"), "")
A6: Dark Primeape | B6: 2 | C6: {=IF(NOT(ISBLANK($A6)), (_xlfn.XLOOKUP($A6,Index!$B$2:$B$995,Index!$C$2:$C$995,"Not Found")),"")} -> F | D6: {=IF(NOT(ISBLANK(A6)), (_xlfn.XLOOKUP($A6,Index!$B$2:B$995,Index!$A$2:$A$995,"Not Found")),"")} -> base5-43 | E6: {=IF(NOT(ISBLANK($A6)), (_xlfn.XLOOKUP($A6,Index!$B$2:$B$995,Index!$D$2:$D$995,"Not Found")),"")} -> 1 | F6: {=IF(NOT(ISBLANK($A6)), (_xlfn.XLOOKUP($A6,Index!$B$2:$B$995,Index!$E$2:$E$995,"Not Found")),"")} -> n | G6: {=IF(NOT(ISBLANK(A6)), ((_xlfn.XLOOKUP(A6,Index!$B$2:$B$995,Index!$F$2:$F$995,"Not Found"))*B6),"")} -> 2 | L6: =IF(NOT(ISBLANK(K6)), SUM(M6:P6), "") | M6: =IF(NOT(ISBLANK($K6)), COUNTIFS($E$2:$E$32, "B", $C$2:$C$32,$K6), "") | N6: =IF(NOT(ISBLANK(K6)),COUNTIFS($E$2:$E$32, "1", $C$2:$C$32,$K6,$F$2:$F$32,"N"), "") | O6: =IF(NOT(ISBLANK($K6)),COUNTIFS($E$2:$E$32, "1", $C$2:$C$32,$K6,$F$2:$F$32,"Y"), "") | P6: =IF(NOT(ISBLANK($K6)),COUNTIFS($E$2:$E$32, "2", $C$2:$C$32,$K6), "") | Q6: =IF(NOT(ISBLANK($K6)),COUNTIFS($E$2:$E$32, "B", $C$2:$C$32,$K6,$F$2:$F$32,"N"), "")
A7: Diglett R | B7: 3 | C7: {=IF(NOT(ISBLANK($A7)), (_xlfn.XLOOKUP($A7,Index!$B$2:$B$995,Index!$C$2:$C$995,"Not Found")),"")} -> F | D7: {=IF(NOT(ISBLANK(A7)), (_xlfn.XLOOKUP($A7,Index!$B$2:B$995,Index!$A$2:$A$995,"Not Found")),"")} -> base5-52 | E7: {=IF(NOT(ISBLANK($A7)), (_xlfn.XLOOKUP($A7,Index!$B$2:$B$995,Index!$D$2:$D$995,"Not Found")),"")} -> b | F7: {=IF(NOT(ISBLANK($A7)), (_xlfn.XLOOKUP($A7,Index!$B$2:$B$995,Index!$E$2:$E$995,"Not Found")),"")} -> y | G7: {=IF(NOT(ISBLANK(A7)), ((_xlfn.XLOOKUP(A7,Index!$B$2:$B$995,Index!$F$2:$F$995,"Not Found"))*B7),"")} -> 0 | K7: Total | L7: =SUM(L2:L6) -> 22 | M7: =SUM(M2:M6) -> 13 | N7: =SUM(N2:N6) -> 4 | O7: =SUM(O2:O6) -> 3 | P7: =SUM(P2:P6) -> 2 | Q7: =SUM(Q2:Q6) -> 3
A8: Dark Dugtrio | B8: 2 | C8: {=IF(NOT(ISBLANK($A8)), (_xlfn.XLOOKUP($A8,Index!$B$2:$B$995,Index!$C$2:$C$995,"Not Found")),"")} -> F | D8: {=IF(NOT(ISBLANK(A8)), (_xlfn.XLOOKUP($A8,Index!$B$2:B$995,Index!$A$2:$A$995,"Not Found")),"")} -> base5-6 | E8: {=IF(NOT(ISBLANK($A8)), (_xlfn.XLOOKUP($A8,Index!$B$2:$B$995,Index!$D$2:$D$995,"Not Found")),"")} -> 1 | F8: {=IF(NOT(ISBLANK($A8)), (_xlfn.XLOOKUP($A8,Index!$B$2:$B$995,Index!$E$2:$E$995,"Not Found")),"")} -> n | G8: {=IF(NOT(ISBLANK(A8)), ((_xlfn.XLOOKUP(A8,Index!$B$2:$B$995,Index!$F$2:$F$995,"Not Found"))*B8),"")} -> 4
A9: Hitmonlee | B9: 2 | C9: {=IF(NOT(ISBLANK($A9)), (_xlfn.XLOOKUP($A9,Index!$B$2:$B$995,Index!$C$2:$C$995,"Not Found")),"")} -> F | D9: {=IF(NOT(ISBLANK(A9)), (_xlfn.XLOOKUP($A9,Index!$B$2:B$995,Index!$A$2:$A$995,"Not Found")),"")} -> base3-7 | E9: {=IF(NOT(ISBLANK($A9)), (_xlfn.XLOOKUP($A9,Index!$B$2:$B$995,Index!$D$2:$D$995,"Not Found")),"")} -> b | F9: {=IF(NOT(ISBLANK($A9)), (_xlfn.XLOOKUP($A9,Index!$B$2:$B$995,Index!$E$2:$E$995,"Not Found")),"")} -> n | G9: {=IF(NOT(ISBLANK(A9)), ((_xlfn.XLOOKUP(A9,Index!$B$2:$B$995,Index!$F$2:$F$995,"Not Found"))*B9),"")} -> 2 | M9: Common | N9: Uncommon | O9: Rare
A10: Lickitung | B10: 1 | C10: {=IF(NOT(ISBLANK($A10)), (_xlfn.XLOOKUP($A10,Index!$B$2:$B$995,Index!$C$2:$C$995,"Not Found")),"")} -> C | D10: {=IF(NOT(ISBLANK(A10)), (_xlfn.XLOOKUP($A10,Index!$B$2:B$995,Index!$A$2:$A$995,"Not Found")),"")} -> base2-38 | E10: {=IF(NOT(ISBLANK($A10)), (_xlfn.XLOOKUP($A10,Index!$B$2:$B$995,Index!$D$2:$D$995,"Not Found")),"")} -> b | F10: {=IF(NOT(ISBLANK($A10)), (_xlfn.XLOOKUP($A10,Index!$B$2:$B$995,Index!$E$2:$E$995,"Not Found")),"")} -> n | G10: {=IF(NOT(ISBLANK(A10)), ((_xlfn.XLOOKUP(A10,Index!$B$2:$B$995,Index!$F$2:$F$995,"Not Found"))*B10),"")} -> 0.5 | K10: Trainer | L10: =SUM(M10:P10) -> 14 | M10: =IF(NOT(ISBLANK($K10)), SUMIFS($B$2:$B$32,$E$2:$E$32, "C", $C$2:$C$32,"T"), "") -> 8 | N10: =IF(NOT(ISBLANK($K10)), SUMIFS($B$2:$B$32,$E$2:$E$32, "U", $C$2:$C$32,"T"), "") -> 4 | O10: =IF(NOT(ISBLANK($K$2)), SUMIFS($B$2:$B$32,$E$2:$E$32, "R", $C$2:$C$32,"T"), "") -> 2
A11: F Energy | B11: 22 | C11: {=IF(NOT(ISBLANK($A11)), (_xlfn.XLOOKUP($A11,Index!$B$2:$B$995,Index!$C$2:$C$995,"Not Found")),"")} -> Energy | D11: {=IF(NOT(ISBLANK(A11)), (_xlfn.XLOOKUP($A11,Index!$B$2:B$995,Index!$A$2:$A$995,"Not Found")),"")} -> base1-97 | E11: {=IF(NOT(ISBLANK($A11)), (_xlfn.XLOOKUP($A11,Index!$B$2:$B$995,Index!$D$2:$D$995,"Not Found")),"")} | F11: {=IF(NOT(ISBLANK($A11)), (_xlfn.XLOOKUP($A11,Index!$B$2:$B$995,Index!$E$2:$E$995,"Not Found")),"")} | G11: {=IF(NOT(ISBLANK(A11)), ((_xlfn.XLOOKUP(A11,Index!$B$2:$B$995,Index!$F$2:$F$995,"Not Found"))*B11),"")} -> 0 | K11: Energy | L11: =IF(NOT(ISBLANK($K$2)), SUMIFS($B$2:$B$32, $C$2:$C$32,"Energy"), "") -> 24
A12: Full Heal Energy | B12: 1 | C12: {=IF(NOT(ISBLANK($A12)), (_xlfn.XLOOKUP($A12,Index!$B$2:$B$995,Index!$C$2:$C$995,"Not Found")),"")} -> Energy | D12: {=IF(NOT(ISBLANK(A12)), (_xlfn.XLOOKUP($A12,Index!$B$2:B$995,Index!$A$2:$A$995,"Not Found")),"")} -> base5-81 | E12: {=IF(NOT(ISBLANK($A12)), (_xlfn.XLOOKUP($A12,Index!$B$2:$B$995,Index!$D$2:$D$995,"Not Found")),"")} | F12: {=IF(NOT(ISBLANK($A12)), (_xlfn.XLOOKUP($A12,Index!$B$2:$B$995,Index!$E$2:$E$995,"Not Found")),"")} | G12: {=IF(NOT(ISBLANK(A12)), ((_xlfn.XLOOKUP(A12,Index!$B$2:$B$995,Index!$F$2:$F$995,"Not Found"))*B12),"")} -> 0 | K12: Pokemon | L12: =L7 -> 22
A13: Potion Energy | B13: 1 | C13: {=IF(NOT(ISBLANK($A13)), (_xlfn.XLOOKUP($A13,Index!$B$2:$B$995,Index!$C$2:$C$995,"Not Found")),"")} -> Energy | D13: {=IF(NOT(ISBLANK(A13)), (_xlfn.XLOOKUP($A13,Index!$B$2:B$995,Index!$A$2:$A$995,"Not Found")),"")} -> base5-82 | E13: {=IF(NOT(ISBLANK($A13)), (_xlfn.XLOOKUP($A13,Index!$B$2:$B$995,Index!$D$2:$D$995,"Not Found")),"")} | F13: {=IF(NOT(ISBLANK($A13)), (_xlfn.XLOOKUP($A13,Index!$B$2:$B$995,Index!$E$2:$E$995,"Not Found")),"")} | G13: {=IF(NOT(ISBLANK(A13)), ((_xlfn.XLOOKUP(A13,Index!$B$2:$B$995,Index!$F$2:$F$995,"Not Found"))*B13),"")} -> 0
A14: Bill | B14: 3 | C14: {=IF(NOT(ISBLANK($A14)), (_xlfn.XLOOKUP($A14,Index!$B$2:$B$995,Index!$C$2:$C$995,"Not Found")),"")} -> T | D14: {=IF(NOT(ISBLANK(A14)), (_xlfn.XLOOKUP($A14,Index!$B$2:B$995,Index!$A$2:$A$995,"Not Found")),"")} -> base1-91 | E14: {=IF(NOT(ISBLANK($A14)), (_xlfn.XLOOKUP($A14,Index!$B$2:$B$995,Index!$D$2:$D$995,"Not Found")),"")} -> c | F14: {=IF(NOT(ISBLANK($A14)), (_xlfn.XLOOKUP($A14,Index!$B$2:$B$995,Index!$E$2:$E$995,"Not Found")),"")} | G14: {=IF(NOT(ISBLANK(A14)), ((_xlfn.XLOOKUP(A14,Index!$B$2:$B$995,Index!$F$2:$F$995,"Not Found"))*B14),"")} -> #VALUE!
A15: Professor Oak | B15: 2 | C15: {=IF(NOT(ISBLANK($A15)), (_xlfn.XLOOKUP($A15,Index!$B$2:$B$995,Index!$C$2:$C$995,"Not Found")),"")} -> T | D15: {=IF(NOT(ISBLANK(A15)), (_xlfn.XLOOKUP($A15,Index!$B$2:B$995,Index!$A$2:$A$995,"Not Found")),"")} -> base1-88 | E15: {=IF(NOT(ISBLANK($A15)), (_xlfn.XLOOKUP($A15,Index!$B$2:$B$995,Index!$D$2:$D$995,"Not Found")),"")} -> u | F15: {=IF(NOT(ISBLANK($A15)), (_xlfn.XLOOKUP($A15,Index!$B$2:$B$995,Index!$E$2:$E$995,"Not Found")),"")} | G15: {=IF(NOT(ISBLANK(A15)), ((_xlfn.XLOOKUP(A15,Index!$B$2:$B$995,Index!$F$2:$F$995,"Not Found"))*B15),"")} -> #VALUE! | K15: Feature Weight:
A16: Potion | B16: 2 | C16: {=IF(NOT(ISBLANK($A16)), (_xlfn.XLOOKUP($A16,Index!$B$2:$B$995,Index!$C$2:$C$995,"Not Found")),"")} -> T | D16: {=IF(NOT(ISBLANK(A16)), (_xlfn.XLOOKUP($A16,Index!$B$2:B$995,Index!$A$2:$A$995,"Not Found")),"")} -> base1-94 | E16: {=IF(NOT(ISBLANK($A16)), (_xlfn.XLOOKUP($A16,Index!$B$2:$B$995,Index!$D$2:$D$995,"Not Found")),"")} -> c | F16: {=IF(NOT(ISBLANK($A16)), (_xlfn.XLOOKUP($A16,Index!$B$2:$B$995,Index!$E$2:$E$995,"Not Found")),"")} | G16: {=IF(NOT(ISBLANK(A16)), ((_xlfn.XLOOKUP(A16,Index!$B$2:$B$995,Index!$F$2:$F$995,"Not Found"))*B16),"")} -> #VALUE! | K16: =K2 -> F | L16: =IF(NOT(ISBLANK($K2)), SUMIFS($G$2:$G$32, $C$2:$C$32,$K2), "") -> 13.5
A17: Item Finder | B17: 1 | C17: {=IF(NOT(ISBLANK($A17)), (_xlfn.XLOOKUP($A17,Index!$B$2:$B$995,Index!$C$2:$C$995,"Not Found")),"")} -> T | D17: {=IF(NOT(ISBLANK(A17)), (_xlfn.XLOOKUP($A17,Index!$B$2:B$995,Index!$A$2:$A$995,"Not Found")),"")} -> base1-74 | E17: {=IF(NOT(ISBLANK($A17)), (_xlfn.XLOOKUP($A17,Index!$B$2:$B$995,Index!$D$2:$D$995,"Not Found")),"")} -> r | F17: {=IF(NOT(ISBLANK($A17)), (_xlfn.XLOOKUP($A17,Index!$B$2:$B$995,Index!$E$2:$E$995,"Not Found")),"")} | G17: {=IF(NOT(ISBLANK(A17)), ((_xlfn.XLOOKUP(A17,Index!$B$2:$B$995,Index!$F$2:$F$995,"Not Found"))*B17),"")} -> #VALUE! | K17: =K3 -> C | L17: =IF(NOT(ISBLANK($K3)), SUMIFS($G$2:$G$32, $C$2:$C$32,$K3), "") -> 0.5
A18: Rocket's Sneak Attack | B18: 1 | C18: {=IF(NOT(ISBLANK($A18)), (_xlfn.XLOOKUP($A18,Index!$B$2:$B$995,Index!$C$2:$C$995,"Not Found")),"")} -> T | D18: {=IF(NOT(ISBLANK(A18)), (_xlfn.XLOOKUP($A18,Index!$B$2:B$995,Index!$A$2:$A$995,"Not Found")),"")} -> base5-16 | E18: {=IF(NOT(ISBLANK($A18)), (_xlfn.XLOOKUP($A18,Index!$B$2:$B$995,Index!$D$2:$D$995,"Not Found")),"")} -> r | F18: {=IF(NOT(ISBLANK($A18)), (_xlfn.XLOOKUP($A18,Index!$B$2:$B$995,Index!$E$2:$E$995,"Not Found")),"")} | G18: {=IF(NOT(ISBLANK(A18)), ((_xlfn.XLOOKUP(A18,Index!$B$2:$B$995,Index!$F$2:$F$995,"Not Found"))*B18),"")} -> #VALUE! | K18: =K4 | L18: =IF(NOT(ISBLANK($K4)), SUMIFS($G$2:$G$32, $C$2:$C$32,$K4), "")
A19: Switch | B19: 1 | C19: {=IF(NOT(ISBLANK($A19)), (_xlfn.XLOOKUP($A19,Index!$B$2:$B$995,Index!$C$2:$C$995,"Not Found")),"")} -> T | D19: {=IF(NOT(ISBLANK(A19)), (_xlfn.XLOOKUP($A19,Index!$B$2:B$995,Index!$A$2:$A$995,"Not Found")),"")} -> base1-95 | E19: {=IF(NOT(ISBLANK($A19)), (_xlfn.XLOOKUP($A19,Index!$B$2:$B$995,Index!$D$2:$D$995,"Not Found")),"")} -> c | F19: {=IF(NOT(ISBLANK($A19)), (_xlfn.XLOOKUP($A19,Index!$B$2:$B$995,Index!$E$2:$E$995,"Not Found")),"")} | G19: {=IF(NOT(ISBLANK(A19)), ((_xlfn.XLOOKUP(A19,Index!$B$2:$B$995,Index!$F$2:$F$995,"Not Found"))*B19),"")} -> #VALUE! | K19: =K5 | L19: =IF(NOT(ISBLANK($K5)), SUMIFS($G$2:$G$32, $C$2:$C$32,$K5), "")
A20: Sleep! | B20: 2 | C20: {=IF(NOT(ISBLANK($A20)), (_xlfn.XLOOKUP($A20,Index!$B$2:$B$995,Index!$C$2:$C$995,"Not Found")),"")} -> T | D20: {=IF(NOT(ISBLANK(A20)), (_xlfn.XLOOKUP($A20,Index!$B$2:B$995,Index!$A$2:$A$995,"Not Found")),"")} -> base5-79 | E20: {=IF(NOT(ISBLANK($A20)), (_xlfn.XLOOKUP($A20,Index!$B$2:$B$995,Index!$D$2:$D$995,"Not Found")),"")} -> c | F20: {=IF(NOT(ISBLANK($A20)), (_xlfn.XLOOKUP($A20,Index!$B$2:$B$995,Index!$E$2:$E$995,"Not Found")),"")} | G20: {=IF(NOT(ISBLANK(A20)), ((_xlfn.XLOOKUP(A20,Index!$B$2:$B$995,Index!$F$2:$F$995,"Not Found"))*B20),"")} -> #VALUE! | K20: =K6
A21: Defender | B21: 2 | C21: {=IF(NOT(ISBLANK($A21)), (_xlfn.XLOOKUP($A21,Index!$B$2:$B$995,Index!$C$2:$C$995,"Not Found")),"")} -> T | D21: {=IF(NOT(ISBLANK(A21)), (_xlfn.XLOOKUP($A21,Index!$B$2:B$995,Index!$A$2:$A$995,"Not Found")),"")} -> base1-80 | E21: {=IF(NOT(ISBLANK($A21)), (_xlfn.XLOOKUP($A21,Index!$B$2:$B$995,Index!$D$2:$D$995,"Not Found")),"")} -> u | F21: {=IF(NOT(ISBLANK($A21)), (_xlfn.XLOOKUP($A21,Index!$B$2:$B$995,Index!$E$2:$E$995,"Not Found")),"")} | G21: {=IF(NOT(ISBLANK(A21)), ((_xlfn.XLOOKUP(A21,Index!$B$2:$B$995,Index!$F$2:$F$995,"Not Found"))*B21),"")} -> #VALUE! | K21: Total: | L21: =SUM(L15:L19) -> 14
C22: {=IF(NOT(ISBLANK($A22)), (_xlfn.XLOOKUP($A22,Index!$B$2:$B$995,Index!$C$2:$C$995,"Not Found")),"")} | D22: {=IF(NOT(ISBLANK(A22)), (_xlfn.XLOOKUP($A22,Index!$B$2:B$995,Index!$A$2:$A$995,"Not Found")),"")} | E22: {=IF(NOT(ISBLANK($A22)), (_xlfn.XLOOKUP($A22,Index!$B$2:$B$995,Index!$D$2:$D$995,"Not Found")),"")} | F22: {=IF(NOT(ISBLANK($A22)), (_xlfn.XLOOKUP($A22,Index!$B$2:$B$995,Index!$E$2:$E$995,"Not Found")),"")} | G22: {=IF(NOT(ISBLANK(A22)), ((_xlfn.XLOOKUP(A22,Index!$B$2:$B$995,Index!$F$2:$F$995,"Not Found"))*B22),"")}
C23: {=IF(NOT(ISBLANK($A23)), (_xlfn.XLOOKUP($A23,Index!$B$2:$B$995,Index!$C$2:$C$995,"Not Found")),"")} | D23: {=IF(NOT(ISBLANK(A23)), (_xlfn.XLOOKUP($A23,Index!$B$2:B$995,Index!$A$2:$A$995,"Not Found")),"")} | E23: {=IF(NOT(ISBLANK($A23)), (_xlfn.XLOOKUP($A23,Index!$B$2:$B$995,Index!$D$2:$D$995,"Not Found")),"")} | F23: {=IF(NOT(ISBLANK($A23)), (_xlfn.XLOOKUP($A23,Index!$B$2:$B$995,Index!$E$2:$E$995,"Not Found")),"")} | G23: {=IF(NOT(ISBLANK(A23)), ((_xlfn.XLOOKUP(A23,Index!$B$2:$B$995,Index!$F$2:$F$995,"Not Found"))*B23),"")}
C24: {=IF(NOT(ISBLANK($A24)), (_xlfn.XLOOKUP($A24,Index!$B$2:$B$995,Index!$C$2:$C$995,"Not Found")),"")} | D24: {=IF(NOT(ISBLANK(A24)), (_xlfn.XLOOKUP($A24,Index!$B$2:B$995,Index!$A$2:$A$995,"Not Found")),"")} | E24: {=IF(NOT(ISBLANK($A24)), (_xlfn.XLOOKUP($A24,Index!$B$2:$B$995,Index!$D$2:$D$995,"Not Found")),"")} | F24: {=IF(NOT(ISBLANK($A24)), (_xlfn.XLOOKUP($A24,Index!$B$2:$B$995,Index!$E$2:$E$995,"Not Found")),"")} | G24: {=IF(NOT(ISBLANK(A24)), ((_xlfn.XLOOKUP(A24,Index!$B$2:$B$995,Index!$F$2:$F$995,"Not Found"))*B24),"")} | K24: Cover Card: | L24: Dark Machamp
C25: {=IF(NOT(ISBLANK($A25)), (_xlfn.XLOOKUP($A25,Index!$B$2:$B$995,Index!$C$2:$C$995,"Not Found")),"")} | D25: {=IF(NOT(ISBLANK(A25)), (_xlfn.XLOOKUP($A25,Index!$B$2:B$995,Index!$A$2:$A$995,"Not Found")),"")} | E25: {=IF(NOT(ISBLANK($A25)), (_xlfn.XLOOKUP($A25,Index!$B$2:$B$995,Index!$D$2:$D$995,"Not Found")),"")} | F25: {=IF(NOT(ISBLANK($A25)), (_xlfn.XLOOKUP($A25,Index!$B$2:$B$995,Index!$E$2:$E$995,"Not Found")),"")} | G25: {=IF(NOT(ISBLANK(A25)), ((_xlfn.XLOOKUP(A25,Index!$B$2:$B$995,Index!$F$2:$F$995,"Not Found"))*B25),"")}
C26: {=IF(NOT(ISBLANK($A26)), (_xlfn.XLOOKUP($A26,Index!$B$2:$B$995,Index!$C$2:$C$995,"Not Found")),"")} | D26: {=IF(NOT(ISBLANK(A26)), (_xlfn.XLOOKUP($A26,Index!$B$2:B$995,Index!$A$2:$A$995,"Not Found")),"")} | E26: {=IF(NOT(ISBLANK($A26)), (_xlfn.XLOOKUP($A26,Index!$B$2:$B$995,Index!$D$2:$D$995,"Not Found")),"")} | F26: {=IF(NOT(ISBLANK($A26)), (_xlfn.XLOOKUP($A26,Index!$B$2:$B$995,Index!$E$2:$E$995,"Not Found")),"")} | G26: {=IF(NOT(ISBLANK(A26)), ((_xlfn.XLOOKUP(A26,Index!$B$2:$B$995,Index!$F$2:$F$995,"Not Found"))*B26),"")}
C27: {=IF(NOT(ISBLANK($A27)), (_xlfn.XLOOKUP($A27,Index!$B$2:$B$995,Index!$C$2:$C$995,"Not Found")),"")} | D27: {=IF(NOT(ISBLANK(A27)), (_xlfn.XLOOKUP($A27,Index!$B$2:B$995,Index!$A$2:$A$995,"Not Found")),"")} | E27: {=IF(NOT(ISBLANK($A27)), (_xlfn.XLOOKUP($A27,Index!$B$2:$B$995,Index!$D$2:$D$995,"Not Found")),"")} | F27: {=IF(NOT(ISBLANK($A27)), (_xlfn.XLOOKUP($A27,Index!$B$2:$B$995,Index!$E$2:$E$995,"Not Found")),"")} | G27: {=IF(NOT(ISBLANK(A27)), ((_xlfn.XLOOKUP(A27,Index!$B$2:$B$995,Index!$F$2:$F$995,"Not Found"))*B27),"")}
C28: {=IF(NOT(ISBLANK($A28)), (_xlfn.XLOOKUP($A28,Index!$B$2:$B$995,Index!$C$2:$C$995,"Not Found")),"")} | D28: {=IF(NOT(ISBLANK(A28)), (_xlfn.XLOOKUP($A28,Index!$B$2:B$995,Index!$A$2:$A$995,"Not Found")),"")} | E28: {=IF(NOT(ISBLANK($A28)), (_xlfn.XLOOKUP($A28,Index!$B$2:$B$995,Index!$D$2:$D$995,"Not Found")),"")} | F28: {=IF(NOT(ISBLANK($A28)), (_xlfn.XLOOKUP($A28,Index!$B$2:$B$995,Index!$E$2:$E$995,"Not Found")),"")} | G28: {=IF(NOT(ISBLANK(A28)), ((_xlfn.XLOOKUP(A28,Index!$B$2:$B$995,Index!$F$2:$F$995,"Not Found"))*B28),"")}
